Workbook
Name \a: #REF!
Name \i: #REF!
Name \j: #REF!
Name \k: #REF!
Name \p: #REF!
Name ________abr01: #REF!
Name ________PIB04: #REF!
Name ________PIB05: #REF!
Name ________PIB06: #REF!
Name ________PIB90: #REF!
Name ________PIB91: #REF!
Name ________PIB92: #REF!
Name ________PIB93: #REF!
Name ________PIB94: #REF!
Name ________PIB95: #REF!
Name ________PIB96: #REF!
Name ________PIB97: #REF!
Name ________PIB98: #REF!
Name ________PIB99: #REF!
Name _______PIB01: #REF!
Name _______PIB02: #REF!
Name _______PIB03: #REF!
Name ______abr01: #REF!
Name ______PIB01: #REF!
Name ______PIB02: #REF!
Name ______PIB03: #REF!
Name ______PIB04: #REF!
Name ______PIB05: #REF!
Name ______PIB06: #REF!
Name ______PIB90: #REF!
Name ______PIB91: #REF!
Name ______PIB92: #REF!
Name ______PIB93: #REF!
Name ______PIB94: #REF!
Name ______PIB95: #REF!
Name ______PIB96: #REF!
Name ______PIB97: #REF!
Name ______PIB98: #REF!
Name ______PIB99: #REF!
Name _____abr01: #REF!
Name _____PIB01: #REF!
Name _____PIB02: #REF!
Name _____PIB03: #REF!
Name _____PIB04: #REF!
Name _____PIB05: #REF!
Name _____PIB06: #REF!
Name _____PIB90: #REF!
Name _____PIB91: #REF!
Name _____PIB92: #REF!
Name _____PIB93: #REF!
Name _____PIB94: #REF!
Name _____PIB95: #REF!
Name _____PIB96: #REF!
Name _____PIB97: #REF!
Name _____PIB98: #REF!
Name _____PIB99: #REF!
Name ____abr01: #REF!
Name ____PIB01: #REF!
Name ____PIB02: #REF!
Name ____PIB03: #REF!

Sheet Datos_Trimestrales
A2: Plantilla de datos para estimación de modelo FISLAC - Brasil
A4: Nota: por favor completar la información con la mayor cantidad de datos históricos disponibles
C7: Sector Real | P7: Sector Monetario | V7: Balanza de Pagos | AJ7: Sector Fiscal
B8: Años | C8: PIB Nominal | D8: PIB Real | E8: PIB potencial | F8: Brecha del PIB | G8: Crecimiento PIB Real | H8: Inversión Privada | I8: Inversión Privada % del PIB | J8: Consumo Privado | K8: Consumo Privado % del PIB | L8: Importaciones | M8: Importaciones % del PIB | N8: Exportaciones | O8: Exportaciones % del PIB | P8: Inflación (%) | Q8: Tasa de Política Monetaria (%) | R8: Tasa activa promedio (%) | S8: Tasa pasiva promedio (%) | T8: Tasa de Cambio (por Dólar) | U8: PIB nominal (USD) | V8: Saldo Cuenta Corriente (USD) | W8: Saldo Cuenta Corriente % del PIB | X8: Saldo Cuenta Capital (USD) | Y8: Saldo Cuenta Capital % del PIB | Z8: Saldo Cuenta financiera (USD) | AA8: Saldo Cuenta financiera % del PIB | AB8: Errores y omisiones (USD) | AC8: Errores y omisiones % del PIB | AD8: Reservas Internacionales Netas (USD) | AE8: Reservas Internacionales Netas % del PIB | AF8: Remesas Internacionales (USD) | AG8: Remesas Internacionales % del PIB | AH8: Inversión extranjera directa (USD) | AI8: Inversión extranjera directa % del PIB | AJ8: Ingreso Fiscal (Total) | AK8: Ingreso Fiscal (Total) % del PIB | AL8: Ingreso por Materias Primas | AM8: Ingreso por Materias Primas % del PIB | AN8: Ingreso Tributario | AO8: Ingreso Tributario % del PIB | AP8: Ingreso Impuestos Consumo | AQ8: Ingreso Impuestos Consumo % del PIB | AR8: Ingreso Impuestos Renta Laboral | AS8: Ingreso Impuestos Renta Laboral % del PIB | AT8: Ingreso Impuestos Renta de capital | AU8: Ingreso Impuestos Renta de capital % del PIB | AV8: Ingreso Impuestos Renta de Empresas | AW8: Ingreso Impuestos Renta de Empresas % del PIB | AX8: Ingreso Otros | AY8: Ingreso Otros % del PIB | AZ8: Gasto Público Total | BA8: Gasto Público Total % del PIB | BB8: Gasto Público Primario | BC8: Gasto Público Primario % del PIB | BD8: Gasto Corriente Primario | BE8: Gasto Corriente Primario % del PIB | BF8: Gasto en atención a desastres naturales | BG8: Gasto en atención a desastres naturales % del PIB | BH8: Gasto de Capital | BI8: Gasto de Capital % del PIB | BJ8: Inversión en adaptación al cambio climático | BK8: Inversión en adaptación al cambio climático % del PIB | BL8: Pago de Intereses | BM8: Pago de Intereses % del PIB | BN8: Balance Primario | BO8: Balance Primario % del PIB | BP8: Balance Total | BQ8: Balance Total % del PIB | BR8: Deuda Bruta (R$ Milhões) | BS8: Deuda Bruta % del PIB
B9: 1995Q1 | P9: 4.3297326 | S9: 70.61 | T9: 0.9056 | U9: 186146 | V9: -5711.0186 | W9: =V9/U9*100 -> -3.0680319 | X9: 1.7698813 | Y9: =X9/U9*100 -> 0.00095080277 | Z9: -5275.1774 | AA9: =Z9/U9*100 -> -2.8338924 | AB9: 434.07126 | AC9: =AB9/U9*100 -> 0.23318861 | AD9: 33742 | AE9: 5.5687403 | AH9: 519.413 | AI9: =AH9/U9*100 -> 0.27903527
B10: 1995Q2 | P10: 7.540996 | S10: 59.21 | T10: 0.9186 | U10: 192551 | V10: -6656.6475 | W10: =V10/U10*100 -> -3.4570828 | X10: 5.5771912 | Y10: =X10/U10*100 -> 0.0028964748 | Z10: -5946.1333 | AA10: =Z10/U10*100 -> -3.0880823 | AB10: 704.93699 | AC10: =AB10/U10*100 -> 0.36610404 | AD10: 33512 | AE10: 5.0244611 | AH10: 1008.784 | AI10: =AH10/U10*100 -> 0.52390484
B11: 1995Q3 | P11: 4.3965487 | S11: 43.93 | T11: 0.9543 | U11: 197782 | V11: -2421.4626 | W11: =V11/U11*100 -> -1.2243089 | X11: 4.659988 | Y11: =X11/U11*100 -> 0.0023561234 | Z11: -1169.2633 | AA11: =Z11/U11*100 -> -0.59118791 | AB11: 1247.5393 | AC11: =AB11/U11*100 -> 0.63076485 | AD11: 48713 | AE11: 6.7486167 | AH11: 1458.417 | AI11: =AH11/U11*100 -> 0.73738611
B12: 1995Q4 | P12: 4.5062071 | S12: 36.24 | T12: 0.96979 | U12: 194256 | V12: -3923.2933 | W12: =V12/U12*100 -> -2.019651 | X12: 6.0067728 | Y12: =X12/U12*100 -> 0.0030921942 | Z12: -4096.6753 | AA12: =Z12/U12*100 -> -2.1089054 | AB12: -179.38879 | AC12: =AB12/U12*100 -> -0.092346591 | AD12: 51840 | AE12: 6.7260472 | AH12: 1396.808 | AI12: =AH12/U12*100 -> 0.71905527
B13: 1996Q1 | C13: 189323.3 | H13: 35403.156 | I13: =H13/C13*100 -> 18.699841 | J13: 125685.05 | K13: =J13/C13*100 -> 66.386465 | L13: 14772.806 | M13: =L13/C13*100 -> 7.8029519 | N13: 12305.881 | O13: =N13/C13*100 -> 6.4999296 | P13: 2.7422583 | S13: 29.06 | T13: 0.9877 | U13: 199236 | V13: -3524.9065 | W13: =V13/U13*100 -> -1.7692116 | X13: 2.218255 | Y13: =X13/U13*100 -> 0.0011133806 | Z13: -4736.5343 | AA13: =Z13/U13*100 -> -2.3773486 | AB13: -1213.8461 | AC13: =AB13/U13*100 -> -0.60925039 | AD13: 55753 | AE13: 7.1129398 | AH13: 1624.533 | AI13: =AH13/U13*100 -> 0.81538126
B14: 1996Q2 | C14: 204610.73 | G14: 1.2870521 | H14: 39326.084 | I14: =H14/C14*100 -> 19.219952 | J14: 132510.86 | K14: =J14/C14*100 -> 64.762421 | L14: 17470.476 | M14: =L14/C14*100 -> 8.5383971 | N14: 14576.312 | O14: =N14/C14*100 -> 7.1239234 | P14: 3.714945 | S14: 24.55 | T14: 1.00285 | U14: 207745 | V14: -4314.8567 | W14: =V14/U14*100 -> -2.0769967 | X14: 21.296416 | Y14: =X14/U14*100 -> 0.010251229 | Z14: -4084.6676 | AA14: =Z14/U14*100 -> -1.966193 | AB14: 208.8927 | AC14: =AB14/U14*100 -> 0.10055246 | AD14: 59997 | AE14: 7.5088327 | AH14: 3731.371 | AI14: =AH14/U14*100 -> 1.7961304
B15: 1996Q3 | C15: 221513.23 | G15: 3.4533084 | H15: 41417.571 | I15: =H15/C15*100 -> 18.697561 | J15: 142658.33 | K15: =J15/C15*100 -> 64.401719 | L15: 20927.58 | M15: =L15/C15*100 -> 9.4475531 | N15: 15560.475 | O15: =N15/C15*100 -> 7.0246255 | P15: 1.7075967 | S15: 23.45 | T15: 1.02025 | U15: 224469 | V15: -5863.0108 | W15: =V15/U15*100 -> -2.6119468 | X15: 5.9151599 | Y15: =X15/U15*100 -> 0.002635179 | Z15: -5766.2799 | AA15: =Z15/U15*100 -> -2.5688536 | AB15: 90.815734 | AC15: =AB15/U15*100 -> 0.040458029 | AD15: 58775 | AE15: 7.118151 | AH15: 1472.075 | AI15: =AH15/U15*100 -> 0.65580325
B16: 1996Q4 | C16: 239316.35 | G16: -0.73454351 | H16: 43186.714 | I16: =H16/C16*100 -> 18.045869 | J16: 156087.5 | K16: =J16/C16*100 -> 65.222247 | L16: 22949.1 | M16: =L16/C16*100 -> 9.5894411 | N16: 15084.715 | O16: =N16/C16*100 -> 6.3032532 | P16: 1.0945657 | S16: 22.27 | T16: 1.03916 | U16: 219568 | V16: -10140.254 | W16: =V16/U16*100 -> -4.618275 | X16: 17.157526 | Y16: =X16/U16*100 -> 0.0078142198 | Z16: -11008.847 | AA16: =Z16/U16*100 -> -5.0138668 | AB16: -885.75071 | AC16: =AB16/U16*100 -> -0.4034061 | AD16: 60110 | AE16: 7.0633054 | AH16: 3963.708 | AI16: =AH16/U16*100 -> 1.8052303
B17: 1997Q1 | C17: 219117.05 | G17: 1.0080695 | H17: 42696.635 | I17: =H17/C17*100 -> 19.485766 | J17: 147807.94 | K17: =J17/C17*100 -> 67.456159 | L17: 19333.246 | M17: =L17/C17*100 -> 8.8232505 | N17: 13162.001 | O17: =N17/C17*100 -> 6.0068356 | P17: 2.2050409 | S17: 21.25 | T17: 1.05972 | U17: 208043 | V17: -4994.6999 | W17: =V17/U17*100 -> -2.4008017 | X17: 2.7593971 | Y17: =X17/U17*100 -> 0.001326359 | Z17: -5836.2198 | AA17: =Z17/U17*100 -> -2.805295 | AB17: -844.27926 | AC17: =AB17/U17*100 -> -0.40581959 | AD17: 58980 | AE17: 6.8595354 | AH17: 3019.1588 | AI17: =AH17/U17*100 -> 1.4512186
B18: 1997Q2 | C18: 232889.54 | G18: 0.54071695 | H18: 46189.458 | I18: =H18/C18*100 -> 19.833204 | J18: 154446.53 | K18: =J18/C18*100 -> 66.317503 | L18: 22570.114 | M18: =L18/C18*100 -> 9.6913383 | N18: 17401.764 | O18: =N18/C18*100 -> 7.4721106 | P18: 1.8402354 | S18: 20.12 | T18: 1.07642 | U18: 218405 | V18: -8235.726 | W18: =V18/U18*100 -> -3.7708505 | X18: 30.054631 | Y18: =X18/U18*100 -> 0.013760963 | Z18: -9155.7773 | AA18: =Z18/U18*100 -> -4.1921097 | AB18: -950.1059 | AC18: =AB18/U18*100 -> -0.43502022 | AD18: 57615 | AE18: 6.618724 | AH18: 4768.614 | AI18: =AH18/U18*100 -> 2.1833813
B19: 1997Q3 | C19: 246178.48 | G19: 1.0877811 | H19: 47287.134 | I19: =H19/C19*100 -> 19.208476 | J19: 157597.81 | K19: =J19/C19*100 -> 64.017704 | L19: 25171.21 | M19: =L19/C19*100 -> 10.224781 | N19: 18528.583 | O19: =N19/C19*100 -> 7.5264835 | P19: 0.26005328 | S19: 19.93 | T19: 1.0952 | U19: 229146 | V19: -7659.8693 | W19: =V19/U19*100 -> -3.3427899 | X19: 28.433883 | Y19: =X19/U19*100 -> 0.012408631 | Z19: -5934.6341 | AA19: =Z19/U19*100 -> -2.5898921 | AB19: 1696.8013 | AC19: =AB19/U19*100 -> 0.74048918 | AD19: 61931 | AE19: 7.0765184 | AH19: 4836.8813 | AI19: =AH19/U19*100 -> 2.1108295
B20: 1997Q4 | C20: 253904.12 | G20: 1.0307259 | H20: 45893.849 | I20: =H20/C20*100 -> 18.075267 | J20: 161953.64 | K20: =J20/C20*100 -> 63.785354 | L20: 24255.155 | M20: =L20/C20*100 -> 9.5528795 | N20: 17398.225 | O20: =N20/C20*100 -> 6.8522815 | P20: 0.83155845 | S20: 34.62 | T20: 1.1152 | U20: 227687 | V20: -11243.068 | W20: =V20/U20*100 -> -4.9379489 | X20: 22.735102 | Y20: =X20/U20*100 -> 0.0099852439 | Z20: -11576.291 | AA20: =Z20/U20*100 -> -5.0843003 | AB20: -355.95838 | AC20: =AB20/U20*100 -> -0.15633672 | AD20: 52173 | AE20: 5.9067273 | AH20: 6368.2802 | AI20: =AH20/U20*100 -> 2.796945
B21: 1998Q1 | C21: 235700.7 | G21: -1.9946134 | H21: 45594.777 | I21: =H21/C21*100 -> 19.344353 | J21: 157102.91 | K21: =J21/C21*100 -> 66.653561 | L21: 21714.344 | M21: =L21/C21*100 -> 9.2126769 | N21: 16098.855 | O21: =N21/C21*100 -> 6.8302108 | P21: 1.5169471 | S21: 24.5 | T21: 1.13556 | U21: 204708 | V21: -6475.7718 | W21: =V21/U21*100 -> -3.163419 | X21: 8.7301072 | Y21: =X21/U21*100 -> 0.0042646634 | Z21: -6855.639 | AA21: =Z21/U21*100 -> -3.3489844 | AB21: -388.59731 | AC21: =AB21/U21*100 -> -0.18983005 | AD21: 68594 | AE21: 7.7952511 | AH21: 3958.882 | AI21: =AH21/U21*100 -> 1.9339166
B22: 1998Q2 | C22: 251935.88 | G22: 1.6450158 | H22: 48379.307 | I22: =H22/C22*100 -> 19.203024 | J22: 159193.94 | K22: =J22/C22*100 -> 63.188278 | L22: 22895.701 | M22: =L22/C22*100 -> 9.0879081 | N22: 18804.595 | O22: =N22/C22*100 -> 7.4640402 | P22: 0.76087404 | S22: 21.04 | T22: 1.156 | U22: 216187 | V22: -7731.2546 | W22: =V22/U22*100 -> -3.5761885 | X22: 26.530834 | Y22: =X22/U22*100 -> 0.012272169 | Z22: -10856.78 | AA22: =Z22/U22*100 -> -5.0219394 | AB22: -3152.0564 | AC22: =AB22/U22*100 -> -1.4580231 | AD22: 70898 | AE22: 8.0774454 | AH22: 6295.0629 | AI22: =AH22/U22*100 -> 2.91186
B23: 1998Q3 | C23: 258043.29 | G23: -0.08650102 | H23: 47636.032 | I23: =H23/C23*100 -> 18.460481 | J23: 163447.31 | K23: =J23/C23*100 -> 63.341043 | L23: 25366.179 | M23: =L23/C23*100 -> 9.8302031 | N23: 18785.814 | O23: =N23/C23*100 -> 7.2801017 | P23: -0.84781572 | S23: 27.57 | T23: 1.18331 | U23: 224265 | V23: -9080.6987 | W23: =V23/U23*100 -> -4.0490931 | X23: 4.6231372 | Y23: =X23/U23*100 -> 0.0020614618 | Z23: -8358.8136 | AA23: =Z23/U23*100 -> -3.7272038 | AB23: 717.26197 | AC23: =AB23/U23*100 -> 0.31982787 | AD23: 45811 | AE23: 5.2484571 | AH23: 9989.9028 | AI23: =AH23/U23*100 -> 4.4545082
B24: 1998Q4 | C24: 256671.15 | G24: -1.0014589 | H24: 44249.303 | I24: =H24/C24*100 -> 17.239687 | J24: 163186.84 | K24: =J24/C24*100 -> 63.578178 | L24: 24325.808 | M24: =L24/C24*100 -> 9.4774217 | N24: 16781.028 | O24: =N24/C24*100 -> 6.5379487 | P24: 0.22957535 | S24: 26.27 | T24: 1.20771 | U24: 218712 | V24: -11705.155 | W24: =V24/U24*100 -> -5.3518577 | X24: 10.542422 | Y24: =X24/U24*100 -> 0.0048202302 | Z24: -10771.166 | AA24: =Z24/U24*100 -> -4.9248171 | AB24: 923.44678 | AC24: =AB24/U24*100 -> 0.42222045 | AD24: 44556 | AE24: 5.1577085 | AH24: 8611.7623 | AI24: =AH24/U24*100 -> 3.9374896
B25: 1999Q1 | C25: 250667.99 | G25: 0.1417472 | H25: 44120.584 | I25: =H25/C25*100 -> 17.601204 | J25: 164892.67 | K25: =J25/C25*100 -> 65.781302 | L25: 25846.744 | M25: =L25/C25*100 -> 10.311146 | N25: 22153.374 | O25: =N25/C25*100 -> 8.8377353 | P25: 2.8768345 | Q25: 42 | S25: 32.88 | T25: 1.80721 | U25: 141714 | V25: -5841.7028 | W25: =V25/U25*100 -> -4.1221777 | X25: 5.8240148 | Y25: =X25/U25*100 -> 0.0041096962 | Z25: -5196.7803 | AA25: =Z25/U25*100 -> -3.6670902 | AB25: 639.09855 | AC25: =AB25/U25*100 -> 0.45097771 | AD25: 33848 | AE25: 4.2263616 | AH25: 7599.044 | AI25: =AH25/U25*100 -> 5.3622394
B26: 1999Q2 | C26: 268708.93 | G26: 0.42404654 | H26: 47152.458 | I26: =H26/C26*100 -> 17.547782 | J26: 170252.07 | K26: =J26/C26*100 -> 63.359291 | L26: 29000.694 | M26: =L26/C26*100 -> 10.792605 | N26: 24727.754 | O26: =N26/C26*100 -> 9.202431 | P26: 1.053228 | Q26: 21 | S26: 19.55 | T26: 1.77436 | U26: 148541 | V26: -7494.84 | W26: =V26/U26*100 -> -5.0456372 | X26: 35.541492 | Y26: =X26/U26*100 -> 0.023927059 | Z26: -7962.0148 | AA26: =Z26/U26*100 -> -5.3601462 | AB26: -502.71633 | AC26: =AB26/U26*100 -> -0.33843607 | AD26: 41346 | AE26: 5.6388701 | AH26: 5472.205 | AI26: =AH26/U26*100 -> 3.6839694
B27: 1999Q3 | C27: 274125.56 | G27: 0.11487801 | H27: 46383.161 | I27: =H27/C27*100 -> 16.920407 | J27: 178811.44 | K27: =J27/C27*100 -> 65.229759 | L27: 32971.23 | M27: =L27/C27*100 -> 12.027784 | N27: 27646.22 | O27: =N27/C27*100 -> 10.08524 | P27: 1.9710413 | Q27: 19 | S27: 18.92 | T27: 1.90375 | U27: 154115 | V27: -5275.6267 | W27: =V27/U27*100 -> -3.4231753 | X27: 2.7351714 | Y27: =X27/U27*100 -> 0.00177476 | Z27: -4609.8031 | AA27: =Z27/U27*100 -> -2.991145 | AB27: 663.08837 | AC27: =AB27/U27*100 -> 0.43025557 | AD27: 42562 | AE27: 6.418814 | AH27: 8996.429 | AI27: =AH27/U27*100 -> 5.8374779
B28: 1999Q4 | C28: 294207.98 | G28: 1.3727965 | H28: 47431.808 | I28: =H28/C28*100 -> 16.121864 | J28: 189576.24 | K28: =J28/C28*100 -> 64.436132 | L28: 36368.152 | M28: =L28/C28*100 -> 12.361375 | N28: 29511.051 | O28: =N28/C28*100 -> 10.030677 | P28: 2.7642108 | Q28: 19 | S28: 18.55 | T28: 1.81568 | U28: 154920 | V28: -8171.4729 | W28: =V28/U28*100 -> -5.2746404 | X28: 16.576248 | Y28: =X28/U28*100 -> 0.010699876 | Z28: -6789.4768 | AA28: =Z28/U28*100 -> -4.3825696 | AB28: 1365.4199 | AC28: =AB28/U28*100 -> 0.88137096 | AD28: 36342 | AE28: 6.0641759 | AH28: 6317.9976 | AI28: =AH28/U28*100 -> 4.0782324
B29: 2000Q1 | C29: 276926.91 | G29: 1.0713041 | H29: 56886.923 | I29: =H29/C29*100 -> 20.542216 | J29: 176025.23 | K29: =J29/C29*100 -> 63.563786 | L29: 31107.005 | M29: =L29/C29*100 -> 11.23293 | N29: 26401.853 | O29: =N29/C29*100 -> 9.5338707 | P29: 0.97257894 | Q29: 18.5 | S29: 18.15 | T29: 1.73742 | U29: 154920 | V29: -4405.445 | W29: =V29/U29*100 -> -2.8436903 | X29: 3.1392793 | Y29: =X29/U29*100 -> 0.0020263873 | Z29: -5037.4009 | AA29: =Z29/U29*100 -> -3.2516143 | AB29: -635.09522 | AC29: =AB29/U29*100 -> -0.40995044 | AD29: 39200 | AE29: 6.4000418 | AH29: 6947.94 | AI29: =AH29/U29*100 -> 4.4848567
B30: 2000Q2 | C30: 292788.56 | G30: 1.3388979 | H30: 53911.079 | I30: =H30/C30*100 -> 18.412973 | J30: 189995.88 | K30: =J30/C30*100 -> 64.89184 | L30: 34983.081 | M30: =L30/C30*100 -> 11.94824 | N30: 30238.766 | O30: =N30/C30*100 -> 10.327851 | P30: 0.6614672 | Q30: 17.5 | S30: 17.51 | T30: 1.81302 | U30: 161772 | V30: -7485.5118 | W30: =V30/U30*100 -> -4.6271986 | X30: 33.233271 | Y30: =X30/U30*100 -> 0.020543277 | Z30: -5540.7745 | AA30: =Z30/U30*100 -> -3.4250516 | AB30: 1911.504 | AC30: =AB30/U30*100 -> 1.1816037 | AD30: 28265 | AE30: 4.5171457 | AH30: 6472.825 | AI30: =AH30/U30*100 -> 4.0012023
B31: 2000Q3 | C31: 308895.8 | G31: 1.3486864 | H31: 53878.575 | I31: =H31/C31*100 -> 17.442314 | J31: 200011.59 | K31: =J31/C31*100 -> 64.750505 | L31: 40155.473 | M31: =L31/C31*100 -> 12.999683 | N31: 33767.675 | O31: =N31/C31*100 -> 10.931736 | P31: 3.1778375 | Q31: 16.5 | S31: 16.05 | T31: 1.85087 | U31: 169058 | V31: -4956.6518 | W31: =V31/U31*100 -> -2.9319238 | X31: 57.037115 | Y31: =X31/U31*100 -> 0.033738194 | Z31: -3196.8393 | AA31: =Z31/U31*100 -> -1.8909719 | AB31: 1702.7753 | AC31: =AB31/U31*100 -> 1.0072137 | AD31: 31431 | AE31: 4.9059578 | AH31: 9442.517 | AI31: =AH31/U31*100 -> 5.5853713
B32: 2000Q4 | C32: 320480.81 | G32: 1.1325354 | H32: 54811.088 | I32: =H32/C32*100 -> 17.102768 | J32: 208493.25 | K32: =J32/C32*100 -> 65.056392 | L32: 43061.948 | M32: =L32/C32*100 -> 13.43667 | N32: 31755.782 | O32: =N32/C32*100 -> 9.9087938 | P32: 1.0528654 | Q32: 15.75 | S32: 15.74 | T32: 1.95728 | U32: 169958 | V32: -9683.2403 | W32: =V32/U32*100 -> -5.6974313 | X32: 33.409251 | Y32: =X32/U32*100 -> 0.019657357 | Z32: -6649.4081 | AA32: =Z32/U32*100 -> -3.9123831 | AB32: 3000.423 | AC32: =AB32/U32*100 -> 1.7653908 | AD32: 33011 | AE32: 5.0344056 | AH32: 10131.437 | AI32: =AH32/U32*100 -> 5.9611414
B33: 2001Q1 | C33: 312469.82 | G33: 0.27338372 | H33: 61689.234 | I33: =H33/C33*100 -> 19.742462 | J33: 203369.32 | K33: =J33/C33*100 -> 65.084468 | L33: 42901.626 | M33: =L33/C33*100 -> 13.729846 | N33: 33576.475 | O33: =N33/C33*100 -> 10.74551 | P33: 1.4167167 | Q33: 15.75 | S33: 15.14 | T33: 2.12975 | U33: 135716 | V33: -7117.6395 | W33: =V33/U33*100 -> -5.2445102 | X33: 11.869906 | Y33: =X33/U33*100 -> 0.0087461358 | Z33: -5855.0117 | AA33: =Z33/U33*100 -> -4.3141647 | AB33: 1250.7579 | AC33: =AB33/U33*100 -> 0.92159942 | AD33: 34407 | AE33: 5.405622 | AH33: 4736.5576 | AI33: =AH33/U33*100 -> 3.490051
B34: 2001Q2 | C34: 323723.56 | G34: -0.37944376 | H34: 62066.886 | I34: =H34/C34*100 -> 19.172805 | J34: 210283.8 | K34: =J34/C34*100 -> 64.957831 | L34: 48577.436 | M34: =L34/C34*100 -> 15.005839 | N34: 40837.156 | O34: =N34/C34*100 -> 12.614824 | P34: 1.5175831 | Q34: 18.25 | S34: 17.18 | T34: 2.36703 | U34: 140033 | V34: -7114.8226 | W34: =V34/U34*100 -> -5.0808185 | X34: 64.390781 | Y34: =X34/U34*100 -> 0.045982576 | Z34: -6503.3097 | AA34: =Z34/U34*100 -> -4.6441265 | AB34: 547.12212 | AC34: =AB34/U34*100 -> 0.39070942 | AD34: 37318 | AE34: 6.070287 | AH34: 5161.7115 | AI34: =AH34/U34*100 -> 3.6860679
B35: 2001Q3 | C35: 332524.45 | G35: -0.45837951 | H35: 60427.389 | I35: =H35/C35*100 -> 18.172315 | J35: 211485.55 | K35: =J35/C35*100 -> 63.600002 | L35: 51522.557 | M35: =L35/C35*100 -> 15.494367 | N35: 45700.995 | O35: =N35/C35*100 -> 13.74365 | P35: 2.3245617 | Q35: 19 | S35: 18.83 | T35: 2.71701 | U35: 142787 | V35: -4455.1805 | W35: =V35/U35*100 -> -3.1201583 | X35: 15.769595 | Y35: =X35/U35*100 -> 0.011044139 | Z35: -5481.9939 | AA35: =Z35/U35*100 -> -3.8392808 | AB35: -1042.583 | AC35: =AB35/U35*100 -> -0.73016658 | AD35: 40054 | AE35: 6.8061866 | AH35: 5382.0797 | AI35: =AH35/U35*100 -> 3.7693065
B36: 2001Q4 | C36: 347037.64 | G36: -0.4482184 | H36: 58153.471 | I36: =H36/C36*100 -> 16.757108 | J36: 218362 | K36: =J36/C36*100 -> 62.921705 | L36: 48632.565 | M36: =L36/C36*100 -> 14.013628 | N36: 42666.833 | O36: =N36/C36*100 -> 12.294584 | P36: 2.2063467 | Q36: 19 | S36: 18.54 | T36: 2.32599 | U36: 141025 | V36: -6202.4346 | W36: =V36/U36*100 -> -4.39811 | X36: 13.654324 | Y36: =X36/U36*100 -> 0.0096822008 | Z36: -5169.824 | AA36: =Z36/U36*100 -> -3.6658919 | AB36: 1018.9563 | AC36: =AB36/U36*100 -> 0.72253591 | AD36: 35866 | AE36: 6.4096676 | AH36: 7945.4976 | AI36: =AH36/U36*100 -> 5.6341057
... B60: 2007Q4 | C60: 726339.31 | G60: 1.4668588 | H60: 131177.44 | I60: =H60/C60*100 -> 18.060077 | J60: 432651.75 | K60: =J60/C60*100 -> 59.566066 | L60: 86062.832 | M60: =L60/C60*100 -> 11.848847 | N60: 92082.932 | O60: =N60/C60*100 -> 12.677674 | P60: 1.4261792 | Q60: 11.25 | S60: 10.32 | T60: 1.79032 | U60: 402481 | V60: -3372.7424 | W60: =V60/U60*100 -> -0.83798799 | X60: 72.54367 | Y60: =X60/U60*100 -> 0.018024123 | Z60: -2079.5499 | AA60: =Z60/U60*100 -> -0.51668275 | AB60: 1220.6489 | AC60: =AB60/U60*100 -> 0.30328112 | AD60: 180334 | AE60: 12.910537 | AH60: 9312.5143 | AI60: =AH60/U60*100 -> 2.3137774
B61: 2008Q1 | C61: 712055.25 | G61: 1.3305789 | H61: 132371.45 | I61: =H61/C61*100 -> 18.590054 | J61: 433753.15 | K61: =J61/C61*100 -> 60.915659 | L61: 86426.453 | M61: =L61/C61*100 -> 12.137605 | N61: 80459.148 | O61: =N61/C61*100 -> 11.299565 | P61: 1.5177807 | Q61: 11.25 | S61: 10.35 | T61: 1.73052 | U61: 404598 | V61: -12155.313 | W61: =V61/U61*100 -> -3.0042939 | X61: 18.616155 | Y61: =X61/U61*100 -> 0.0046011485 | Z61: -13957.967 | AA61: =Z61/U61*100 -> -3.4498359 | AB61: -1821.2702 | AC61: =AB61/U61*100 -> -0.45014316 | AD61: 195232 | AE61: 12.994113 | AH61: 10181.419 | AI61: =AH61/U61*100 -> 2.5164285 | BR61: ='BCB-DBGG-trimestral'!B3 -> 1599048.5 | BS61: ='BCB-DBGG-trimestral'!C3 -> 57.090623
B62: 2008Q2 | C62: 769525.16 | G62: 2.0311179 | H62: 147732.51 | I62: =H62/C62*100 -> 19.197879 | J62: 456472.74 | K62: =J62/C62*100 -> 59.318754 | L62: 98761.08 | M62: =L62/C62*100 -> 12.834029 | N62: 98392.591 | O62: =N62/C62*100 -> 12.786144 | P62: 2.0944221 | Q62: 12.25 | S62: 11.44 | T62: 1.60444 | U62: 457169 | V62: -8114.0063 | W62: =V62/U62*100 -> -1.7748374 | X62: 44.527334 | Y62: =X62/U62*100 -> 0.0097397974 | Z62: -6043.4203 | AA62: =Z62/U62*100 -> -1.3219226 | AB62: 2026.0586 | AC62: =AB62/U62*100 -> 0.44317498 | AD62: 200827 | AE62: 12.376414 | AH62: 9966.4043 | AI62: =AH62/U62*100 -> 2.1800263 | BR62: ='BCB-DBGG-trimestral'!B4 -> 1612136.7 | BS62: ='BCB-DBGG-trimestral'!C4 -> 55.595415
B63: 2008Q3 | C63: 812602.58 | G63: 1.5348641 | H63: 168885.98 | I63: =H63/C63*100 -> 20.783343 | J63: 480468.43 | K63: =J63/C63*100 -> 59.127111 | L63: 114296.52 | M63: =L63/C63*100 -> 14.065489 | N63: 115435.04 | O63: =N63/C63*100 -> 14.205596 | P63: 1.0734116 | Q63: 13.75 | S63: 12.42 | T63: 1.86427 | U63: 479466 | V63: -8637.0573 | W63: =V63/U63*100 -> -1.801391 | X63: 60.107773 | Y63: =X63/U63*100 -> 0.012536399 | Z63: -8770.7197 | AA63: =Z63/U63*100 -> -1.8292683 | AB63: -193.77017 | AC63: =AB63/U63*100 -> -0.040413746 | AD63: 206494 | AE63: 11.842194 | AH63: 15585.27 | AI63: =AH63/U63*100 -> 3.2505476 | BR63: ='BCB-DBGG-trimestral'!B5 -> 1656166.5 | BS63: ='BCB-DBGG-trimestral'!C5 -> 54.830469
B64: 2008Q4 | C64: 815620.1 | G64: -3.743358 | H64: 153855.63 | I64: =H64/C64*100 -> 18.863639 | J64: 486815.73 | K64: =J64/C64*100 -> 59.686578 | L64: 127291.91 | M64: =L64/C64*100 -> 15.606765 | N64: 126593.99 | O64: =N64/C64*100 -> 15.521195 | P64: 1.0941623 | Q64: 13.75 | S64: 12.5 | T64: 2.36636 | U64: 351914 | V64: -6695.3509 | W64: =V64/U64*100 -> -1.9025532 | X64: 28.845365 | Y64: =X64/U64*100 -> 0.0081967085 | Z64: 4632.1964 | AA64: =Z64/U64*100 -> 1.3162865 | AB64: 11298.702 | AC64: =AB64/U64*100 -> 3.2106429 | AD64: 193783 | AE64: 11.445137 | AH64: 14983.309 | AI64: =AH64/U64*100 -> 4.257662 | BR64: ='BCB-DBGG-trimestral'!B6 -> 1740887.8 | BS64: ='BCB-DBGG-trimestral'!C6 -> 55.980645
B65: 2009Q1 | C65: 756127.09 | G65: -1.3586991 | H65: 134944.75 | I65: =H65/C65*100 -> 17.846835 | J65: 474263.58 | K65: =J65/C65*100 -> 62.722734 | L65: 93767.449 | M65: =L65/C65*100 -> 12.401017 | N65: 87414.684 | O65: =N65/C65*100 -> 11.560845 | P65: 1.2344185 | Q65: 11.25 | S65: 10.47 | T65: 2.26828 | U65: 320254 | V65: -6412.1017 | W65: =V65/U65*100 -> -2.0021925 | X65: 26.361606 | Y65: =X65/U65*100 -> 0.0082314682 | Z65: -4704.8754 | AA65: =Z65/U65*100 -> -1.4691075 | AB65: 1680.8646 | AC65: =AB65/U65*100 -> 0.52485359 | AD65: 190388 | AE65: 11.83414 | AH65: 5670.3621 | AI65: =AH65/U65*100 -> 1.7705828 | BR65: ='BCB-DBGG-trimestral'!B7 -> 1812527.1 | BS65: ='BCB-DBGG-trimestral'!C7 -> 57.469847
B66: 2009Q2 | C66: 803577.49 | G66: 1.7878377 | H66: 147361.7 | I66: =H66/C66*100 -> 18.338206 | J66: 504219.99 | K66: =J66/C66*100 -> 62.746903 | L66: 88904.311 | M66: =L66/C66*100 -> 11.063564 | N66: 93899.818 | O66: =N66/C66*100 -> 11.685223 | P66: 1.3156592 | Q66: 9.25 | S66: 8.74 | T66: 1.96863 | U66: 380565 | V66: -3030.2091 | W66: =V66/U66*100 -> -0.79623957 | X66: 76.441572 | Y66: =X66/U66*100 -> 0.020086338 | Z66: -1955.0872 | AA66: =Z66/U66*100 -> -0.5137328 | AB66: 998.68032 | AC66: =AB66/U66*100 -> 0.26242043 | AD66: 201467 | AE66: 13.148879 | AH66: 8225.4 | AI66: =AH66/U66*100 -> 2.1613653 | BR66: ='BCB-DBGG-trimestral'!B8 -> 1859801.5 | BS66: ='BCB-DBGG-trimestral'!C8 -> 58.338895
B67: 2009Q3 | C67: 852843.25 | G67: 2.3601913 | H67: 172381.63 | I67: =H67/C67*100 -> 20.212581 | J67: 534397.21 | K67: =J67/C67*100 -> 62.66066 | L67: 95863.413 | M67: =L67/C67*100 -> 11.240449 | N67: 92906.412 | O67: =N67/C67*100 -> 10.893727 | P67: 0.63125611 | Q67: 8.75 | S67: 8.21 | T67: 1.79845 | U67: 449297 | V67: -6580.4682 | W67: =V67/U67*100 -> -1.4646143 | X67: 29.411123 | Y67: =X67/U67*100 -> 0.0065460314 | Z67: -3100.8944 | AA67: =Z67/U67*100 -> -0.69016583 | AB67: 3450.1627 | AC67: =AB67/U67*100 -> 0.76790247 | AD67: 221629 | AE67: 14.755298 | AH67: 7577.1987 | AI67: =AH67/U67*100 -> 1.6864566 | BR67: ='BCB-DBGG-trimestral'!B9 -> 1962852.3 | BS67: ='BCB-DBGG-trimestral'!C9 -> 60.80391
B68: 2009Q4 | C68: 920491.52 | G68: 2.5162009 | H68: 181987.7 | I68: =H68/C68*100 -> 19.770709 | J68: 552152.41 | K68: =J68/C68*100 -> 59.984519 | L68: 96585.222 | M68: =L68/C68*100 -> 10.492788 | N68: 87459.557 | O68: =N68/C68*100 -> 9.5013973 | P68: 1.0636908 | Q68: 8.75 | S68: 8.16 | T68: 1.76247 | U68: 522508 | V68: -13305.654 | W68: =V68/U68*100 -> -2.5464977 | X68: 105.003 | Y68: =X68/U68*100 -> 0.020095961 | Z68: -13693.534 | AA68: =Z68/U68*100 -> -2.6207319 | AB68: -492.88289 | AC68: =AB68/U68*100 -> -0.09433021 | AD68: 238520 | AE68: 14.260228 | AH68: 10007.971 | AI68: =AH68/U68*100 -> 1.9153718 | BR68: ='BCB-DBGG-trimestral'!B10 -> 1973423.7 | BS68: ='BCB-DBGG-trimestral'!C10 -> 59.207932
B69: 2010Q1 | C69: 886397.39 | G69: 2.1144317 | H69: 163725.54 | I69: =H69/C69*100 -> 18.470896 | J69: 546391.81 | K69: =J69/C69*100 -> 61.641857 | L69: 101274.07 | M69: =L69/C69*100 -> 11.425357 | N69: 86801.172 | O69: =N69/C69*100 -> 9.7925798 | P69: 2.0635673 | Q69: 8.75 | S69: 8.34 | T69: 1.79614 | U69: 488663 | V69: -23077.008 | W69: =V69/U69*100 -> -4.7224791 | X69: 77.792801 | Y69: =X69/U69*100 -> 0.015919519 | Z69: -22603.623 | AA69: =Z69/U69*100 -> -4.6256056 | AB69: 395.5921 | AC69: =AB69/U69*100 -> 0.08095397 | AD69: 243762 | AE69: 13.240501 | AH69: 14121.922 | AI69: =AH69/U69*100 -> 2.8899101 | BR69: ='BCB-DBGG-trimestral'!B11 -> 1947898.9 | BS69: ='BCB-DBGG-trimestral'!C11 -> 56.243857
B70: 2010Q2 | C70: 944145.04 | G70: 1.2731056 | H70: 172802.95 | I70: =H70/C70*100 -> 18.302585 | J70: 568567.3 | K70: =J70/C70*100 -> 60.220334 | L70: 111181.68 | M70: =L70/C70*100 -> 11.775911 | N70: 105294.32 | O70: =N70/C70*100 -> 11.152346 | P70: 1.002643 | Q70: 10.25 | S70: 8.87 | T70: 1.78434 | U70: 525814 | V70: -19371.556 | W70: =V70/U70*100 -> -3.684108 | X70: 33.79209 | Y70: =X70/U70*100 -> 0.0064266243 | Z70: -17113.235 | AA70: =Z70/U70*100 -> -3.2546175 | AB70: 2224.5289 | AC70: =AB70/U70*100 -> 0.42306384 | AD70: 253114 | AE70: 12.743105 | AH70: 12086.004 | AI70: =AH70/U70*100 -> 2.2985321 | BR70: ='BCB-DBGG-trimestral'!B12 -> 2010317.7 | BS70: ='BCB-DBGG-trimestral'!C12 -> 55.78208
B71: 2010Q3 | C71: 997934.74 | G71: 0.88622612 | H71: 179939.9 | I71: =H71/C71*100 -> 18.031229 | J71: 596732.42 | K71: =J71/C71*100 -> 59.796738 | L71: 126847.24 | M71: =L71/C71*100 -> 12.710976 | N71: 114224.83 | O71: =N71/C71*100 -> 11.446123 | P71: 0.49988106 | Q71: 10.75 | S71: 9.18 | T71: 1.71323 | U71: 571140 | V71: -23931.447 | W71: =V71/U71*100 -> -4.1901193 | X71: 118.29375 | Y71: =X71/U71*100 -> 0.020711866 | Z71: -21326.733 | AA71: =Z71/U71*100 -> -3.734064 | AB71: 2486.4201 | AC71: =AB71/U71*100 -> 0.43534337 | AD71: 275206 | AE71: 13.054539 | AH71: 21520.114 | AI71: =AH71/U71*100 -> 3.7679227 | BR71: ='BCB-DBGG-trimestral'!B13 -> 2057909.4 | BS71: ='BCB-DBGG-trimestral'!C13 -> 54.89268
B72: 2010Q4 | C72: 1057369.8 | G72: 1.3990209 | H72: 222497.61 | I72: =H72/C72*100 -> 21.042553 | J72: 628475.47 | K72: =J72/C72*100 -> 59.437621 | L72: 123369.01 | M72: =L72/C72*100 -> 11.667537 | N72: 115899.67 | O72: =N72/C72*100 -> 10.961129 | P72: 2.226281 | Q72: 10.75 | S72: 9.09 | T72: 1.68789 | U72: 624133 | V72: -20337.767 | W72: =V72/U72*100 -> -3.258563 | X72: 12.174845 | Y72: =X72/U72*100 -> 0.0019506812 | Z72: -17016.377 | AA72: =Z72/U72*100 -> -2.7264024 | AB72: 3309.2155 | AC72: =AB72/U72*100 -> 0.53020999 | AD72: 288575 | AE72: 13.05917 | AH72: 34661.893 | AI72: =AH72/U72*100 -> 5.5536069 | BR72: ='BCB-DBGG-trimestral'!B14 -> 2011521.7 | BS72: ='BCB-DBGG-trimestral'!C14 -> 51.765334
B73: 2011Q1 | C73: 1016530.6 | G73: 1.4030217 | H73: 177786.21 | I73: =H73/C73*100 -> 17.489508 | J73: 623584.96 | K73: =J73/C73*100 -> 61.344433 | L73: 116373.9 | M73: =L73/C73*100 -> 11.448145 | N73: 103744.11 | O73: =N73/C73*100 -> 10.205704 | P73: 2.439696 | Q73: 11.75 | R73: 27.422288 | S73: 11.04 | T73: 1.65593 | U73: 609903 | V73: -22235.461 | W73: =V73/U73*100 -> -3.6457373 | X73: 74.474192 | Y73: =X73/U73*100 -> 0.012210826 | Z73: -24399.495 | AA73: =Z73/U73*100 -> -4.0005533 | AB73: -2238.5078 | AC73: =AB73/U73*100 -> -0.36702686 | AD73: 317146 | AE73: 13.605635 | AH73: 25828.318 | AI73: =AH73/U73*100 -> 4.2348238 | BR73: ='BCB-DBGG-trimestral'!B15 -> 2112891.1 | BS73: ='BCB-DBGG-trimestral'!C15 -> 52.612089
B74: 2011Q2 | C74: 1086712.2 | G74: 0.91690019 | H74: 199019.86 | I74: =H74/C74*100 -> 18.313943 | J74: 648648.82 | K74: =J74/C74*100 -> 59.689106 | L74: 130951.36 | M74: =L74/C74*100 -> 12.050233 | N74: 124992.6 | O74: =N74/C74*100 -> 11.501904 | P74: 1.3956003 | Q74: 12.25 | R74: 27.572219 | S74: 11.75 | T74: 1.58974 | U74: 680395 | V74: -19021.878 | W74: =V74/U74*100 -> -2.7957109 | X74: 31.655429 | Y74: =X74/U74*100 -> 0.0046525076 | Z74: -19441.084 | AA74: =Z74/U74*100 -> -2.8573232 | AB74: -450.8621 | AC74: =AB74/U74*100 -> -0.066264758 | AD74: 335775 | AE74: 13.508968 | AH74: 25359.617 | AI74: =AH74/U74*100 -> 3.7271904 | BR74: ='BCB-DBGG-trimestral'!B16 -> 2177090.4 | BS74: ='BCB-DBGG-trimestral'!C16 -> 52.352184
B75: 2011Q3 | C75: 1112334.2 | G75: -0.16667756 | H75: 199027.28 | I75: =H75/C75*100 -> 17.892758 | J75: 668612.01 | K75: =J75/C75*100 -> 60.108913 | L75: 141578.78 | M75: =L75/C75*100 -> 12.728079 | N75: 137086.17 | O75: =N75/C75*100 -> 12.324188 | P75: 1.0633971 | Q75: 12 | R75: 27.272519 | S75: 11.15 | T75: 1.83083 | U75: 680127 | V75: -20604.273 | W75: =V75/U75*100 -> -3.0294744 | X75: 111.87863 | Y75: =X75/U75*100 -> 0.016449667 | Z75: -22836.2 | AA75: =Z75/U75*100 -> -3.3576376 | AB75: -2343.8051 | AC75: =AB75/U75*100 -> -0.34461287 | AD75: 349708 | AE75: 13.478519 | AH75: 26601.23 | AI75: =AH75/U75*100 -> 3.911215 | BR75: ='BCB-DBGG-trimestral'!B17 -> 2226487.2 | BS75: ='BCB-DBGG-trimestral'!C17 -> 52.106596
B76: 2011Q4 | C76: 1160804.9 | G76: 0.94437205 | H76: 241204.65 | I76: =H76/C76*100 -> 20.779086 | J76: 696968.21 | K76: =J76/C76*100 -> 60.041805 | L76: 151661.96 | M76: =L76/C76*100 -> 13.065241 | N76: 141072.12 | O76: =N76/C76*100 -> 12.152957 | P76: 1.4569951 | Q76: 11 | R76: 25.783678 | S76: 10.22 | T76: 1.86119 | U76: 644059 | V76: -21714.594 | W76: =V76/U76*100 -> -3.3715226 | X76: 37.786502 | Y76: =X76/U76*100 -> 0.0058669317 | Z76: -22311.994 | AA76: =Z76/U76*100 -> -3.464278 | AB76: -635.18654 | AC76: =AB76/U76*100 -> -0.098622415 | AD76: 352012 | AE76: 13.463919 | AH76: 24638.064 | AI76: =AH76/U76*100 -> 3.8254359 | BR76: ='BCB-DBGG-trimestral'!B18 -> 2243603.7 | BS76: ='BCB-DBGG-trimestral'!C18 -> 51.266176
B77: 2012Q1 | C77: 1129474.1 | G77: -1.4237513 | H77: 194540.37 | I77: =H77/C77*100 -> 17.223977 | J77: 694700.85 | K77: =J77/C77*100 -> 61.506574 | L77: 137047.68 | M77: =L77/C77*100 -> 12.13376 | N77: 119042.57 | O77: =N77/C77*100 -> 10.539646 | P77: 1.224539 | Q77: 9.75 | R77: 26.526091 | S77: 8.92 | T77: 1.82116 | U77: 638271 | V77: -24654.723 | W77: =V77/U77*100 -> -3.8627358 | X77: 28.572477 | Y77: =X77/U77*100 -> 0.0044765432 | Z77: -24157.389 | AA77: =Z77/U77*100 -> -3.7848169 | AB77: 468.76137 | AC77: =AB77/U77*100 -> 0.073442373 | AD77: 365216 | AE77: 13.819011 | AH77: 29412.841 | AI77: =AH77/U77*100 -> 4.6082058 | BR77: ='BCB-DBGG-trimestral'!B19 -> 2366667.5 | BS77: ='BCB-DBGG-trimestral'!C19 -> 52.717662
B78: 2012Q2 | C78: 1183125.6 | G78: 1.743836 | H78: 215509.07 | I78: =H78/C78*100 -> 18.215232 | J78: 718125.68 | K78: =J78/C78*100 -> 60.697331 | L78: 160923.1 | M78: =L78/C78*100 -> 13.601523 | N78: 146495.84 | O78: =N78/C78*100 -> 12.382103 | P78: 1.08289 | Q78: 8.5 | R78: 23.580332 | S78: 7.65 | T78: 2.05627 | U78: 602799 | V78: -21507.089 | W78: =V78/U78*100 -> -3.5678707 | X78: 42.452798 | Y78: =X78/U78*100 -> 0.0070426125 | Z78: -23211.954 | AA78: =Z78/U78*100 -> -3.8506954 | AB78: -1747.3173 | AC78: =AB78/U78*100 -> -0.28986731 | AD78: 373910 | AE78: 14.575933 | AH78: 17012.547 | AI78: =AH78/U78*100 -> 2.8222587 | BR78: ='BCB-DBGG-trimestral'!B20 -> 2449693.4 | BS78: ='BCB-DBGG-trimestral'!C20 -> 53.419818
B79: 2012Q3 | C79: 1230448.8 | G79: 1.7069923 | H79: 215552.7 | I79: =H79/C79*100 -> 17.518218 | J79: 753550.97 | K79: =J79/C79*100 -> 61.241959 | L79: 162813.86 | M79: =L79/C79*100 -> 13.232071 | N79: 153302.59 | O79: =N79/C79*100 -> 12.459079 | P79: 1.4167088 | Q79: 7.5 | R79: 22.275365 | S79: 7.13 | T79: 2.02807 | U79: 605760 | V79: -19093.425 | W79: =V79/U79*100 -> -3.1519785 | X79: 106.07299 | Y79: =X79/U79*100 -> 0.017510729 | Z79: -22472.775 | AA79: =Z79/U79*100 -> -3.7098479 | AB79: -3485.4225 | AC79: =AB79/U79*100 -> -0.5753801 | AD79: 378726 | AE79: 15.204451 | AH79: 22104.661 | AI79: =AH79/U79*100 -> 3.649079 | BR79: ='BCB-DBGG-trimestral'!B21 -> 2542432.7 | BS79: ='BCB-DBGG-trimestral'!C21 -> 54.049997
B80: 2012Q4 | C80: 1271711.4 | G80: 0.12768121 | H80: 266577.86 | I80: =H80/C80*100 -> 20.962135 | J80: 790456.5 | K80: =J80/C80*100 -> 62.156909 | L80: 176532.36 | M80: =L80/C80*100 -> 13.88148 | N80: 153034 | O80: =N80/C80*100 -> 12.033705 | P80: 1.9931711 | Q80: 7.25 | R80: 20.412703 | S80: 6.64 | T80: 2.06738 | U80: 616719 | V80: -27422.934 | W80: =V80/U80*100 -> -4.446585 | X80: 30.816033 | Y80: =X80/U80*100 -> 0.0049967705 | Z80: -24087.578 | AA80: =Z80/U80*100 -> -3.9057623 | AB80: 3304.5403 | AC80: =AB80/U80*100 -> 0.53582593 | AD80: 373147 | AE80: 15.146725 | AH80: 24038.339 | AI80: =AH80/U80*100 -> 3.8977783 | BR80: ='BCB-DBGG-trimestral'!B22 -> 2583946.4 | BS80: ='BCB-DBGG-trimestral'!C22 -> 53.667189
B81: 2013Q1 | C81: 1241613.6 | G81: 0.44427138 | H81: 214488.17 | I81: =H81/C81*100 -> 17.274953 | J81: 777712.9 | K81: =J81/C81*100 -> 62.637271 | L81: 164279.7 | M81: =L81/C81*100 -> 13.231145 | N81: 125320.82 | O81: =N81/C81*100 -> 10.093383 | P81: 1.9420063 | Q81: 7.25 | R81: 20.983041 | S81: 6.68 | T81: 1.99925 | U81: 620346 | V81: -27525.405 | W81: =V81/U81*100 -> -4.4371053 | X81: 97.854139 | Y81: =X81/U81*100 -> 0.015774123 | Z81: -28246.48 | AA81: =Z81/U81*100 -> -4.5533428 | AB81: -818.92842 | AC81: =AB81/U81*100 -> -0.13201156 | AD81: 376934 | AE81: 15.41259 | AH81: 14654.774 | AI81: =AH81/U81*100 -> 2.3623549 | BR81: ='BCB-DBGG-trimestral'!B23 -> 2663208.8 | BS81: ='BCB-DBGG-trimestral'!C23 -> 54.054458
B82: 2013Q2 | C82: 1322580 | G82: 1.4356852 | H82: 247032.98 | I82: =H82/C82*100 -> 18.678112 | J82: 805984.64 | K82: =J82/C82*100 -> 60.940332 | L82: 181368.76 | M82: =L82/C82*100 -> 13.713254 | N82: 156292.69 | O82: =N82/C82*100 -> 11.817258 | P82: 1.184505 | Q82: 8 | R82: 20.840225 | S82: 7.98 | T82: 2.20836 | U82: 637728 | V82: -18815.759 | W82: =V82/U82*100 -> -2.9504363 | X82: 35.081316 | Y82: =X82/U82*100 -> 0.0055009841 | Z82: -20637.345 | AA82: =Z82/U82*100 -> -3.2360732 | AB82: -1856.6676 | AC82: =AB82/U82*100 -> -0.29113785 | AD82: 369402 | AE82: 14.891921 | AH82: 29730.318 | AI82: =AH82/U82*100 -> 4.661912 | BR82: ='BCB-DBGG-trimestral'!B24 -> 2715918.7 | BS82: ='BCB-DBGG-trimestral'!C24 -> 53.606968
B83: 2013Q3 | C83: 1354134.1 | G83: 0.44055772 | H83: 244365.79 | I83: =H83/C83*100 -> 18.045908 | J83: 833144.87 | K83: =J83/C83*100 -> 61.526023 | L83: 201819.31 | M83: =L83/C83*100 -> 14.903938 | N83: 169810.29 | O83: =N83/C83*100 -> 12.540138 | P83: 0.62084221 | Q83: 9 | R83: 21.555853 | S83: 8.48 | T83: 2.22639 | U83: 590079 | V83: -23323.367 | W83: =V83/U83*100 -> -3.9525839 | X83: 139.99165 | Y83: =X83/U83*100 -> 0.023724222 | Z83: -22632.669 | AA83: =Z83/U83*100 -> -3.835532 | AB83: 550.7065 | AC83: =AB83/U83*100 -> 0.093327589 | AD83: 368654 | AE83: 14.956314 | AH83: 12389.329 | AI83: =AH83/U83*100 -> 2.0996051 | BR83: ='BCB-DBGG-trimestral'!B25 -> 2747899.6 | BS83: ='BCB-DBGG-trimestral'!C25 -> 52.945643
B84: 2013Q4 | C84: 1413291.3 | G84: 0.19613271 | H84: 301388.06 | I84: =H84/C84*100 -> 21.325262 | J84: 873579.59 | K84: =J84/C84*100 -> 61.811717 | L84: 201290.24 | M84: =L84/C84*100 -> 14.242658 | N84: 174627.2 | O84: =N84/C84*100 -> 12.356066 | P84: 2.0433326 | Q84: 10 | R84: 21.843191 | S84: 9.19 | T84: 2.34997 | U84: 620306 | V84: -18719.499 | W84: =V84/U84*100 -> -3.0177845 | X84: 49.326629 | Y84: =X84/U84*100 -> 0.0079519833 | Z84: -18085.445 | AA84: =Z84/U84*100 -> -2.9155683 | AB84: 584.72688 | AC84: =AB84/U84*100 -> 0.094264263 | AD84: 358808 | AE84: 14.535708 | AH84: 18436.608 | AI84: =AH84/U84*100 -> 2.9721795 | BR84: ='BCB-DBGG-trimestral'!B26 -> 2747996.7 | BS84: ='BCB-DBGG-trimestral'!C26 -> 51.541506
... B124: 2023Q4 | C124: 2865301.3 | G124: 0.31765321 | H124: 630484.52 | I124: =H124/C124*100 -> 22.004126 | J124: 1814673.9 | K124: =J124/C124*100 -> 63.332743 | L124: 433196.89 | M124: =L124/C124*100 -> 15.11872 | N124: 494913.92 | O124: =N124/C124*100 -> 17.272666 | P124: 1.0836246 | Q124: 11.75 | R124: 28.17356 | S124: 3.09 | T124: 4.87099 | U124: 577860 | V124: -5642.8135 | W124: =V124/U124*100 -> -0.97650184 | X124: -3610.4894 | Y124: =X124/U124*100 -> -0.62480348 | Z124: -7283.296 | AA124: =Z124/U124*100 -> -1.2603911 | AB124: 1970.0068 | AC124: =AB124/U124*100 -> 0.34091421 | AD124: 355034 | AE124: 16.204266 | AH124: 7747.1366 | AI124: =AH124/U124*100 -> 1.3406598 | BR124: ='BCB-DBGG-trimestral'!B66 -> 8079270 | BS124: ='BCB-DBGG-trimestral'!C66 -> 73.82816
B125: 2024Q1 | C125: 2753199.8 | G125: 0.87534341 | H125: 469846.88 | I125: =H125/C125*100 -> 17.065484 | J125: 1778714.5 | K125: =J125/C125*100 -> 64.605354 | L125: 430190.27 | M125: =L125/C125*100 -> 15.625102 | N125: 454239.32 | O125: =N125/C125*100 -> 16.498596 | P125: 1.4154168 | Q125: 10.75 | R125: 28.17356 | T125: 4.99794 | U125: 554843 | V125: -13789.601 | W125: =V125/U125*100 -> -2.4853158 | X125: -4276.6697 | Y125: =X125/U125*100 -> -0.77078916 | Z125: -18620.661 | AA125: =Z125/U125*100 -> -3.3560234 | AB125: -554.39043 | AC125: =AB125/U125*100 -> -0.099918432 | AD125: 355008 | AE125: 15.778905 | AH125: 23053.881 | AI125: =AH125/U125*100 -> 4.1550278 | BR125: ='BCB-DBGG-trimestral'!B67 -> 8347114 | BS125: ='BCB-DBGG-trimestral'!C67 -> 75.094185
B126: 2024Q2 | C126: 2921229.4 | G126: 1.5248492 | H126: 545214.66 | I126: =H126/C126*100 -> 18.663877 | J126: 1828527.7 | K126: =J126/C126*100 -> 62.594459 | L126: 493781.76 | M126: =L126/C126*100 -> 16.903217 | N126: 537411.33 | O126: =N126/C126*100 -> 18.396752 | P126: 1.0535526 | Q126: 10.5 | R126: 27.872565 | T126: 5.45726 | U126: 559085 | V126: -9175.7893 | W126: =V126/U126*100 -> -1.6412154 | X126: -4274.6242 | Y126: =X126/U126*100 -> -0.76457502 | Z126: -14149.027 | AA126: =Z126/U126*100 -> -2.5307469 | AB126: -698.61303 | AC126: =AB126/U126*100 -> -0.1249565 | AD126: 357827 | AE126: 15.842159 | AH126: 17922.987 | AI126: =AH126/U126*100 -> 3.2057714 | BR126: ='BCB-DBGG-trimestral'!B68 -> 8691535 | BS126: ='BCB-DBGG-trimestral'!C68 -> 76.853831
B127: 2024Q3 | C127: 2989913.4 | G127: 0.78963294 | H127: 535100.96 | I127: =H127/C127*100 -> 17.896872 | J127: 1915960.5 | K127: =J127/C127*100 -> 64.080804 | L127: 565752.25 | M127: =L127/C127*100 -> 18.922028 | N127: 562215.6 | O127: =N127/C127*100 -> 18.803742 | P127: 0.8015547 | Q127: 10.75 | R127: 27.422288 | T127: 5.46949 | U127: 537840 | V127: -21161.069 | W127: =V127/U127*100 -> -3.9344542 | X127: -4173.0652 | Y127: =X127/U127*100 -> -0.77589342 | Z127: -29651.182 | AA127: =Z127/U127*100 -> -5.5130117 | AB127: -4317.0484 | AC127: =AB127/U127*100 -> -0.80266407 | AD127: 372016 | AE127: 16.685115 | AH127: 20591.371 | AI127: =AH127/U127*100 -> 3.828531 | BR127: ='BCB-DBGG-trimestral'!B69 -> 8928002.7 | BS127: ='BCB-DBGG-trimestral'!C69 -> 77.435199
B128: 2024Q4 | C128: 3080367.5 | G128: 0.064402841 | H128: 660167.62 | I128: =H128/C128*100 -> 21.431457 | J128: 1966673.7 | K128: =J128/C128*100 -> 63.845423 | L128: 567542.57 | M128: =L128/C128*100 -> 18.424509 | N128: 561905.68 | O128: =N128/C128*100 -> 18.241514 | P128: 1.4770299 | Q128: 12.25 | R128: 28.475204 | T128: 6.16576 | U128: 526647 | V128: -22041.852 | W128: =V128/U128*100 -> -4.185318 | X128: -3545.5428 | Y128: =X128/U128*100 -> -0.67322947 | Z128: -25757.282 | AA128: =Z128/U128*100 -> -4.8908058 | AB128: -169.88758 | AC128: =AB128/U128*100 -> -0.03225834 | AD128: 329730 | AE128: 15.136234 | AH128: 12522.547 | AI128: =AH128/U128*100 -> 2.3777875 | BR128: ='BCB-DBGG-trimestral'!B70 -> 8984236.6 | BS128: ='BCB-DBGG-trimestral'!C70 -> 76.496027
B129: 2025Q1 | C129: 3019578.9 | G129: 1.3073923 | H129: 517268.55 | I129: =H129/C129*100 -> 17.130487 | J129: 1933978.1 | K129: =J129/C129*100 -> 64.04794 | L129: 568480.83 | M129: =L129/C129*100 -> 18.826494 | N129: 533917.57 | O129: =N129/C129*100 -> 17.681855 | P129: 2.0404197 | Q129: 14.25 | R129: 31.219429 | T129: 5.71627 | U129: 515753 | V129: -23223.549 | W129: =V129/U129*100 -> -4.5028433 | X129: -2853.1736 | Y129: =X129/U129*100 -> -0.55320543 | Z129: -25774.671 | AA129: =Z129/U129*100 -> -4.9974835 | AB129: 302.05176 | AC129: =AB129/U129*100 -> 0.058565197 | AD129: 336157 | AE129: 15.713227 | AH129: 23041.535 | AI129: =AH129/U129*100 -> 4.4675523 | BR129: ='BCB-DBGG-trimestral'!B71 -> 9095938.3 | BS129: ='BCB-DBGG-trimestral'!C71 -> 75.729504
B130: 2025Q2 | C130: 3176745.1 | G130: 0.37300929 | H130: 583903.01 | I130: =H130/C130*100 -> 18.380543 | J130: 1981934.3 | K130: =J130/C130*100 -> 62.388836 | L130: 552675.59 | M130: =L130/C130*100 -> 17.397543 | N130: 581342.99 | O130: =N130/C130*100 -> 18.299957 | P130: 0.93287033 | Q130: 15 | R130: 31.681989 | T130: 5.49785 | U130: 559132 | V130: -11397.873 | W130: =V130/U130*100 -> -2.0384941 | X130: -3638.6222 | Y130: =X130/U130*100 -> -0.65076264 | Z130: -12504.6 | AA130: =Z130/U130*100 -> -2.2364307 | AB130: 2531.8954 | AC130: =AB130/U130*100 -> 0.45282607 | AD130: 344440 | AE130: 16.100052 | AH130: 12963.157 | AI130: =AH130/U130*100 -> 2.318443 | BR130: ='BCB-DBGG-trimestral'!B72 -> 9388792.9 | BS130: ='BCB-DBGG-trimestral'!C72 -> 76.539459
B131: 2025Q3 | P131: 0.63025009 | Q131: 15 | R131: 31.37345 | T131: 5.32214 | U131: 587032 | V131: -22284.052 | W131: =V131/U131*100 -> -3.7960541 | X131: -4702.4871 | Y131: =X131/U131*100 -> -0.80106146 | Z131: -27555.295 | AA131: =Z131/U131*100 -> -4.6940022 | AB131: -568.75523 | AC131: =AB131/U131*100 -> -0.096886581 | AD131: 356582 | AE131: 16.292967 | AH131: 27315.663 | AI131: =AH131/U131*100 -> 4.6531812
B132: 2025Q4
A133: Completar con los pronósticos que se tengan en caso de estar disponibles | B133: 2026Q1
B134: 2026Q2
B135: 2026Q3
B136: 2026Q4
B137: 2027Q1
B138: 2027Q2
B139: 2027Q3
B140: 2027Q4
B141: 2028Q1
B142: 2028Q2
B143: 2028Q3
B144: 2028Q4

Sheet Datos_Anuales
A2: Plantilla de datos para estimación de modelo FISLAC - Brasil
A4: Nota: por favor completar la información con la mayor cantidad de datos históricos disponibles
C7: Sector Real | P7: Sector Monetario | V7: Balanza de Pagos | AJ7: Sector Fiscal
B8: Años | C8: PIB Nominal | D8: PIB Real | E8: PIB potencial | F8: Brecha del PIB | G8: Crecimiento PIB Real | H8: Inversión Privada | I8: Inversión Privada % del PIB | J8: Consumo Privado | K8: Consumo Privado % del PIB | L8: Importaciones | M8: Importaciones % del PIB | N8: Exportaciones | O8: Exportaciones % del PIB | P8: Inflación (%) | Q8: Tasa de Política Monetaria (%) | R8: Tasa activa promedio (%) | S8: Tasa pasiva promedio (%) | T8: Tasa de Cambio (por Dólar) | U8: PIB Nominal (USD) | V8: Saldo Cuenta Corriente (USD) | W8: Saldo Cuenta Corriente % del PIB | X8: Saldo Cuenta Capital (USD) | Y8: Saldo Cuenta Capital % del PIB | Z8: Saldo Cuenta financiera (USD) | AA8: Saldo Cuenta financiera % del PIB | AB8: Errores y omisiones (USD) | AC8: Errores y omisiones % del PIB | AD8: Reservas Internacionales Netas (USD) | AE8: Reservas Internacionales Netas % del PIB | AF8: Remesas Internacionales (USD) | AG8: Remesas Internacionales % del PIB | AH8: Inversión extranjera directa (USD) | AI8: Inversión extranjera directa % del PIB | AJ8: Ingreso Fiscal (Total) | AK8: Ingreso Fiscal (Total) % del PIB | AL8: Ingreso por Materias Primas | AM8: Ingreso por Materias Primas % del PIB | AN8: Ingreso Tributario | AO8: Ingreso Tributario % del PIB | AP8: Ingreso Impuestos Consumo | AQ8: Ingreso Impuestos Consumo % del PIB | AR8: Ingreso Impuestos Renta Laboral | AS8: Ingreso Impuestos Renta Laboral % del PIB | AT8: Ingreso Impuestos Renta de capital | AU8: Ingreso Impuestos Renta de capital % del PIB | AV8: Ingreso Impuestos Renta de Empresas | AW8: Ingreso Impuestos Renta de Empresas % del PIB | AX8: Ingreso Otros | AY8: Ingreso Otros % del PIB | AZ8: Gasto Público Total | BA8: Gasto Público Total % del PIB | BB8: Gasto Público Primario | BC8: Gasto Público Primario % del PIB | BD8: Gasto Corriente Primario | BE8: Gasto Corriente Primario % del PIB | BF8: Gasto en atención a desastres naturales | BG8: Gasto en atención a desastres naturales % del PIB | BH8: Gasto de Capital | BI8: Gasto de Capital % del PIB | BJ8: Inversión en adaptación al cambio climático | BK8: Inversión en adaptación al cambio climático % del PIB | BL8: Pago de Intereses | BM8: Pago de Intereses % del PIB | BN8: Balance Primario | BO8: Balance Primario % del PIB | BP8: Balance Total | BQ8: Balance Total % del PIB | BR8: Deuda Bruta (R$ Milhões) | BS8: Deuda Bruta % del PIB
B9: 1981 | P9: 95.623044
B10: 1982 | P10: 104.79043
B11: 1983 | P11: 164.01202
B12: 1984 | P12: 215.26333
B13: 1985 | P13: 242.2298
B14: 1986 | P14: 79.664497
B15: 1987 | P15: 363.41152
B16: 1988 | P16: 980.21349
B17: 1989 | P17: 1972.9116
B18: 1990 | P18: 1620.9665 | U18: 469318 | AD18: 9973 | AE18: =AD18/U18*100 -> 2.1249984
B19: 1991 | P19: 472.7 | U19: 405679 | AD19: 9406 | AE19: =AD19/U19*100 -> 2.3185819
B20: 1992 | P20: 1119.1008 | S20: 1520.75 | U20: 387295 | AD20: 23754 | AE20: =AD20/U20*100 -> 6.1333092
B21: 1993 | P21: 2477.1471 | S21: 4730.51 | U21: 429685 | AD21: 32211 | AE21: =AD21/U21*100 -> 7.4964218
B22: 1994 | P22: 916.46 | S22: 49.99 | T22: 0.8518 | U22: 543087 | AD22: 38806 | AE22: =AD22/U22*100 -> 7.1454482
B23: 1995 | C23: 705991.55 | H23: 143219.55 | I23: =H23/C23*100 -> 20.286298 | J23: 449762.08 | K23: =J23/C23*100 -> 63.706439 | L23: 66755.631 | M23: =L23/C23*100 -> 9.455585 | N23: 53153.222 | O23: =N23/C23*100 -> 7.528875 | P23: 22.408162 | S23: 36.24 | T23: 0.96979 | U23: 770733 | V23: -18712.422 | W23: =V23/U23*100 -> -2.4278735 | X23: 18.013833 | Y23: =X23/U23*100 -> 0.0023372339 | Z23: -16487.249 | AA23: =Z23/U23*100 -> -2.1391648 | AB23: 2207.1588 | AC23: =AB23/U23*100 -> 0.28637139 | AD23: 51840 | AE23: =AD23/U23*100 -> 6.7260647 | AH23: 4383.422 | AI23: =AH23/U23*100 -> 0.56873418
B24: 1996 | C24: 854763.61 | G24: 2.2088641 | H24: 159333.52 | I24: =H24/C24*100 -> 18.640654 | J24: 556941.74 | K24: =J24/C24*100 -> 65.157399 | L24: 76119.963 | M24: =L24/C24*100 -> 8.9053818 | N24: 57527.383 | O24: =N24/C24*100 -> 6.7302097 | P24: 9.5649518 | S24: 22.27 | T24: 1.03916 | U24: 851019 | V24: -23843.028 | W24: =V24/U24*100 -> -2.8017034 | X24: 46.587357 | Y24: =X24/U24*100 -> 0.0054743028 | Z24: -25596.329 | AA24: =Z24/U24*100 -> -3.0077271 | AB24: -1799.8884 | AC24: =AB24/U24*100 -> -0.21149802 | AD24: 60110 | AE24: =AD24/U24*100 -> 7.0632971 | AH24: 10791.687 | AI24: =AH24/U24*100 -> 1.26809
B25: 1997 | C25: 952089.2 | G25: 3.394846 | H25: 182067.08 | I25: =H25/C25*100 -> 19.122901 | J25: 621805.93 | K25: =J25/C25*100 -> 65.30963 | L25: 91329.724 | M25: =L25/C25*100 -> 9.5925597 | N25: 66490.573 | O25: =N25/C25*100 -> 6.9836496 | P25: 5.2243185 | S25: 34.62 | T25: 1.1152 | U25: 883282 | V25: -32133.363 | W25: =V25/U25*100 -> -3.6379506 | X25: 83.983013 | Y25: =X25/U25*100 -> 0.0095080635 | Z25: -32502.922 | AA25: =Z25/U25*100 -> -3.6797899 | AB25: -453.54221 | AC25: =AB25/U25*100 -> -0.051347385 | AD25: 52173 | AE25: =AD25/U25*100 -> 5.9067206 | AH25: 18992.934 | AI25: =AH25/U25*100 -> 2.1502685 | AJ25: =HLOOKUP(B25,'RTN-2.2'!$A$5:$AC$164,2,0) -> 159012.38 | AK25: =HLOOKUP(B25,'RTN-2.2-A'!$A$5:$AC$164,2,0)*100 -> 16.701416 | AN25: =HLOOKUP(B25,'RTN-2.2'!$A$5:$AC$164,3,0) -> 101710.99 | AO25: =HLOOKUP(B25,'RTN-2.2-A'!$A$5:$AC$164,3,0)*100 -> 10.682927 | AR25: =HLOOKUP(B25,'RTN-2.2'!$A$5:$AC$164,15,0) -> 10105.371 | AS25: =HLOOKUP(B25,'RTN-2.2-A'!$A$5:$AC$164,15,0)*100 -> 1.0613891 | AT25: =HLOOKUP(B25,'RTN-2.2'!$A$5:$AC$164,16,0) -> 5009.8452 | AU25: =HLOOKUP(B25,'RTN-2.2-A'!$A$5:$AC$164,16,0)*100 -> 0.52619494 | AV25: =HLOOKUP(B25,'RTN-2.2'!$A$5:$AC$164,13,0) -> 12213.438 | AW25: =HLOOKUP(B25,'RTN-2.2-A'!$A$5:$AC$164,13,0)*100 -> 1.2828039 | AZ25: =HLOOKUP(B25,'RTN-2.2'!$A$5:$AC$164,59,0) -> 132968 | BA25: =HLOOKUP(B25,'RTN-2.2-A'!$A$5:$AC$164,59,0)*100 -> 13.965918 | BL25: =HLOOKUP(B25,'RTN-2.2'!$A$5:$AC$164,159,0)*(-1) -> 18931.52 | BM25: =HLOOKUP(B25,'RTN-2.2-A'!$A$5:$AC$164,159,0)*100*(-1) -> 1.9884187 | BN25: =HLOOKUP(B25,'RTN-2.2'!$A$5:$AC$164,151,0) -> 1800.7523 | BO25: =HLOOKUP(B25,'RTN-2.2-A'!$A$5:$AC$164,151,0)*100 -> 0.18913693
B26: 1998 | C26: 1002351 | G26: 0.3380979 | H26: 185859.42 | I26: =H26/C26*100 -> 18.542348 | J26: 642931.01 | K26: =J26/C26*100 -> 64.142301 | L26: 94302.032 | M26: =L26/C26*100 -> 9.4080846 | N26: 70470.292 | O26: =N26/C26*100 -> 7.0305003 | P26: 1.6549782 | S26: 26.27 | T26: 1.20771 | U26: 863872 | V26: -34992.88 | W26: =V26/U26*100 -> -4.050702 | X26: 50.4265 | Y26: =X26/U26*100 -> 0.0058372653 | Z26: -36842.399 | AA26: =Z26/U26*100 -> -4.2647983 | AB26: -1899.9449 | AC26: =AB26/U26*100 -> -0.21993362 | AD26: 44556 | AE26: =AD26/U26*100 -> 5.1577085 | AH26: 28855.61 | AI26: =AH26/U26*100 -> 3.3402645 | AJ26: =HLOOKUP(B26,'RTN-2.2'!$A$5:$AC$164,2,0) -> 183516.2 | AK26: =HLOOKUP(B26,'RTN-2.2-A'!$A$5:$AC$164,2,0)*100 -> 18.308577 | AN26: =HLOOKUP(B26,'RTN-2.2'!$A$5:$AC$164,3,0) -> 111752.41 | AO26: =HLOOKUP(B26,'RTN-2.2-A'!$A$5:$AC$164,3,0)*100 -> 11.14903 | AR26: =HLOOKUP(B26,'RTN-2.2'!$A$5:$AC$164,15,0) -> 11879.118 | AS26: =HLOOKUP(B26,'RTN-2.2-A'!$A$5:$AC$164,15,0)*100 -> 1.1851255 | AT26: =HLOOKUP(B26,'RTN-2.2'!$A$5:$AC$164,16,0) -> 11927.483 | AU26: =HLOOKUP(B26,'RTN-2.2-A'!$A$5:$AC$164,16,0)*100 -> 1.1899507 | AV26: =HLOOKUP(B26,'RTN-2.2'!$A$5:$AC$164,13,0) -> 11838.117 | AW26: =HLOOKUP(B26,'RTN-2.2-A'!$A$5:$AC$164,13,0)*100 -> 1.1810351 | AZ26: =HLOOKUP(B26,'RTN-2.2'!$A$5:$AC$164,59,0) -> 148782.88 | BA26: =HLOOKUP(B26,'RTN-2.2-A'!$A$5:$AC$164,59,0)*100 -> 14.843391 | BL26: =HLOOKUP(B26,'RTN-2.2'!$A$5:$AC$164,159,0)*(-1) -> 50141.5 | BM26: =HLOOKUP(B26,'RTN-2.2-A'!$A$5:$AC$164,159,0)*100*(-1) -> 5.0023894 | BN26: =HLOOKUP(B26,'RTN-2.2'!$A$5:$AC$164,151,0) -> 7577.0177 | BO26: =HLOOKUP(B26,'RTN-2.2-A'!$A$5:$AC$164,151,0)*100 -> 0.75592459
B27: 1999 | C27: 1087710.5 | G27: 0.46793757 | H27: 185088.01 | I27: =H27/C27*100 -> 17.016294 | J27: 703532.42 | K27: =J27/C27*100 -> 64.680119 | L27: 124186.82 | M27: =L27/C27*100 -> 11.417268 | N27: 104038.4 | O27: =N27/C27*100 -> 9.5648983 | P27: 8.9397888 | Q27: 19 | S27: 18.55 | T27: 1.81568 | U27: 599290 | V27: -26783.642 | W27: =V27/U27*100 -> -4.469229 | X27: 60.676927 | Y27: =X27/U27*100 -> 0.010124802 | Z27: -24558.075 | AA27: =Z27/U27*100 -> -4.0978616 | AB27: 2164.8905 | AC27: =AB27/U27*100 -> 0.36124255 | AD27: 36342 | AE27: =AD27/U27*100 -> 6.0641759 | AH27: 28385.676 | AI27: =AH27/U27*100 -> 4.7365509 | AJ27: =HLOOKUP(B27,'RTN-2.2'!$A$5:$AC$164,2,0) -> 209383.53 | AK27: =HLOOKUP(B27,'RTN-2.2-A'!$A$5:$AC$164,2,0)*100 -> 19.249932 | AN27: =HLOOKUP(B27,'RTN-2.2'!$A$5:$AC$164,3,0) -> 134315.24 | AO27: =HLOOKUP(B27,'RTN-2.2-A'!$A$5:$AC$164,3,0)*100 -> 12.348437 | AR27: =HLOOKUP(B27,'RTN-2.2'!$A$5:$AC$164,15,0) -> 11451.938 | AS27: =HLOOKUP(B27,'RTN-2.2-A'!$A$5:$AC$164,15,0)*100 -> 1.052848 | AT27: =HLOOKUP(B27,'RTN-2.2'!$A$5:$AC$164,16,0) -> 13623.401 | AU27: =HLOOKUP(B27,'RTN-2.2-A'!$A$5:$AC$164,16,0)*100 -> 1.2524841 | AV27: =HLOOKUP(B27,'RTN-2.2'!$A$5:$AC$164,13,0) -> 12760.411 | AW27: =HLOOKUP(B27,'RTN-2.2-A'!$A$5:$AC$164,13,0)*100 -> 1.173144 | AZ27: =HLOOKUP(B27,'RTN-2.2'!$A$5:$AC$164,59,0) -> 158679.81 | BA27: =HLOOKUP(B27,'RTN-2.2-A'!$A$5:$AC$164,59,0)*100 -> 14.588423 | BL27: =HLOOKUP(B27,'RTN-2.2'!$A$5:$AC$164,159,0)*(-1) -> 49008.09 | BM27: =HLOOKUP(B27,'RTN-2.2-A'!$A$5:$AC$164,159,0)*100*(-1) -> 4.5056189 | BN27: =HLOOKUP(B27,'RTN-2.2'!$A$5:$AC$164,151,0) -> 20164.293 | BO27: =HLOOKUP(B27,'RTN-2.2-A'!$A$5:$AC$164,151,0)*100 -> 1.853829
B28: 2000 | C28: 1199092.1 | G28: 4.3879494 | H28: 219487.66 | I28: =H28/C28*100 -> 18.304488 | J28: 774525.95 | K28: =J28/C28*100 -> 64.5927 | L28: 149307.51 | M28: =L28/C28*100 -> 12.451713 | N28: 122164.08 | O28: =N28/C28*100 -> 10.188048 | P28: 5.9745933 | Q28: 15.75 | S28: 15.74 | T28: 1.95728 | U28: 655707 | V28: -26530.849 | W28: =V28/U28*100 -> -4.0461439 | X28: 126.81892 | Y28: =X28/U28*100 -> 0.01934079 | Z28: -20424.423 | AA28: =Z28/U28*100 -> -3.1148703 | AB28: 5979.6071 | AC28: =AB28/U28*100 -> 0.91193279 | AD28: 33011 | AE28: =AD28/U28*100 -> 5.0344132 | AH28: 32994.719 | AI28: =AH28/U28*100 -> 5.0319302 | AJ28: =HLOOKUP(B28,'RTN-2.2'!$A$5:$AC$164,2,0) -> 235051.93 | AK28: =HLOOKUP(B28,'RTN-2.2-A'!$A$5:$AC$164,2,0)*100 -> 19.602492 | AN28: =HLOOKUP(B28,'RTN-2.2'!$A$5:$AC$164,3,0) -> 156187.72 | AO28: =HLOOKUP(B28,'RTN-2.2-A'!$A$5:$AC$164,3,0)*100 -> 13.025499 | AR28: =HLOOKUP(B28,'RTN-2.2'!$A$5:$AC$164,15,0) -> 13817.417 | AS28: =HLOOKUP(B28,'RTN-2.2-A'!$A$5:$AC$164,15,0)*100 -> 1.1523233 | AT28: =HLOOKUP(B28,'RTN-2.2'!$A$5:$AC$164,16,0) -> 10676.972 | AU28: =HLOOKUP(B28,'RTN-2.2-A'!$A$5:$AC$164,16,0)*100 -> 0.89042134 | AV28: =HLOOKUP(B28,'RTN-2.2'!$A$5:$AC$164,13,0) -> 17511.299 | AW28: =HLOOKUP(B28,'RTN-2.2-A'!$A$5:$AC$164,13,0)*100 -> 1.4603798 | AZ28: =HLOOKUP(B28,'RTN-2.2'!$A$5:$AC$164,59,0) -> 177372.06 | BA28: =HLOOKUP(B28,'RTN-2.2-A'!$A$5:$AC$164,59,0)*100 -> 14.792197 | BL28: =HLOOKUP(B28,'RTN-2.2'!$A$5:$AC$164,159,0)*(-1) -> 45447.03 | BM28: =HLOOKUP(B28,'RTN-2.2-A'!$A$5:$AC$164,159,0)*100*(-1) -> 3.7901201 | BN28: =HLOOKUP(B28,'RTN-2.2'!$A$5:$AC$164,151,0) -> 20982.204 | BO28: =HLOOKUP(B28,'RTN-2.2-A'!$A$5:$AC$164,151,0)*100 -> 1.749841
B29: 2001 | C29: 1315755.5 | G29: 1.3898964 | H29: 242336.98 | I29: =H29/C29*100 -> 18.418087 | J29: 843500.68 | K29: =J29/C29*100 -> 64.107708 | L29: 191634.18 | M29: =L29/C29*100 -> 14.564574 | N29: 162781.46 | O29: =N29/C29*100 -> 12.371711 | P29: 7.6734364 | Q29: 19 | S29: 18.54 | T29: 2.32599 | U29: 559563 | V29: -24890.077 | W29: =V29/U29*100 -> -4.4481278 | X29: 105.68461 | Y29: =X29/U29*100 -> 0.01888699 | Z29: -23010.139 | AA29: =Z29/U29*100 -> -4.1121624 | AB29: 1774.2533 | AC29: =AB29/U29*100 -> 0.31707838 | AD29: 35866 | AE29: =AD29/U29*100 -> 6.4096447 | AH29: 23225.846 | AI29: =AH29/U29*100 -> 4.1507116 | AJ29: =HLOOKUP(B29,'RTN-2.2'!$A$5:$AC$164,2,0) -> 270441.18 | AK29: =HLOOKUP(B29,'RTN-2.2-A'!$A$5:$AC$164,2,0)*100 -> 20.554061 | AN29: =HLOOKUP(B29,'RTN-2.2'!$A$5:$AC$164,3,0) -> 179218.17 | AO29: =HLOOKUP(B29,'RTN-2.2-A'!$A$5:$AC$164,3,0)*100 -> 13.620933 | AR29: =HLOOKUP(B29,'RTN-2.2'!$A$5:$AC$164,15,0) -> 16924.356 | AS29: =HLOOKUP(B29,'RTN-2.2-A'!$A$5:$AC$164,15,0)*100 -> 1.2862843 | AT29: =HLOOKUP(B29,'RTN-2.2'!$A$5:$AC$164,16,0) -> 15193.088 | AU29: =HLOOKUP(B29,'RTN-2.2-A'!$A$5:$AC$164,16,0)*100 -> 1.1547045 | AV29: =HLOOKUP(B29,'RTN-2.2'!$A$5:$AC$164,13,0) -> 16842.886 | AW29: =HLOOKUP(B29,'RTN-2.2-A'!$A$5:$AC$164,13,0)*100 -> 1.2800924 | AZ29: =HLOOKUP(B29,'RTN-2.2'!$A$5:$AC$164,59,0) -> 205643.18 | BA29: =HLOOKUP(B29,'RTN-2.2-A'!$A$5:$AC$164,59,0)*100 -> 15.629286 | BL29: =HLOOKUP(B29,'RTN-2.2'!$A$5:$AC$164,159,0)*(-1) -> 47253.044 | BM29: =HLOOKUP(B29,'RTN-2.2-A'!$A$5:$AC$164,159,0)*100*(-1) -> 3.5913242 | BN29: =HLOOKUP(B29,'RTN-2.2'!$A$5:$AC$164,151,0) -> 21737.1 | BO29: =HLOOKUP(B29,'RTN-2.2-A'!$A$5:$AC$164,151,0)*100 -> 1.6520623
B30: 2002 | C30: 1488787.3 | G30: 3.0534619 | H30: 266883.74 | I30: =H30/C30*100 -> 17.926251 | J30: 921536.01 | K30: =J30/C30*100 -> 61.898435 | L30: 199315.37 | M30: =L30/C30*100 -> 13.387767 | N30: 211863.21 | O30: =N30/C30*100 -> 14.23059 | P30: 12.530273 | Q30: 25 | S30: 22.66 | T30: 3.51755 | U30: 508101 | V30: -9407.0433 | W30: =V30/U30*100 -> -1.8514121 | X30: 79.278742 | Y30: =X30/U30*100 -> 0.015602949 | Z30: -6893.3476 | AA30: =Z30/U30*100 -> -1.3566884 | AB30: 2434.417 | AC30: =AB30/U30*100 -> 0.47912068 | AD30: 37823 | AE30: =AD30/U30*100 -> 7.4439924 | AH30: 16586.6 | AI30: =AH30/U30*100 -> 3.2644297 | AJ30: =HLOOKUP(B30,'RTN-2.2'!$A$5:$AC$164,2,0) -> 320056.45 | AK30: =HLOOKUP(B30,'RTN-2.2-A'!$A$5:$AC$164,2,0)*100 -> 21.497797 | AN30: =HLOOKUP(B30,'RTN-2.2'!$A$5:$AC$164,3,0) -> 219900.79 | AO30: =HLOOKUP(B30,'RTN-2.2-A'!$A$5:$AC$164,3,0)*100 -> 14.770465 | AR30: =HLOOKUP(B30,'RTN-2.2'!$A$5:$AC$164,15,0) -> 16413.73 | AS30: =HLOOKUP(B30,'RTN-2.2-A'!$A$5:$AC$164,15,0)*100 -> 1.10249 | AT30: =HLOOKUP(B30,'RTN-2.2'!$A$5:$AC$164,16,0) -> 16223.956 | AU30: =HLOOKUP(B30,'RTN-2.2-A'!$A$5:$AC$164,16,0)*100 -> 1.0897431 | AV30: =HLOOKUP(B30,'RTN-2.2'!$A$5:$AC$164,13,0) -> 33341.047 | AW30: =HLOOKUP(B30,'RTN-2.2-A'!$A$5:$AC$164,13,0)*100 -> 2.2394769 | AZ30: =HLOOKUP(B30,'RTN-2.2'!$A$5:$AC$164,59,0) -> 236461.07 | BA30: =HLOOKUP(B30,'RTN-2.2-A'!$A$5:$AC$164,59,0)*100 -> 15.882798 | BL30: =HLOOKUP(B30,'RTN-2.2'!$A$5:$AC$164,159,0)*(-1) -> 41948.248 | BM30: =HLOOKUP(B30,'RTN-2.2-A'!$A$5:$AC$164,159,0)*100*(-1) -> 2.817612 | BN30: =HLOOKUP(B30,'RTN-2.2'!$A$5:$AC$164,151,0) -> 31577.205 | BO30: =HLOOKUP(B30,'RTN-2.2-A'!$A$5:$AC$164,151,0)*100 -> 2.1210018
B31: 2003 | C31: 1717950.4 | G31: 1.140829 | H31: 285261.53 | I31: =H31/C31*100 -> 16.604759 | J31: 1062460.4 | K31: =J31/C31*100 -> 61.84465 | L31: 222639.52 | M31: =L31/C31*100 -> 12.959601 | N31: 260798.33 | O31: =N31/C31*100 -> 15.180784 | P31: 9.3005128 | Q31: 16.5 | S31: 15.56 | T31: 2.91157 | U31: 559465 | V31: 2193.173 | W31: =V31/U31*100 -> 0.39201255 | X31: 82.844955 | Y31: =X31/U31*100 -> 0.014807889 | Z31: 4360.9966 | AA31: =Z31/U31*100 -> 0.77949408 | AB31: 2084.9786 | AC31: =AB31/U31*100 -> 0.37267364 | AD31: 49296 | AE31: =AD31/U31*100 -> 8.8112751 | AH31: 10123.014 | AI31: =AH31/U31*100 -> 1.8094096 | AJ31: =HLOOKUP(B31,'RTN-2.2'!$A$5:$AC$164,2,0) -> 356131.53 | AK31: =HLOOKUP(B31,'RTN-2.2-A'!$A$5:$AC$164,2,0)*100 -> 20.730024 | AN31: =HLOOKUP(B31,'RTN-2.2'!$A$5:$AC$164,3,0) -> 242869.36 | AO31: =HLOOKUP(B31,'RTN-2.2-A'!$A$5:$AC$164,3,0)*100 -> 14.137158 | AR31: =HLOOKUP(B31,'RTN-2.2'!$A$5:$AC$164,15,0) -> 19622.902 | AS31: =HLOOKUP(B31,'RTN-2.2-A'!$A$5:$AC$164,15,0)*100 -> 1.1422275 | AT31: =HLOOKUP(B31,'RTN-2.2'!$A$5:$AC$164,16,0) -> 18859.928 | AU31: =HLOOKUP(B31,'RTN-2.2-A'!$A$5:$AC$164,16,0)*100 -> 1.0978156 | AV31: =HLOOKUP(B31,'RTN-2.2'!$A$5:$AC$164,13,0) -> 31584.585 | AW31: =HLOOKUP(B31,'RTN-2.2-A'!$A$5:$AC$164,13,0)*100 -> 1.8385039 | AZ31: =HLOOKUP(B31,'RTN-2.2'!$A$5:$AC$164,59,0) -> 260122.4 | BA31: =HLOOKUP(B31,'RTN-2.2-A'!$A$5:$AC$164,59,0)*100 -> 15.141438 | BL31: =HLOOKUP(B31,'RTN-2.2'!$A$5:$AC$164,159,0)*(-1) -> 100896.43 | BM31: =HLOOKUP(B31,'RTN-2.2-A'!$A$5:$AC$164,159,0)*100*(-1) -> 5.8730698 | BN31: =HLOOKUP(B31,'RTN-2.2'!$A$5:$AC$164,151,0) -> 39080.048 | BO31: =HLOOKUP(B31,'RTN-2.2-A'!$A$5:$AC$164,151,0)*100 -> 2.2748066
B32: 2004 | C32: 1957751.2 | G32: 5.7599646 | H32: 339087.08 | I32: =H32/C32*100 -> 17.320233 | J32: 1178695 | K32: =J32/C32*100 -> 60.206577 | L32: 257101.5 | M32: =L32/C32*100 -> 13.132491 | N32: 323924.85 | O32: =N32/C32*100 -> 16.545762 | P32: 7.5994958 | Q32: 17.75 | S32: 16.19 | T32: 2.6859 | U32: 669340 | V32: 8959.3134 | W32: =V32/U32*100 -> 1.3385295 | X32: -213.09615 | Y32: =X32/U32*100 -> -0.031836757 | Z32: 11153.288 | AA32: =Z32/U32*100 -> 1.6663114 | AB32: 2407.0713 | AC32: =AB32/U32*100 -> 0.35961862 | AD32: 52935 | AE32: =AD32/U32*100 -> 7.9085368 | AH32: 18161.38 | AI32: =AH32/U32*100 -> 2.7133266 | AJ32: =HLOOKUP(B32,'RTN-2.2'!$A$5:$AC$164,2,0) -> 418993.29 | AK32: =HLOOKUP(B32,'RTN-2.2-A'!$A$5:$AC$164,2,0)*100 -> 21.401764 | AN32: =HLOOKUP(B32,'RTN-2.2'!$A$5:$AC$164,3,0) -> 286807.67 | AO32: =HLOOKUP(B32,'RTN-2.2-A'!$A$5:$AC$164,3,0)*100 -> 14.649853 | AR32: =HLOOKUP(B32,'RTN-2.2'!$A$5:$AC$164,15,0) -> 23684.779 | AS32: =HLOOKUP(B32,'RTN-2.2-A'!$A$5:$AC$164,15,0)*100 -> 1.2097952 | AT32: =HLOOKUP(B32,'RTN-2.2'!$A$5:$AC$164,16,0) -> 17168.747 | AU32: =HLOOKUP(B32,'RTN-2.2-A'!$A$5:$AC$164,16,0)*100 -> 0.87696264 | AV32: =HLOOKUP(B32,'RTN-2.2'!$A$5:$AC$164,13,0) -> 36144.181 | AW32: =HLOOKUP(B32,'RTN-2.2-A'!$A$5:$AC$164,13,0)*100 -> 1.8462091 | AZ32: =HLOOKUP(B32,'RTN-2.2'!$A$5:$AC$164,59,0) -> 305610.66 | BA32: =HLOOKUP(B32,'RTN-2.2-A'!$A$5:$AC$164,59,0)*100 -> 15.610291 | BL32: =HLOOKUP(B32,'RTN-2.2'!$A$5:$AC$164,159,0)*(-1) -> 79418.517 | BM32: =HLOOKUP(B32,'RTN-2.2-A'!$A$5:$AC$164,159,0)*100*(-1) -> 4.0566195 | BN32: =HLOOKUP(B32,'RTN-2.2'!$A$5:$AC$164,151,0) -> 49341.425 | BO32: =HLOOKUP(B32,'RTN-2.2-A'!$A$5:$AC$164,151,0)*100 -> 2.5203113
B33: 2005 | C33: 2170584.5 | G33: 3.2021352 | H33: 370218.88 | I33: =H33/C33*100 -> 17.056183 | J33: 1313295.9 | K33: =J33/C33*100 -> 60.504252 | L33: 257061.58 | M33: =L33/C33*100 -> 11.842966 | N33: 330880.2 | O33: =N33/C33*100 -> 15.243829 | P33: 5.6892268 | Q33: 18 | S33: 16.55 | T33: 2.34129 | U33: 892033 | V33: 11679.375 | W33: =V33/U33*100 -> 1.3092985 | X33: 187.04449 | Y33: =X33/U33*100 -> 0.020968338 | Z33: 15204.315 | AA33: =Z33/U33*100 -> 1.7044565 | AB33: 3337.8952 | AC33: =AB33/U33*100 -> 0.37418965 | AD33: 53799 | AE33: =AD33/U33*100 -> 6.0310549 | AH33: 15459.982 | AI33: =AH33/U33*100 -> 1.7331177 | AJ33: =HLOOKUP(B33,'RTN-2.2'!$A$5:$AC$164,2,0) -> 487822.08 | AK33: =HLOOKUP(B33,'RTN-2.2-A'!$A$5:$AC$164,2,0)*100 -> 22.474227 | AN33: =HLOOKUP(B33,'RTN-2.2'!$A$5:$AC$164,3,0) -> 333069.63 | AO33: =HLOOKUP(B33,'RTN-2.2-A'!$A$5:$AC$164,3,0)*100 -> 15.344698 | AR33: =HLOOKUP(B33,'RTN-2.2'!$A$5:$AC$164,15,0) -> 28736.411 | AS33: =HLOOKUP(B33,'RTN-2.2-A'!$A$5:$AC$164,15,0)*100 -> 1.323902 | AT33: =HLOOKUP(B33,'RTN-2.2'!$A$5:$AC$164,16,0) -> 19967.36 | AU33: =HLOOKUP(B33,'RTN-2.2-A'!$A$5:$AC$164,16,0)*100 -> 0.91990707 | AV33: =HLOOKUP(B33,'RTN-2.2'!$A$5:$AC$164,13,0) -> 48964.977 | AW33: =HLOOKUP(B33,'RTN-2.2-A'!$A$5:$AC$164,13,0)*100 -> 2.2558429 | AZ33: =HLOOKUP(B33,'RTN-2.2'!$A$5:$AC$164,59,0) -> 354925.38 | BA33: =HLOOKUP(B33,'RTN-2.2-A'!$A$5:$AC$164,59,0)*100 -> 16.351604 | BL33: =HLOOKUP(B33,'RTN-2.2'!$A$5:$AC$164,159,0)*(-1) -> 129025.37 | BM33: =HLOOKUP(B33,'RTN-2.2-A'!$A$5:$AC$164,159,0)*100*(-1) -> 5.9442686 | BN33: =HLOOKUP(B33,'RTN-2.2'!$A$5:$AC$164,151,0) -> 52673.168 | BO33: =HLOOKUP(B33,'RTN-2.2-A'!$A$5:$AC$164,151,0)*100 -> 2.4266813
B34: 2006 | C34: 2409449.9 | G34: 3.9619887 | H34: 414673.55 | I34: =H34/C34*100 -> 17.2103 | J34: 1456215.5 | K34: =J34/C34*100 -> 60.437676 | L34: 281119.76 | M34: =L34/C34*100 -> 11.667384 | N34: 346341.95 | O34: =N34/C34*100 -> 14.374316 | P34: 3.1415161 | Q34: 13.25 | S34: 12.04 | T34: 2.14877 | U34: 1107131 | V34: 10774 | W34: =V34/U34*100 -> 0.9731459 | X34: 179.72642 | Y34: =X34/U34*100 -> 0.016233527 | Z34: 15429.69 | AA34: =Z34/U34*100 -> 1.3936644 | AB34: 4475.9639 | AC34: =AB34/U34*100 -> 0.40428494 | AD34: 85839 | AE34: =AD34/U34*100 -> 7.753283 | AH34: 19418.086 | AI34: =AH34/U34*100 -> 1.7539104 | AJ34: =HLOOKUP(B34,'RTN-2.2'!$A$5:$AC$164,2,0) -> 542810.01 | AK34: =HLOOKUP(B34,'RTN-2.2-A'!$A$5:$AC$164,2,0)*100 -> 22.528379 | AN34: =HLOOKUP(B34,'RTN-2.2'!$A$5:$AC$164,3,0) -> 359189.17 | AO34: =HLOOKUP(B34,'RTN-2.2-A'!$A$5:$AC$164,3,0)*100 -> 14.907518 | AR34: =HLOOKUP(B34,'RTN-2.2'!$A$5:$AC$164,15,0) -> 29902.243 | AS34: =HLOOKUP(B34,'RTN-2.2-A'!$A$5:$AC$164,15,0)*100 -> 1.2410402 | AT34: =HLOOKUP(B34,'RTN-2.2'!$A$5:$AC$164,16,0) -> 21293.287 | AU34: =HLOOKUP(B34,'RTN-2.2-A'!$A$5:$AC$164,16,0)*100 -> 0.88374058 | AV34: =HLOOKUP(B34,'RTN-2.2'!$A$5:$AC$164,13,0) -> 53965.864 | AW34: =HLOOKUP(B34,'RTN-2.2-A'!$A$5:$AC$164,13,0)*100 -> 2.2397587 | AZ34: =HLOOKUP(B34,'RTN-2.2'!$A$5:$AC$164,59,0) -> 403738.39 | BA34: =HLOOKUP(B34,'RTN-2.2-A'!$A$5:$AC$164,59,0)*100 -> 16.756455 | BL34: =HLOOKUP(B34,'RTN-2.2'!$A$5:$AC$164,159,0)*(-1) -> 125826.62 | BM34: =HLOOKUP(B34,'RTN-2.2-A'!$A$5:$AC$164,159,0)*100*(-1) -> 5.2222134 | BN34: =HLOOKUP(B34,'RTN-2.2'!$A$5:$AC$164,151,0) -> 48748.23 | BO34: =HLOOKUP(B34,'RTN-2.2-A'!$A$5:$AC$164,151,0)*100 -> 2.0232099
B35: 2007 | C35: 2720262.9 | G35: 6.0698706 | H35: 489532.03 | I35: =H35/C35*100 -> 17.995761 | J35: 1628756 | K35: =J35/C35*100 -> 59.874948 | L35: 325477.73 | M35: =L35/C35*100 -> 11.964936 | N35: 362547.81 | O35: =N35/C35*100 -> 13.327675 | P35: 4.4576586 | Q35: 11.25 | S35: 10.32 | T35: 1.79032 | U35: 1396797 | V35: -2753.6702 | W35: =V35/U35*100 -> -0.19714176 | X35: 249.36078 | Y35: =X35/U35*100 -> 0.017852328 | Z35: 681.90924 | AA35: =Z35/U35*100 -> 0.048819495 | AB35: 3186.2187 | AC35: =AB35/U35*100 -> 0.22810893 | AD35: 180334 | AE35: =AD35/U35*100 -> 12.910537 | AH35: 44579.492 | AI35: =AH35/U35*100 -> 3.1915513 | AJ35: =HLOOKUP(B35,'RTN-2.2'!$A$5:$AC$164,2,0) -> 618352.11 | AK35: =HLOOKUP(B35,'RTN-2.2-A'!$A$5:$AC$164,2,0)*100 -> 22.731336 | AN35: =HLOOKUP(B35,'RTN-2.2'!$A$5:$AC$164,3,0) -> 417509.44 | AO35: =HLOOKUP(B35,'RTN-2.2-A'!$A$5:$AC$164,3,0)*100 -> 15.348128 | AR35: =HLOOKUP(B35,'RTN-2.2'!$A$5:$AC$164,15,0) -> 32071.986 | AS35: =HLOOKUP(B35,'RTN-2.2-A'!$A$5:$AC$164,15,0)*100 -> 1.1790032 | AT35: =HLOOKUP(B35,'RTN-2.2'!$A$5:$AC$164,16,0) -> 21488.195 | AU35: =HLOOKUP(B35,'RTN-2.2-A'!$A$5:$AC$164,16,0)*100 -> 0.78993081 | AV35: =HLOOKUP(B35,'RTN-2.2'!$A$5:$AC$164,13,0) -> 67797.984 | AW35: =HLOOKUP(B35,'RTN-2.2-A'!$A$5:$AC$164,13,0)*100 -> 2.492332 | AZ35: =HLOOKUP(B35,'RTN-2.2'!$A$5:$AC$164,59,0) -> 458785.05 | BA35: =HLOOKUP(B35,'RTN-2.2-A'!$A$5:$AC$164,59,0)*100 -> 16.865467 | BL35: =HLOOKUP(B35,'RTN-2.2'!$A$5:$AC$164,159,0)*(-1) -> 119045.7 | BM35: =HLOOKUP(B35,'RTN-2.2-A'!$A$5:$AC$164,159,0)*100*(-1) -> 4.3762572 | BN35: =HLOOKUP(B35,'RTN-2.2'!$A$5:$AC$164,151,0) -> 57650.389 | BO35: =HLOOKUP(B35,'RTN-2.2-A'!$A$5:$AC$164,151,0)*100 -> 2.1192947
B36: 2008 | C36: 3109803.1 | G36: 5.0941954 | H36: 602845.58 | I36: =H36/C36*100 -> 19.38533 | J36: 1857510 | K36: =J36/C36*100 -> 59.730793 | L36: 426775.97 | M36: =L36/C36*100 -> 13.723569 | N36: 420880.77 | O36: =N36/C36*100 -> 13.534001 | P36: 5.9027244 | Q36: 13.75 | S36: 12.5 | T36: 2.36636 | U36: 1693147 | V36: -35601.728 | W36: =V36/U36*100 -> -2.1026956 | X36: 152.09663 | Y36: =X36/U36*100 -> 0.0089830728 | Z36: -24139.911 | AA36: =Z36/U36*100 -> -1.4257422 | AB36: 11309.72 | AC36: =AB36/U36*100 -> 0.66797036 | AD36: 193783 | AE36: =AD36/U36*100 -> 11.445137 | AH36: 50716.403 | AI36: =AH36/U36*100 -> 2.9953928 | AJ36: =HLOOKUP(B36,'RTN-2.2'!$A$5:$AC$164,2,0) -> 715615.9 | AK36: =HLOOKUP(B36,'RTN-2.2-A'!$A$5:$AC$164,2,0)*100 -> 23.011614 | AN36: =HLOOKUP(B36,'RTN-2.2'!$A$5:$AC$164,3,0) -> 466337.04 | AO36: =HLOOKUP(B36,'RTN-2.2-A'!$A$5:$AC$164,3,0)*100 -> 14.99571 | AR36: =HLOOKUP(B36,'RTN-2.2'!$A$5:$AC$164,15,0) -> 41345.879 | AS36: =HLOOKUP(B36,'RTN-2.2-A'!$A$5:$AC$164,15,0)*100 -> 1.3295337 | AT36: =HLOOKUP(B36,'RTN-2.2'!$A$5:$AC$164,16,0) -> 25585.371 | AU36: =HLOOKUP(B36,'RTN-2.2-A'!$A$5:$AC$164,16,0)*100 -> 0.82273282 | AV36: =HLOOKUP(B36,'RTN-2.2'!$A$5:$AC$164,13,0) -> 81414.289 | AW36: =HLOOKUP(B36,'RTN-2.2-A'!$A$5:$AC$164,13,0)*100 -> 2.6179886 | AZ36: =HLOOKUP(B36,'RTN-2.2'!$A$5:$AC$164,59,0) -> 516818.49 | BA36: =HLOOKUP(B36,'RTN-2.2-A'!$A$5:$AC$164,59,0)*100 -> 16.61901 | BL36: =HLOOKUP(B36,'RTN-2.2'!$A$5:$AC$164,159,0)*(-1) -> 96198.68 | BM36: =HLOOKUP(B36,'RTN-2.2-A'!$A$5:$AC$164,159,0)*100*(-1) -> 3.093401 | BN36: =HLOOKUP(B36,'RTN-2.2'!$A$5:$AC$164,151,0) -> 71438.389 | BO36: =HLOOKUP(B36,'RTN-2.2-A'!$A$5:$AC$164,151,0)*100 -> 2.2971998 | BR36: ='BCB-DBGG-anual'!B4 -> 1740887.8 | BS36: ='BCB-DBGG-anual'!C4 -> 55.980645
B37: 2009 | C37: 3333039.4 | G37: -0.125812 | H37: 636675.78 | I37: =H37/C37*100 -> 19.101958 | J37: 2065033.2 | K37: =J37/C37*100 -> 61.95646 | L37: 375120.4 | M37: =L37/C37*100 -> 11.254604 | N37: 361680.47 | O37: =N37/C37*100 -> 10.851371 | P37: 4.3116501 | Q37: 8.75 | S37: 8.16 | T37: 1.76247 | U37: 1672625 | V37: -29328.433 | W37: =V37/U37*100 -> -1.7534374 | X37: 237.2173 | Y37: =X37/U37*100 -> 0.014182336 | Z37: -23454.391 | AA37: =Z37/U37*100 -> -1.4022504 | AB37: 5636.8248 | AC37: =AB37/U37*100 -> 0.3370047 | AD37: 238520 | AE37: =AD37/U37*100 -> 14.26022 | AH37: 31480.932 | AI37: =AH37/U37*100 -> 1.8821273 | AJ37: =HLOOKUP(B37,'RTN-2.2'!$A$5:$AC$164,2,0) -> 738124.95 | AK37: =HLOOKUP(B37,'RTN-2.2-A'!$A$5:$AC$164,2,0)*100 -> 22.145701 | AN37: =HLOOKUP(B37,'RTN-2.2'!$A$5:$AC$164,3,0) -> 456139.33 | AO37: =HLOOKUP(B37,'RTN-2.2-A'!$A$5:$AC$164,3,0)*100 -> 13.685387 | AR37: =HLOOKUP(B37,'RTN-2.2'!$A$5:$AC$164,15,0) -> 42074.017 | AS37: =HLOOKUP(B37,'RTN-2.2-A'!$A$5:$AC$164,15,0)*100 -> 1.2623318 | AT37: =HLOOKUP(B37,'RTN-2.2'!$A$5:$AC$164,16,0) -> 23431.558 | AU37: =HLOOKUP(B37,'RTN-2.2-A'!$A$5:$AC$164,16,0)*100 -> 0.70300874 | AV37: =HLOOKUP(B37,'RTN-2.2'!$A$5:$AC$164,13,0) -> 81084.153 | AW37: =HLOOKUP(B37,'RTN-2.2-A'!$A$5:$AC$164,13,0)*100 -> 2.4327391 | AZ37: =HLOOKUP(B37,'RTN-2.2'!$A$5:$AC$164,59,0) -> 579009.45 | BA37: =HLOOKUP(B37,'RTN-2.2-A'!$A$5:$AC$164,59,0)*100 -> 17.371816 | BL37: =HLOOKUP(B37,'RTN-2.2'!$A$5:$AC$164,159,0)*(-1) -> 149806.4 | BM37: =HLOOKUP(B37,'RTN-2.2-A'!$A$5:$AC$164,159,0)*100*(-1) -> 4.4945884 | BN37: =HLOOKUP(B37,'RTN-2.2'!$A$5:$AC$164,151,0) -> 39436.419 | BO37: =HLOOKUP(B37,'RTN-2.2-A'!$A$5:$AC$164,151,0)*100 -> 1.1831969 | BR37: ='BCB-DBGG-anual'!B5 -> 1973423.7 | BS37: ='BCB-DBGG-anual'!C5 -> 59.207932
B38: 2010 | C38: 3885847 | G38: 7.5282258 | H38: 797946 | I38: =H38/C38*100 -> 20.534674 | J38: 2340167 | K38: =J38/C38*100 -> 60.222829 | L38: 462672 | M38: =L38/C38*100 -> 11.906593 | N38: 422220 | O38: =N38/C38*100 -> 10.865585 | P38: 5.9086887 | Q38: 10.75 | S38: 9.09 | T38: 1.68789 | U38: 2209751 | V38: -86717.778 | W38: =V38/U38*100 -> -3.9243235 | X38: 242.05349 | Y38: =X38/U38*100 -> 0.010953881 | Z38: -78059.968 | AA38: =Z38/U38*100 -> -3.5325233 | AB38: 8415.7566 | AC38: =AB38/U38*100 -> 0.38084638 | AD38: 288575 | AE38: =AD38/U38*100 -> 13.059164 | AH38: 82389.932 | AI38: =AH38/U38*100 -> 3.7284713 | AJ38: =HLOOKUP(B38,'RTN-2.2'!$A$5:$AC$164,2,0) -> 918531.37 | AK38: =HLOOKUP(B38,'RTN-2.2-A'!$A$5:$AC$164,2,0)*100 -> 23.637868 | AN38: =HLOOKUP(B38,'RTN-2.2'!$A$5:$AC$164,3,0) -> 531205.99 | AO38: =HLOOKUP(B38,'RTN-2.2-A'!$A$5:$AC$164,3,0)*100 -> 13.670276 | AR38: =HLOOKUP(B38,'RTN-2.2'!$A$5:$AC$164,15,0) -> 49144.427 | AS38: =HLOOKUP(B38,'RTN-2.2-A'!$A$5:$AC$164,15,0)*100 -> 1.2647031 | AT38: =HLOOKUP(B38,'RTN-2.2'!$A$5:$AC$164,16,0) -> 25169.452 | AU38: =HLOOKUP(B38,'RTN-2.2-A'!$A$5:$AC$164,16,0)*100 -> 0.64772114 | AV38: =HLOOKUP(B38,'RTN-2.2'!$A$5:$AC$164,13,0) -> 84874.314 | AW38: =HLOOKUP(B38,'RTN-2.2-A'!$A$5:$AC$164,13,0)*100 -> 2.1841908 | AZ38: =HLOOKUP(B38,'RTN-2.2'!$A$5:$AC$164,59,0) -> 707269.91 | BA38: =HLOOKUP(B38,'RTN-2.2-A'!$A$5:$AC$164,59,0)*100 -> 18.201178 | BL38: =HLOOKUP(B38,'RTN-2.2'!$A$5:$AC$164,159,0)*(-1) -> 124508.74 | BM38: =HLOOKUP(B38,'RTN-2.2-A'!$A$5:$AC$164,159,0)*100*(-1) -> 3.2041597 | BN38: =HLOOKUP(B38,'RTN-2.2'!$A$5:$AC$164,151,0) -> 77891.169 | BO38: =HLOOKUP(B38,'RTN-2.2-A'!$A$5:$AC$164,151,0)*100 -> 2.0044837 | BR38: ='BCB-DBGG-anual'!B6 -> 2011521.7 | BS38: ='BCB-DBGG-anual'!C6 -> 51.765334
B39: 2011 | C39: 4376382 | G39: 3.9744231 | H39: 901927 | I39: =H39/C39*100 -> 20.608964 | J39: 2637814 | K39: =J39/C39*100 -> 60.273852 | L39: 540566 | M39: =L39/C39*100 -> 12.351892 | N39: 506895 | O39: =N39/C39*100 -> 11.582513 | P39: 6.5033527 | Q39: 11 | R39: 25.783678 | S39: 10.22 | T39: 1.86119 | U39: 2614482 | V39: -83576.206 | W39: =V39/U39*100 -> -3.196664 | X39: 255.79475 | Y39: =X39/U39*100 -> 0.0097837641 | Z39: -88988.773 | AA39: =Z39/U39*100 -> -3.4036866 | AB39: -5668.3616 | AC39: =AB39/U39*100 -> -0.2168063 | AD39: 352012 | AE39: =AD39/U39*100 -> 13.463929 | AH39: 102427.23 | AI39: =AH39/U39*100 -> 3.9176873 | AJ39: =HLOOKUP(B39,'RTN-2.2'!$A$5:$AC$164,2,0) -> 988270.08 | AK39: =HLOOKUP(B39,'RTN-2.2-A'!$A$5:$AC$164,2,0)*100 -> 22.581897 | AN39: =HLOOKUP(B39,'RTN-2.2'!$A$5:$AC$164,3,0) -> 628894.93 | AO39: =HLOOKUP(B39,'RTN-2.2-A'!$A$5:$AC$164,3,0)*100 -> 14.370202 | AR39: =HLOOKUP(B39,'RTN-2.2'!$A$5:$AC$164,15,0) -> 58400.376 | AS39: =HLOOKUP(B39,'RTN-2.2-A'!$A$5:$AC$164,15,0)*100 -> 1.3344442 | AT39: =HLOOKUP(B39,'RTN-2.2'!$A$5:$AC$164,16,0) -> 35543.231 | AU39: =HLOOKUP(B39,'RTN-2.2-A'!$A$5:$AC$164,16,0)*100 -> 0.81216016 | AV39: =HLOOKUP(B39,'RTN-2.2'!$A$5:$AC$164,13,0) -> 98706.499 | AW39: =HLOOKUP(B39,'RTN-2.2-A'!$A$5:$AC$164,13,0)*100 -> 2.2554361 | AZ39: =HLOOKUP(B39,'RTN-2.2'!$A$5:$AC$164,59,0) -> 733343.38 | BA39: =HLOOKUP(B39,'RTN-2.2-A'!$A$5:$AC$164,59,0)*100 -> 16.756841 | BL39: =HLOOKUP(B39,'RTN-2.2'!$A$5:$AC$164,159,0)*(-1) -> 180553.07 | BM39: =HLOOKUP(B39,'RTN-2.2-A'!$A$5:$AC$164,159,0)*100*(-1) -> 4.1256241 | BN39: =HLOOKUP(B39,'RTN-2.2'!$A$5:$AC$164,151,0) -> 91891.031 | BO39: =HLOOKUP(B39,'RTN-2.2-A'!$A$5:$AC$164,151,0)*100 -> 2.0997032 | BR39: ='BCB-DBGG-anual'!B7 -> 2243603.7 | BS39: ='BCB-DBGG-anual'!C7 -> 51.266176
B40: 2012 | C40: 4814760 | G40: 1.921176 | H40: 997460 | I40: =H40/C40*100 -> 20.716713 | J40: 2956834 | K40: =J40/C40*100 -> 61.411867 | L40: 637317 | M40: =L40/C40*100 -> 13.236735 | N40: 571875 | O40: =N40/C40*100 -> 11.877539 | P40: 5.8385947 | Q40: 7.25 | R40: 20.412703 | S40: 6.64 | T40: 2.06738 | U40: 2463549 | V40: -92678.171 | W40: =V40/U40*100 -> -3.761978 | X40: 207.9143 | Y40: =X40/U40*100 -> 0.0084396251 | Z40: -93929.695 | AA40: =Z40/U40*100 -> -3.8127797 | AB40: -1459.4381 | AC40: =AB40/U40*100 -> -0.059241287 | AD40: 373147 | AE40: =AD40/U40*100 -> 15.146725 | AH40: 92568.388 | AI40: =AH40/U40*100 -> 3.7575217 | AJ40: =HLOOKUP(B40,'RTN-2.2'!$A$5:$AC$164,2,0) -> 1072289.4 | AK40: =HLOOKUP(B40,'RTN-2.2-A'!$A$5:$AC$164,2,0)*100 -> 22.27088 | AN40: =HLOOKUP(B40,'RTN-2.2'!$A$5:$AC$164,3,0) -> 647535.06 | AO40: =HLOOKUP(B40,'RTN-2.2-A'!$A$5:$AC$164,3,0)*100 -> 13.448958 | AR40: =HLOOKUP(B40,'RTN-2.2'!$A$5:$AC$164,15,0) -> 63933.98 | AS40: =HLOOKUP(B40,'RTN-2.2-A'!$A$5:$AC$164,15,0)*100 -> 1.3278747 | AT40: =HLOOKUP(B40,'RTN-2.2'!$A$5:$AC$164,16,0) -> 33853.764 | AU40: =HLOOKUP(B40,'RTN-2.2-A'!$A$5:$AC$164,16,0)*100 -> 0.70312464 | AV40: =HLOOKUP(B40,'RTN-2.2'!$A$5:$AC$164,13,0) -> 101104.32 | AW40: =HLOOKUP(B40,'RTN-2.2-A'!$A$5:$AC$164,13,0)*100 -> 2.0998829 | AZ40: =HLOOKUP(B40,'RTN-2.2'!$A$5:$AC$164,59,0) -> 815907.02 | BA40: =HLOOKUP(B40,'RTN-2.2-A'!$A$5:$AC$164,59,0)*100 -> 16.945954 | BL40: =HLOOKUP(B40,'RTN-2.2'!$A$5:$AC$164,159,0)*(-1) -> 147267.63 | BM40: =HLOOKUP(B40,'RTN-2.2-A'!$A$5:$AC$164,159,0)*100*(-1) -> 3.0586703 | BN40: =HLOOKUP(B40,'RTN-2.2'!$A$5:$AC$164,151,0) -> 84987.966 | BO40: =HLOOKUP(B40,'RTN-2.2-A'!$A$5:$AC$164,151,0)*100 -> 1.7651548 | BR40: ='BCB-DBGG-anual'!B8 -> 2583946.4 | BS40: ='BCB-DBGG-anual'!C8 -> 53.667189
B41: 2013 | C41: 5331619 | G41: 3.0048227 | H41: 1114944 | I41: =H41/C41*100 -> 20.911922 | J41: 3290422 | K41: =J41/C41*100 -> 61.71525 | L41: 748758 | M41: =L41/C41*100 -> 14.043727 | N41: 626051 | O41: =N41/C41*100 -> 11.742231 | P41: 5.9106833 | Q41: 10 | R41: 21.843191 | S41: 9.19 | T41: 2.34997 | U41: 2468456 | V41: -88384.03 | W41: =V41/U41*100 -> -3.580539 | X41: 322.25374 | Y41: =X41/U41*100 -> 0.013054871 | Z41: -89601.939 | AA41: =Z41/U41*100 -> -3.6298779 | AB41: -1540.1626 | AC41: =AB41/U41*100 -> -0.062393764 | AD41: 358808 | AE41: =AD41/U41*100 -> 14.535726 | AH41: 75211.029 | AI41: =AH41/U41*100 -> 3.0468855 | AJ41: =HLOOKUP(B41,'RTN-2.2'!$A$5:$AC$164,2,0) -> 1178983.2 | AK41: =HLOOKUP(B41,'RTN-2.2-A'!$A$5:$AC$164,2,0)*100 -> 22.113044 | AN41: =HLOOKUP(B41,'RTN-2.2'!$A$5:$AC$164,3,0) -> 720193.37 | AO41: =HLOOKUP(B41,'RTN-2.2-A'!$A$5:$AC$164,3,0)*100 -> 13.507968 | AR41: =HLOOKUP(B41,'RTN-2.2'!$A$5:$AC$164,15,0) -> 66881.97 | AS41: =HLOOKUP(B41,'RTN-2.2-A'!$A$5:$AC$164,15,0)*100 -> 1.2544402 | AT41: =HLOOKUP(B41,'RTN-2.2'!$A$5:$AC$164,16,0) -> 37035.331 | AU41: =HLOOKUP(B41,'RTN-2.2-A'!$A$5:$AC$164,16,0)*100 -> 0.69463573 | AV41: =HLOOKUP(B41,'RTN-2.2'!$A$5:$AC$164,13,0) -> 114143.61 | AW41: =HLOOKUP(B41,'RTN-2.2-A'!$A$5:$AC$164,13,0)*100 -> 2.1408808 | AZ41: =HLOOKUP(B41,'RTN-2.2'!$A$5:$AC$164,59,0) -> 924929.13 | BA41: =HLOOKUP(B41,'RTN-2.2-A'!$A$5:$AC$164,59,0)*100 -> 17.347998 | BL41: =HLOOKUP(B41,'RTN-2.2'!$A$5:$AC$164,159,0)*(-1) -> 185845.65 | BM41: =HLOOKUP(B41,'RTN-2.2-A'!$A$5:$AC$164,159,0)*100*(-1) -> 3.4857264 | BN41: =HLOOKUP(B41,'RTN-2.2'!$A$5:$AC$164,151,0) -> 72159.145 | BO41: =HLOOKUP(B41,'RTN-2.2-A'!$A$5:$AC$164,151,0)*100 -> 1.353419 | BR41: ='BCB-DBGG-anual'!B9 -> 2747996.7 | BS41: ='BCB-DBGG-anual'!C9 -> 51.541506
B42: 2014 | C42: 5778953 | G42: 0.50395574 | H42: 1148453 | I42: =H42/C42*100 -> 19.873029 | J42: 3638404 | K42: =J42/C42*100 -> 62.959571 | L42: 790183 | M42: =L42/C42*100 -> 13.673463 | N42: 636375 | O42: =N42/C42*100 -> 11.011943 | P42: 6.4074708 | Q42: 11.75 | R42: 23.434708 | S42: 10.64 | T42: 2.67261 | U42: 2454846 | V42: -110493.24 | W42: =V42/U42*100 -> -4.5010254 | X42: 231.47856 | Y42: =X42/U42*100 -> 0.0094294533 | Z42: -108932.09 | AA42: =Z42/U42*100 -> -4.4374305 | AB42: 1329.6771 | AC42: =AB42/U42*100 -> 0.054165397 | AD42: 363551 | AE42: =AD42/U42*100 -> 14.809524 | AH42: 87713.983 | AI42: =AH42/U42*100 -> 3.5730951 | AJ42: =HLOOKUP(B42,'RTN-2.2'!$A$5:$AC$164,2,0) -> 1221474.1 | AK42: =HLOOKUP(B42,'RTN-2.2-A'!$A$5:$AC$164,2,0)*100 -> 21.136599 | AN42: =HLOOKUP(B42,'RTN-2.2'!$A$5:$AC$164,3,0) -> 739178 | AO42: =HLOOKUP(B42,'RTN-2.2-A'!$A$5:$AC$164,3,0)*100 -> 12.790864 | AR42: =HLOOKUP(B42,'RTN-2.2'!$A$5:$AC$164,15,0) -> 73934.249 | AS42: =HLOOKUP(B42,'RTN-2.2-A'!$A$5:$AC$164,15,0)*100 -> 1.279371 | AT42: =HLOOKUP(B42,'RTN-2.2'!$A$5:$AC$164,16,0) -> 41210.966 | AU42: =HLOOKUP(B42,'RTN-2.2-A'!$A$5:$AC$164,16,0)*100 -> 0.71312166 | AV42: =HLOOKUP(B42,'RTN-2.2'!$A$5:$AC$164,13,0) -> 112709 | AW42: =HLOOKUP(B42,'RTN-2.2-A'!$A$5:$AC$164,13,0)*100 -> 1.950336 | AZ42: =HLOOKUP(B42,'RTN-2.2'!$A$5:$AC$164,59,0) -> 1046495 | BA42: =HLOOKUP(B42,'RTN-2.2-A'!$A$5:$AC$164,59,0)*100 -> 18.108731 | BL42: =HLOOKUP(B42,'RTN-2.2'!$A$5:$AC$164,159,0)*(-1) -> 251070.22 | BM42: =HLOOKUP(B42,'RTN-2.2-A'!$A$5:$AC$164,159,0)*100*(-1) -> 4.3445623 | BN42: =HLOOKUP(B42,'RTN-2.2'!$A$5:$AC$164,151,0) -> -23482.403 | BO42: =HLOOKUP(B42,'RTN-2.2-A'!$A$5:$AC$164,151,0)*100 -> -0.40634356 | BR42: ='BCB-DBGG-anual'!B10 -> 3252448.5 | BS42: ='BCB-DBGG-anual'!C10 -> 56.280931
B43: 2015 | C43: 5995787 | G43: -3.5457634 | H43: 1069397 | I43: =H43/C43*100 -> 17.835807 | J43: 3835193 | K43: =J43/C43*100 -> 63.964797 | L43: 842614 | M43: =L43/C43*100 -> 14.053435 | N43: 773468 | O43: =N43/C43*100 -> 12.900191 | P43: 10.673028 | Q43: 14.25 | R43: 29.384044 | S43: 13.17 | T43: 3.92522 | U43: 1796168 | V43: -63408.884 | W43: =V43/U43*100 -> -3.5302313 | X43: 461.15786 | Y43: =X43/U43*100 -> 0.025674539 | Z43: -65429.525 | AA43: =Z43/U43*100 -> -3.6427286 | AB43: -2481.7985 | AC43: =AB43/U43*100 -> -0.13817185 | AD43: 356464 | AE43: =AD43/U43*100 -> 19.845805 | AH43: 64738.153 | AI43: =AH43/U43*100 -> 3.6042371 | AJ43: =HLOOKUP(B43,'RTN-2.2'!$A$5:$AC$164,2,0) -> 1249103.7 | AK43: =HLOOKUP(B43,'RTN-2.2-A'!$A$5:$AC$164,2,0)*100 -> 20.833023 | AN43: =HLOOKUP(B43,'RTN-2.2'!$A$5:$AC$164,3,0) -> 765137.18 | AO43: =HLOOKUP(B43,'RTN-2.2-A'!$A$5:$AC$164,3,0)*100 -> 12.761247 | AR43: =HLOOKUP(B43,'RTN-2.2'!$A$5:$AC$164,15,0) -> 75712.984 | AS43: =HLOOKUP(B43,'RTN-2.2-A'!$A$5:$AC$164,15,0)*100 -> 1.2627697 | AT43: =HLOOKUP(B43,'RTN-2.2'!$A$5:$AC$164,16,0) -> 53648.381 | AU43: =HLOOKUP(B43,'RTN-2.2-A'!$A$5:$AC$164,16,0)*100 -> 0.89476796 | AV43: =HLOOKUP(B43,'RTN-2.2'!$A$5:$AC$164,13,0) -> 107605.09 | AW43: =HLOOKUP(B43,'RTN-2.2-A'!$A$5:$AC$164,13,0)*100 -> 1.7946783 | AZ43: =HLOOKUP(B43,'RTN-2.2'!$A$5:$AC$164,59,0) -> 1164921.7 | BA43: =HLOOKUP(B43,'RTN-2.2-A'!$A$5:$AC$164,59,0)*100 -> 19.429003 | BL43: =HLOOKUP(B43,'RTN-2.2'!$A$5:$AC$164,159,0)*(-1) -> 397240.42 | BM43: =HLOOKUP(B43,'RTN-2.2-A'!$A$5:$AC$164,159,0)*100*(-1) -> 6.6253258 | BN43: =HLOOKUP(B43,'RTN-2.2'!$A$5:$AC$164,151,0) -> -120502.23 | BO43: =HLOOKUP(B43,'RTN-2.2-A'!$A$5:$AC$164,151,0)*100 -> -2.0097816 | BR43: ='BCB-DBGG-anual'!B11 -> 3927523.1 | BS43: ='BCB-DBGG-anual'!C11 -> 65.504713
B44: 2016 | C44: 6269328 | G44: -3.2759169 | H44: 973271 | I44: =H44/C44*100 -> 15.524327 | J44: 4028136 | K44: =J44/C44*100 -> 64.25148 | L44: 756520 | M44: =L44/C44*100 -> 12.067003 | N44: 781577 | O44: =N44/C44*100 -> 12.466679 | P44: 6.2879882 | Q44: 13.75 | R44: 31.836507 | S44: 11.77 | T44: 3.30092 | U44: 1800134 | V44: -30528.825 | W44: =V44/U44*100 -> -1.6959196 | X44: 273.22122 | Y44: =X44/U44*100 -> 0.015177827 | Z44: -22191.681 | AA44: =Z44/U44*100 -> -1.2327794 | AB44: 8063.9234 | AC44: =AB44/U44*100 -> 0.4479624 | AD44: 365016 | AE44: =AD44/U44*100 -> 20.277157 | AH44: 74294.628 | AI44: =AH44/U44*100 -> 4.1271721 | AJ44: =HLOOKUP(B44,'RTN-2.2'!$A$5:$AC$164,2,0) -> 1315985.3 | AK44: =HLOOKUP(B44,'RTN-2.2-A'!$A$5:$AC$164,2,0)*100 -> 20.990851 | AN44: =HLOOKUP(B44,'RTN-2.2'!$A$5:$AC$164,3,0) -> 819751.85 | AO44: =HLOOKUP(B44,'RTN-2.2-A'!$A$5:$AC$164,3,0)*100 -> 13.075594 | AR44: =HLOOKUP(B44,'RTN-2.2'!$A$5:$AC$164,15,0) -> 82165.791 | AS44: =HLOOKUP(B44,'RTN-2.2-A'!$A$5:$AC$164,15,0)*100 -> 1.3105997 | AT44: =HLOOKUP(B44,'RTN-2.2'!$A$5:$AC$164,16,0) -> 59403.682 | AU44: =HLOOKUP(B44,'RTN-2.2-A'!$A$5:$AC$164,16,0)*100 -> 0.9475287 | AV44: =HLOOKUP(B44,'RTN-2.2'!$A$5:$AC$164,13,0) -> 133954.96 | AW44: =HLOOKUP(B44,'RTN-2.2-A'!$A$5:$AC$164,13,0)*100 -> 2.1366717 | AZ44: =HLOOKUP(B44,'RTN-2.2'!$A$5:$AC$164,59,0) -> 1250425.6 | BA44: =HLOOKUP(B44,'RTN-2.2-A'!$A$5:$AC$164,59,0)*100 -> 19.945129 | BL44: =HLOOKUP(B44,'RTN-2.2'!$A$5:$AC$164,159,0)*(-1) -> 318362.14 | BM44: =HLOOKUP(B44,'RTN-2.2-A'!$A$5:$AC$164,159,0)*100*(-1) -> 5.0780904 | BN44: =HLOOKUP(B44,'RTN-2.2'!$A$5:$AC$164,151,0) -> -161275.62 | BO44: =HLOOKUP(B44,'RTN-2.2-A'!$A$5:$AC$164,151,0)*100 -> -2.5724547 | BR44: ='BCB-DBGG-anual'!B12 -> 4378486.4 | BS44: ='BCB-DBGG-anual'!C12 -> 69.839804
B45: 2017 | C45: 6585479 | G45: 1.322869 | H45: 958779 | I45: =H45/C45*100 -> 14.558987 | J45: 4247259 | K45: =J45/C45*100 -> 64.494306 | L45: 777137 | M45: =L45/C45*100 -> 11.800767 | N45: 824434 | O45: =N45/C45*100 -> 12.518968 | P45: 2.9474213 | Q45: 7 | R45: 25.487833 | S45: 6.66 | T45: 3.305 | U45: 2063185 | V45: -25263.599 | W45: =V45/U45*100 -> -1.2244951 | X45: 305.55971 | Y45: =X45/U45*100 -> 0.014810097 | Z45: -20406.386 | AA45: =Z45/U45*100 -> -0.98907204 | AB45: 4551.6529 | AC45: =AB45/U45*100 -> 0.22061293 | AD45: 373972 | AE45: =AD45/U45*100 -> 18.125956 | AH45: 68885.491 | AI45: =AH45/U45*100 -> 3.3387937 | AJ45: =HLOOKUP(B45,'RTN-2.2'!$A$5:$AC$164,2,0) -> 1383653.1 | AK45: =HLOOKUP(B45,'RTN-2.2-A'!$A$5:$AC$164,2,0)*100 -> 21.010668 | AN45: =HLOOKUP(B45,'RTN-2.2'!$A$5:$AC$164,3,0) -> 835563.54 | AO45: =HLOOKUP(B45,'RTN-2.2-A'!$A$5:$AC$164,3,0)*100 -> 12.687969 | AR45: =HLOOKUP(B45,'RTN-2.2'!$A$5:$AC$164,15,0) -> 91045.155 | AS45: =HLOOKUP(B45,'RTN-2.2-A'!$A$5:$AC$164,15,0)*100 -> 1.3825138 | AT45: =HLOOKUP(B45,'RTN-2.2'!$A$5:$AC$164,16,0) -> 59469.811 | AU45: =HLOOKUP(B45,'RTN-2.2-A'!$A$5:$AC$164,16,0)*100 -> 0.90304458 | AV45: =HLOOKUP(B45,'RTN-2.2'!$A$5:$AC$164,13,0) -> 118000.44 | AW45: =HLOOKUP(B45,'RTN-2.2-A'!$A$5:$AC$164,13,0)*100 -> 1.7918278 | AZ45: =HLOOKUP(B45,'RTN-2.2'!$A$5:$AC$164,59,0) -> 1279579.3 | BA45: =HLOOKUP(B45,'RTN-2.2-A'!$A$5:$AC$164,59,0)*100 -> 19.430315 | BL45: =HLOOKUP(B45,'RTN-2.2'!$A$5:$AC$164,159,0)*(-1) -> 340907.29 | BM45: =HLOOKUP(B45,'RTN-2.2-A'!$A$5:$AC$164,159,0)*100*(-1) -> 5.1766514 | BN45: =HLOOKUP(B45,'RTN-2.2'!$A$5:$AC$164,151,0) -> -124261.49 | BO45: =HLOOKUP(B45,'RTN-2.2-A'!$A$5:$AC$164,151,0)*100 -> -1.8869013 | BR45: ='BCB-DBGG-anual'!B13 -> 4854678.6 | BS45: ='BCB-DBGG-anual'!C13 -> 73.717927
B46: 2018 | C46: 7004141 | G46: 1.7836668 | H46: 1057409 | I46: =H46/C46*100 -> 15.096912 | J46: 4525801 | K46: =J46/C46*100 -> 64.616075 | L46: 997474 | M46: =L46/C46*100 -> 14.241204 | N46: 1025056 | O46: =N46/C46*100 -> 14.634999 | P46: 3.7455812 | Q46: 6.5 | R46: 22.998779 | S46: 5.95 | T46: 3.89078 | U46: 1916213 | V46: -53818.304 | W46: =V46/U46*100 -> -2.8085763 | X46: -535.96139 | Y46: =X46/U46*100 -> -0.027969823 | Z46: -55804.832 | AA46: =Z46/U46*100 -> -2.9122458 | AB46: -1450.5663 | AC46: =AB46/U46*100 -> -0.075699637 | AD46: 374715 | AE46: =AD46/U46*100 -> 19.554976 | AH46: 78183.84 | AI46: =AH46/U46*100 -> 4.0801226 | AJ46: =HLOOKUP(B46,'RTN-2.2'!$A$5:$AC$164,2,0) -> 1488999.2 | AK46: =HLOOKUP(B46,'RTN-2.2-A'!$A$5:$AC$164,2,0)*100 -> 21.258841 | AN46: =HLOOKUP(B46,'RTN-2.2'!$A$5:$AC$164,3,0) -> 905052.42 | AO46: =HLOOKUP(B46,'RTN-2.2-A'!$A$5:$AC$164,3,0)*100 -> 12.921676 | AR46: =HLOOKUP(B46,'RTN-2.2'!$A$5:$AC$164,15,0) -> 101613.5 | AS46: =HLOOKUP(B46,'RTN-2.2-A'!$A$5:$AC$164,15,0)*100 -> 1.4507632 | AT46: =HLOOKUP(B46,'RTN-2.2'!$A$5:$AC$164,16,0) -> 53585.498 | AU46: =HLOOKUP(B46,'RTN-2.2-A'!$A$5:$AC$164,16,0)*100 -> 0.76505454 | AV46: =HLOOKUP(B46,'RTN-2.2'!$A$5:$AC$164,13,0) -> 124194.11 | AW46: =HLOOKUP(B46,'RTN-2.2-A'!$A$5:$AC$164,13,0)*100 -> 1.7731527 | AZ46: =HLOOKUP(B46,'RTN-2.2'!$A$5:$AC$164,59,0) -> 1352496.8 | BA46: =HLOOKUP(B46,'RTN-2.2-A'!$A$5:$AC$164,59,0)*100 -> 19.30996 | BL46: =HLOOKUP(B46,'RTN-2.2'!$A$5:$AC$164,159,0)*(-1) -> 310307.13 | BM46: =HLOOKUP(B46,'RTN-2.2-A'!$A$5:$AC$164,159,0)*100*(-1) -> 4.4303381 | BN46: =HLOOKUP(B46,'RTN-2.2'!$A$5:$AC$164,151,0) -> -120221.28 | BO46: =HLOOKUP(B46,'RTN-2.2-A'!$A$5:$AC$164,151,0)*100 -> -1.7164315 | BR46: ='BCB-DBGG-anual'!B14 -> 5271982.3 | BS46: ='BCB-DBGG-anual'!C14 -> 75.269505
B47: 2019 | C47: 7389131 | G47: 1.2207778 | H47: 1143185 | I47: =H47/C47*100 -> 15.47117 | J47: 4813579 | K47: =J47/C47*100 -> 65.144047 | L47: 1091178 | M47: =L47/C47*100 -> 14.767339 | N47: 1043561 | O47: =N47/C47*100 -> 14.122919 | P47: 4.3061516 | Q47: 4.5 | R47: 22.708944 | S47: 5.29 | T47: 4.05975 | U47: 1872800 | V47: -63959.511 | W47: =V47/U47*100 -> -3.4151811 | X47: -2651.3205 | Y47: =X47/U47*100 -> -0.14156987 | Z47: -67347.206 | AA47: =Z47/U47*100 -> -3.5960704 | AB47: -736.37478 | AC47: =AB47/U47*100 -> -0.039319457 | AD47: 356884 | AE47: =AD47/U47*100 -> 19.056173 | AH47: 69174.412 | AI47: =AH47/U47*100 -> 3.6936358 | AJ47: =HLOOKUP(B47,'RTN-2.2'!$A$5:$AC$164,2,0) -> 1635607.9 | AK47: =HLOOKUP(B47,'RTN-2.2-A'!$A$5:$AC$164,2,0)*100 -> 22.135321 | AN47: =HLOOKUP(B47,'RTN-2.2'!$A$5:$AC$164,3,0) -> 946082.86 | AO47: =HLOOKUP(B47,'RTN-2.2-A'!$A$5:$AC$164,3,0)*100 -> 12.803709 | AR47: =HLOOKUP(B47,'RTN-2.2'!$A$5:$AC$164,15,0) -> 116822.87 | AS47: =HLOOKUP(B47,'RTN-2.2-A'!$A$5:$AC$164,15,0)*100 -> 1.5810096 | AT47: =HLOOKUP(B47,'RTN-2.2'!$A$5:$AC$164,16,0) -> 57184.16 | AU47: =HLOOKUP(B47,'RTN-2.2-A'!$A$5:$AC$164,16,0)*100 -> 0.77389561 | AV47: =HLOOKUP(B47,'RTN-2.2'!$A$5:$AC$164,13,0) -> 131462.43 | AW47: =HLOOKUP(B47,'RTN-2.2-A'!$A$5:$AC$164,13,0)*100 -> 1.7791325 | AZ47: =HLOOKUP(B47,'RTN-2.2'!$A$5:$AC$164,59,0) -> 1442341.8 | BA47: =HLOOKUP(B47,'RTN-2.2-A'!$A$5:$AC$164,59,0)*100 -> 19.519776 | BL47: =HLOOKUP(B47,'RTN-2.2'!$A$5:$AC$164,159,0)*(-1) -> 310115.06 | BM47: =HLOOKUP(B47,'RTN-2.2-A'!$A$5:$AC$164,159,0)*100*(-1) -> 4.1969085 | BN47: =HLOOKUP(B47,'RTN-2.2'!$A$5:$AC$164,151,0) -> -95064.747 | BO47: =HLOOKUP(B47,'RTN-2.2-A'!$A$5:$AC$164,151,0)*100 -> -1.2865484 | BR47: ='BCB-DBGG-anual'!B15 -> 5500104.2 | BS47: ='BCB-DBGG-anual'!C15 -> 74.435061
B48: 2020 | C48: 7609597 | G48: -3.2767588 | H48: 1260227 | I48: =H48/C48*100 -> 16.561022 | J48: 4805004 | K48: =J48/C48*100 -> 63.144001 | L48: 1206009 | M48: =L48/C48*100 -> 15.848527 | N48: 1252049 | O48: =N48/C48*100 -> 16.453552 | P48: 4.5174569 | Q48: 2 | R48: 18.295818 | S48: 4.35 | T48: 5.16449 | U48: 1475529 | V48: -24223.442 | W48: =V48/U48*100 -> -1.6416785 | X48: 846.88194 | Y48: =X48/U48*100 -> 0.05739514 | Z48: -16260.263 | AA48: =Z48/U48*100 -> -1.1019955 | AB48: 7116.2973 | AC48: =AB48/U48*100 -> 0.48228786 | AD48: 355620 | AE48: =AD48/U48*100 -> 24.101187 | AH48: 38270.116 | AI48: =AH48/U48*100 -> 2.593654 | AJ48: =HLOOKUP(B48,'RTN-2.2'!$A$5:$AC$164,2,0) -> 1468096.1 | AK48: =HLOOKUP(B48,'RTN-2.2-A'!$A$5:$AC$164,2,0)*100 -> 19.292692 | AN48: =HLOOKUP(B48,'RTN-2.2'!$A$5:$AC$164,3,0) -> 899522.51 | AO48: =HLOOKUP(B48,'RTN-2.2-A'!$A$5:$AC$164,3,0)*100 -> 11.820895 | AR48: =HLOOKUP(B48,'RTN-2.2'!$A$5:$AC$164,15,0) -> 114819.77 | AS48: =HLOOKUP(B48,'RTN-2.2-A'!$A$5:$AC$164,15,0)*100 -> 1.508881 | AT48: =HLOOKUP(B48,'RTN-2.2'!$A$5:$AC$164,16,0) -> 48346.122 | AU48: =HLOOKUP(B48,'RTN-2.2-A'!$A$5:$AC$164,16,0)*100 -> 0.63533091 | AV48: =HLOOKUP(B48,'RTN-2.2'!$A$5:$AC$164,13,0) -> 126635.39 | AW48: =HLOOKUP(B48,'RTN-2.2-A'!$A$5:$AC$164,13,0)*100 -> 1.6641537 | AZ48: =HLOOKUP(B48,'RTN-2.2'!$A$5:$AC$164,59,0) -> 1947552.9 | BA48: =HLOOKUP(B48,'RTN-2.2-A'!$A$5:$AC$164,59,0)*100 -> 25.593378 | BL48: =HLOOKUP(B48,'RTN-2.2'!$A$5:$AC$164,159,0)*(-1) -> 266657.22 | BM48: =HLOOKUP(B48,'RTN-2.2-A'!$A$5:$AC$164,159,0)*100*(-1) -> 3.5042227 | BN48: =HLOOKUP(B48,'RTN-2.2'!$A$5:$AC$164,151,0) -> -743254.82 | BO48: =HLOOKUP(B48,'RTN-2.2-A'!$A$5:$AC$164,151,0)*100 -> -9.7673348 | BR48: ='BCB-DBGG-anual'!B16 -> 6615755.2 | BS48: ='BCB-DBGG-anual'!C16 -> 86.939626
B49: 2021 | C49: 9012142 | G49: 4.7626044 | H49: 1614782 | I49: =H49/C49*100 -> 17.917849 | J49: 5530571 | K49: =J49/C49*100 -> 61.367997 | L49: 1671473 | M49: =L49/C49*100 -> 18.5469 | N49: 1722169 | O49: =N49/C49*100 -> 19.10943 | P49: 10.060983 | Q49: 9.25 | R49: 24.310818 | S49: 9.27 | T49: 5.66446 | U49: 1670493 | V49: -39397.557 | W49: =V49/U49*100 -> -2.3584389 | X49: -5723.4605 | Y49: =X49/U49*100 -> -0.34262104 | Z49: -50167.884 | AA49: =Z49/U49*100 -> -3.0031784 | AB49: -5046.8665 | AC49: =AB49/U49*100 -> -0.30211839 | AD49: 362204 | AE49: =AD49/U49*100 -> 21.682461 | AH49: 46440.504 | AI49: =AH49/U49*100 -> 2.7800478 | AJ49: =HLOOKUP(B49,'RTN-2.2'!$A$5:$AC$164,2,0) -> 1932649.7 | AK49: =HLOOKUP(B49,'RTN-2.2-A'!$A$5:$AC$164,2,0)*100 -> 21.444954 | AN49: =HLOOKUP(B49,'RTN-2.2'!$A$5:$AC$164,3,0) -> 1195712.3 | AO49: =HLOOKUP(B49,'RTN-2.2-A'!$A$5:$AC$164,3,0)*100 -> 13.267793 | AR49: =HLOOKUP(B49,'RTN-2.2'!$A$5:$AC$164,15,0) -> 130681.79 | AS49: =HLOOKUP(B49,'RTN-2.2-A'!$A$5:$AC$164,15,0)*100 -> 1.4500636 | AT49: =HLOOKUP(B49,'RTN-2.2'!$A$5:$AC$164,16,0) -> 55575.662 | AU49: =HLOOKUP(B49,'RTN-2.2-A'!$A$5:$AC$164,16,0)*100 -> 0.61667539 | AV49: =HLOOKUP(B49,'RTN-2.2'!$A$5:$AC$164,13,0) -> 214466.79 | AW49: =HLOOKUP(B49,'RTN-2.2-A'!$A$5:$AC$164,13,0)*100 -> 2.3797538 | AZ49: =HLOOKUP(B49,'RTN-2.2'!$A$5:$AC$164,59,0) -> 1614170.8 | BA49: =HLOOKUP(B49,'RTN-2.2-A'!$A$5:$AC$164,59,0)*100 -> 17.911067 | BL49: =HLOOKUP(B49,'RTN-2.2'!$A$5:$AC$164,159,0)*(-1) -> 407282.24 | BM49: =HLOOKUP(B49,'RTN-2.2-A'!$A$5:$AC$164,159,0)*100*(-1) -> 4.5192612 | BN49: =HLOOKUP(B49,'RTN-2.2'!$A$5:$AC$164,151,0) -> -35067.934 | BO49: =HLOOKUP(B49,'RTN-2.2-A'!$A$5:$AC$164,151,0)*100 -> -0.38911875 | BR49: ='BCB-DBGG-anual'!B17 -> 6966925.2 | BS49: ='BCB-DBGG-anual'!C17 -> 77.305986
B50: 2022 | C50: 10079677 | G50: 3.0166944 | H50: 1794223 | I50: =H50/C50*100 -> 17.800402 | J50: 6356657.7 | K50: =J50/C50*100 -> 63.064103 | L50: 1933816.3 | M50: =L50/C50*100 -> 19.185301 | N50: 1978717.6 | O50: =N50/C50*100 -> 19.630765 | P50: 5.7850929 | Q50: 13.75 | R50: 29.688298 | S50: 12.39 | T50: 5.22728 | U50: 1951572 | V50: -41960.06 | W50: =V50/U50*100 -> -2.1500647 | X50: -7123.9354 | Y50: =X50/U50*100 -> -0.36503574 | Z50: -49148.116 | AA50: =Z50/U50*100 -> -2.518386 | AB50: -64.120887 | AC50: =AB50/U50*100 -> -0.0032856019 | AD50: 324703 | AE50: =AD50/U50*100 -> 16.638023 | AH50: 75501.039 | AI50: =AH50/U50*100 -> 3.8687293 | AJ50: =HLOOKUP(B50,'RTN-2.2'!$A$5:$AC$164,2,0) -> 2313305.4 | AK50: =HLOOKUP(B50,'RTN-2.2-A'!$A$5:$AC$164,2,0)*100 -> 22.950195 | AN50: =HLOOKUP(B50,'RTN-2.2'!$A$5:$AC$164,3,0) -> 1390000.4 | AO50: =HLOOKUP(B50,'RTN-2.2-A'!$A$5:$AC$164,3,0)*100 -> 13.790129 | AR50: =HLOOKUP(B50,'RTN-2.2'!$A$5:$AC$164,15,0) -> 153160.51 | AS50: =HLOOKUP(B50,'RTN-2.2-A'!$A$5:$AC$164,15,0)*100 -> 1.5194983 | AT50: =HLOOKUP(B50,'RTN-2.2'!$A$5:$AC$164,16,0) -> 97046.628 | AU50: =HLOOKUP(B50,'RTN-2.2-A'!$A$5:$AC$164,16,0)*100 -> 0.96279505 | AV50: =HLOOKUP(B50,'RTN-2.2'!$A$5:$AC$164,13,0) -> 286330.2 | AW50: =HLOOKUP(B50,'RTN-2.2-A'!$A$5:$AC$164,13,0)*100 -> 2.8406685 | AZ50: =HLOOKUP(B50,'RTN-2.2'!$A$5:$AC$164,59,0) -> 1809693.1 | BA50: =HLOOKUP(B50,'RTN-2.2-A'!$A$5:$AC$164,59,0)*100 -> 17.95388 | BL50: =HLOOKUP(B50,'RTN-2.2'!$A$5:$AC$164,159,0)*(-1) -> 503234.4 | BM50: =HLOOKUP(B50,'RTN-2.2-A'!$A$5:$AC$164,159,0)*100*(-1) -> 4.9925649 | BN50: =HLOOKUP(B50,'RTN-2.2'!$A$5:$AC$164,151,0) -> 46408.462 | BO50: =HLOOKUP(B50,'RTN-2.2-A'!$A$5:$AC$164,151,0)*100 -> 0.46041617 | BR50: ='BCB-DBGG-anual'!B18 -> 7224882.2 | BS50: ='BCB-DBGG-anual'!C18 -> 71.677718
B51: 2023 | C51: 10943345 | G51: 3.2416553 | H51: 1795909.6 | I51: =H51/C51*100 -> 16.410975 | J51: 6886025.6 | K51: =J51/C51*100 -> 62.924323 | L51: 1717766.5 | M51: =L51/C51*100 -> 15.696906 | N51: 1966445.1 | O51: =N51/C51*100 -> 17.969324 | P51: 4.62119 | Q51: 11.75 | R51: 28.17356 | S51: 3.09 | T51: 4.87099 | U51: 2190991 | V51: -27073.227 | W51: =V51/U51*100 -> -1.2356613 | X51: -11365.728 | Y51: =X51/U51*100 -> -0.51874828 | Z51: -38388.92 | AA51: =Z51/U51*100 -> -1.7521259 | AB51: 50.034806 | AC51: =AB51/U51*100 -> 0.002283661 | AD51: 355034 | AE51: =AD51/U51*100 -> 16.204266 | AH51: 62750.364 | AI51: =AH51/U51*100 -> 2.8640174 | AJ51: =HLOOKUP(B51,'RTN-2.2'!$A$5:$AC$164,2,0) -> 2353432.2 | AK51: =HLOOKUP(B51,'RTN-2.2-A'!$A$5:$AC$164,2,0)*100 -> 21.505603 | AN51: =HLOOKUP(B51,'RTN-2.2'!$A$5:$AC$164,3,0) -> 1439302.6 | AO51: =HLOOKUP(B51,'RTN-2.2-A'!$A$5:$AC$164,3,0)*100 -> 13.15231 | AR51: =HLOOKUP(B51,'RTN-2.2'!$A$5:$AC$164,15,0) -> 164752.2 | AS51: =HLOOKUP(B51,'RTN-2.2-A'!$A$5:$AC$164,15,0)*100 -> 1.5055013 | AT51: =HLOOKUP(B51,'RTN-2.2'!$A$5:$AC$164,16,0) -> 123815.55 | AU51: =HLOOKUP(B51,'RTN-2.2-A'!$A$5:$AC$164,16,0)*100 -> 1.1314233 | AV51: =HLOOKUP(B51,'RTN-2.2'!$A$5:$AC$164,13,0) -> 261802.26 | AW51: =HLOOKUP(B51,'RTN-2.2-A'!$A$5:$AC$164,13,0)*100 -> 2.3923423 | AZ51: =HLOOKUP(B51,'RTN-2.2'!$A$5:$AC$164,59,0) -> 2129922.5 | BA51: =HLOOKUP(B51,'RTN-2.2-A'!$A$5:$AC$164,59,0)*100 -> 19.463177 | BL51: =HLOOKUP(B51,'RTN-2.2'!$A$5:$AC$164,159,0)*(-1) -> 614548.09 | BM51: =HLOOKUP(B51,'RTN-2.2-A'!$A$5:$AC$164,159,0)*100*(-1) -> 5.6157245 | BN51: =HLOOKUP(B51,'RTN-2.2'!$A$5:$AC$164,151,0) -> -228499.38 | BO51: =HLOOKUP(B51,'RTN-2.2-A'!$A$5:$AC$164,151,0)*100 -> -2.0880214 | BR51: ='BCB-DBGG-anual'!B19 -> 8079270 | BS51: ='BCB-DBGG-anual'!C19 -> 73.82816
B52: 2024 | C52: 11744710 | G52: 3.3958665 | H52: 2000465.5 | I52: =H52/C52*100 -> 17.032906 | J52: 7489876.4 | K52: =J52/C52*100 -> 63.77234 | L52: 2057266.9 | M52: =L52/C52*100 -> 17.51654 | N52: 2115771.9 | O52: =N52/C52*100 -> 18.01468 | P52: 4.8311967 | Q52: 12.25 | R52: 28.475204 | T52: 6.16576 | U52: 2178416 | V52: -66168.31 | W52: =V52/U52*100 -> -3.0374506 | X52: -16269.902 | Y52: =X52/U52*100 -> -0.74686846 | Z52: -88178.152 | AA52: =Z52/U52*100 -> -4.0478105 | AB52: -5739.9395 | AC52: =AB52/U52*100 -> -0.26349143 | AD52: 329730 | AE52: =AD52/U52*100 -> 15.136227 | AH52: 74090.786 | AI52: =AH52/U52*100 -> 3.4011312 | AJ52: =HLOOKUP(B52,'RTN-2.2'!$A$5:$AC$164,2,0) -> 2679441.6 | AK52: =HLOOKUP(B52,'RTN-2.2-A'!$A$5:$AC$164,2,0)*100 -> 22.814029 | AN52: =HLOOKUP(B52,'RTN-2.2'!$A$5:$AC$164,3,0) -> 1690020.4 | AO52: =HLOOKUP(B52,'RTN-2.2-A'!$A$5:$AC$164,3,0)*100 -> 14.389631 | AR52: =HLOOKUP(B52,'RTN-2.2'!$A$5:$AC$164,15,0) -> 184368.41 | AS52: =HLOOKUP(B52,'RTN-2.2-A'!$A$5:$AC$164,15,0)*100 -> 1.5697996 | AT52: =HLOOKUP(B52,'RTN-2.2'!$A$5:$AC$164,16,0) -> 147041.58 | AU52: =HLOOKUP(B52,'RTN-2.2-A'!$A$5:$AC$164,16,0)*100 -> 1.2519814 | AV52: =HLOOKUP(B52,'RTN-2.2'!$A$5:$AC$164,13,0) -> 280437.59 | AW52: =HLOOKUP(B52,'RTN-2.2-A'!$A$5:$AC$164,13,0)*100 -> 2.3877779 | AZ52: =HLOOKUP(B52,'RTN-2.2'!$A$5:$AC$164,59,0) -> 2204711.3 | BA52: =HLOOKUP(B52,'RTN-2.2-A'!$A$5:$AC$164,59,0)*100 -> 18.771952 | BL52: =HLOOKUP(B52,'RTN-2.2'!$A$5:$AC$164,159,0)*(-1) -> 855206.35 | BM52: =HLOOKUP(B52,'RTN-2.2-A'!$A$5:$AC$164,159,0)*100*(-1) -> 7.2816302 | BN52: =HLOOKUP(B52,'RTN-2.2'!$A$5:$AC$164,151,0) -> -42923.692 | BO52: =HLOOKUP(B52,'RTN-2.2-A'!$A$5:$AC$164,151,0)*100 -> -0.36547255 | BP52: =HLOOKUP(B52,'STN-RPF-Tabela 1'!$A$4:$M$73,64,0)*1000 -> -47552.864 | BQ52: =HLOOKUP(B52,'STN-RPF-Tabela 2'!$A$4:$M$73,64,0) -> -0.40488751 | BR52: ='BCB-DBGG-anual'!B20 -> 8984236.6 | BS52: ='BCB-DBGG-anual'!C20 -> 76.496027
A53: Completar con los pronósticos que se tengan en caso de estar disponibles | B53: 2025 | AJ53: =HLOOKUP(B53,'STN-RPF-Tabela 1'!$A$4:$M$73,2,0)*1000 -> 2929954.5 | AK53: =HLOOKUP(B53,'STN-RPF-Tabela 2'!$A$4:$M$73,2,0) -> 23.022474 | AN53: =HLOOKUP(B53,'STN-RPF-Tabela 1'!$A$4:$M$73,3,0)*1000 -> 1878239.5 | AO53: =HLOOKUP(B53,'STN-RPF-Tabela 2'!$A$4:$M$73,3,0) -> 14.758496 | AR53: =HLOOKUP(B53,'STN-RPF-Tabela 1'!$A$4:$M$73,15,0)*1000 -> 203726.85 | AS53: =HLOOKUP(B53,'STN-RPF-Tabela 2'!$A$4:$M$73,15,0) -> 1.6008085 | AT53: =HLOOKUP(B53,'STN-RPF-Tabela 1'!$A$4:$M$73,16,0)*1000 -> 163891.99 | AU53: =HLOOKUP(B53,'STN-RPF-Tabela 2'!$A$4:$M$73,16,0) -> 1.2878013 | AV53: =HLOOKUP(B53,'STN-RPF-Tabela 1'!$A$4:$M$73,13,0)*1000 -> 316569.53 | AW53: =HLOOKUP(B53,'STN-RPF-Tabela 2'!$A$4:$M$73,13,0) -> 2.4874836 | AZ53: =HLOOKUP(B53,'STN-RPF-Tabela 1'!$A$4:$M$73,48,0)*1000 -> 2394678.6 | BA53: =HLOOKUP(B53,'STN-RPF-Tabela 2'!$A$4:$M$73,48,0) -> 18.816478 | BL53: =HLOOKUP(B53,'STN-RPF-Tabela 1'!$A$4:$M$73,66,0)*1000 -> 1115333.4 | BM53: =HLOOKUP(B53,'STN-RPF-Tabela 2'!$A$4:$M$73,66,0) -> 8.7638684 | BN53: =HLOOKUP(B53,'STN-RPF-Tabela 1'!$A$4:$M$73,61,0)*1000 -> -45323.068 | BO53: =HLOOKUP(B53,'STN-RPF-Tabela 2'!$A$4:$M$73,61,0) -> -0.35613153 | BP53: =HLOOKUP(B53,'STN-RPF-Tabela 1'!$A$4:$M$73,64,0)*1000 -> -33191.482 | BQ53: =HLOOKUP(B53,'STN-RPF-Tabela 2'!$A$4:$M$73,64,0) -> -0.26080611 | BR53: ='BCB-DBGG-anual'!B21 -> 10122813 | BS53: ='BCB-DBGG-anual'!C21 -> 78.970214
B54: 2026 | AJ54: =HLOOKUP(B54,'STN-RPF-Tabela 1'!$A$4:$M$73,2,0)*1000 -> 3198282.2 | AK54: =HLOOKUP(B54,'STN-RPF-Tabela 2'!$A$4:$M$73,2,0) -> 23.317381 | AN54: =HLOOKUP(B54,'STN-RPF-Tabela 1'!$A$4:$M$73,3,0)*1000 -> 2045283 | AO54: =HLOOKUP(B54,'STN-RPF-Tabela 2'!$A$4:$M$73,3,0) -> 14.91133 | AR54: =HLOOKUP(B54,'STN-RPF-Tabela 1'!$A$4:$M$73,15,0)*1000 -> 223519.05 | AS54: =HLOOKUP(B54,'STN-RPF-Tabela 2'!$A$4:$M$73,15,0) -> 1.6295869 | AT54: =HLOOKUP(B54,'STN-RPF-Tabela 1'!$A$4:$M$73,16,0)*1000 -> 185903.2 | AU54: =HLOOKUP(B54,'STN-RPF-Tabela 2'!$A$4:$M$73,16,0) -> 1.355345 | AV54: =HLOOKUP(B54,'STN-RPF-Tabela 1'!$A$4:$M$73,13,0)*1000 -> 335574.31 | AW54: =HLOOKUP(B54,'STN-RPF-Tabela 2'!$A$4:$M$73,13,0) -> 2.4465365 | AZ54: =HLOOKUP(B54,'STN-RPF-Tabela 1'!$A$4:$M$73,48,0)*1000 -> 2601442.2 | BA54: =HLOOKUP(B54,'STN-RPF-Tabela 2'!$A$4:$M$73,48,0) -> 18.966062 | BL54: =HLOOKUP(B54,'STN-RPF-Tabela 1'!$A$4:$M$73,66,0)*1000 -> 1143546.9 | BM54: =HLOOKUP(B54,'STN-RPF-Tabela 2'!$A$4:$M$73,66,0) -> 8.3371375 | BN54: =HLOOKUP(B54,'STN-RPF-Tabela 1'!$A$4:$M$73,61,0)*1000 -> -26471.266 | BO54: =HLOOKUP(B54,'STN-RPF-Tabela 2'!$A$4:$M$73,61,0) -> -0.19299129 | BP54: =HLOOKUP(B54,'STN-RPF-Tabela 1'!$A$4:$M$73,64,0)*1000 -> -32056.403 | BQ54: =HLOOKUP(B54,'STN-RPF-Tabela 2'!$A$4:$M$73,64,0) -> -0.23371026 | BR54: ='BCB-DBGG-anual'!B22 -> 11406904 | BS54: ='BCB-DBGG-anual'!C22 -> 82.501529
B55: 2027 | AJ55: =HLOOKUP(B55,'STN-RPF-Tabela 1'!$A$4:$M$73,2,0)*1000 -> 3419593.9 | AK55: =HLOOKUP(B55,'STN-RPF-Tabela 2'!$A$4:$M$73,2,0) -> 23.196804 | AN55: =HLOOKUP(B55,'STN-RPF-Tabela 1'!$A$4:$M$73,3,0)*1000 -> 2163118.5 | AO55: =HLOOKUP(B55,'STN-RPF-Tabela 2'!$A$4:$M$73,3,0) -> 14.673507 | AR55: =HLOOKUP(B55,'STN-RPF-Tabela 1'!$A$4:$M$73,15,0)*1000 -> 240518.12 | AS55: =HLOOKUP(B55,'STN-RPF-Tabela 2'!$A$4:$M$73,15,0) -> 1.6315539 | AT55: =HLOOKUP(B55,'STN-RPF-Tabela 1'!$A$4:$M$73,16,0)*1000 -> 173389.52 | AU55: =HLOOKUP(B55,'STN-RPF-Tabela 2'!$A$4:$M$73,16,0) -> 1.1761872 | AV55: =HLOOKUP(B55,'STN-RPF-Tabela 1'!$A$4:$M$73,13,0)*1000 -> 357423.03 | AW55: =HLOOKUP(B55,'STN-RPF-Tabela 2'!$A$4:$M$73,13,0) -> 2.4245779 | AZ55: =HLOOKUP(B55,'STN-RPF-Tabela 1'!$A$4:$M$73,48,0)*1000 -> 2696219.2 | BA55: =HLOOKUP(B55,'STN-RPF-Tabela 2'!$A$4:$M$73,48,0) -> 18.289794 | BL55: =HLOOKUP(B55,'STN-RPF-Tabela 1'!$A$4:$M$73,66,0)*1000 -> 1100961.5 | BM55: =HLOOKUP(B55,'STN-RPF-Tabela 2'!$A$4:$M$73,66,0) -> 7.4683686 | BN55: =HLOOKUP(B55,'STN-RPF-Tabela 1'!$A$4:$M$73,61,0)*1000 -> 73708.298 | BO55: =HLOOKUP(B55,'STN-RPF-Tabela 2'!$A$4:$M$73,61,0) -> 0.5 | BP55: =HLOOKUP(B55,'STN-RPF-Tabela 1'!$A$4:$M$73,64,0)*1000 -> 67835.185 | BQ55: =HLOOKUP(B55,'STN-RPF-Tabela 2'!$A$4:$M$73,64,0) -> 0.46015975 | BR55: ='BCB-DBGG-anual'!B23 -> 12503855 | BS55: ='BCB-DBGG-anual'!C23 -> 83.932155
B56: 2028 | AJ56: =HLOOKUP(B56,'STN-RPF-Tabela 1'!$A$4:$M$73,2,0)*1000 -> 3680509.4 | AK56: =HLOOKUP(B56,'STN-RPF-Tabela 2'!$A$4:$M$73,2,0) -> 23.27634 | AN56: =HLOOKUP(B56,'STN-RPF-Tabela 1'!$A$4:$M$73,3,0)*1000 -> 2273043.8 | AO56: =HLOOKUP(B56,'STN-RPF-Tabela 2'!$A$4:$M$73,3,0) -> 14.375222 | AR56: =HLOOKUP(B56,'STN-RPF-Tabela 1'!$A$4:$M$73,15,0)*1000 -> 257843.44 | AS56: =HLOOKUP(B56,'STN-RPF-Tabela 2'!$A$4:$M$73,15,0) -> 1.6306579 | AT56: =HLOOKUP(B56,'STN-RPF-Tabela 1'!$A$4:$M$73,16,0)*1000 -> 163276.44 | AU56: =HLOOKUP(B56,'STN-RPF-Tabela 2'!$A$4:$M$73,16,0) -> 1.0325957 | AV56: =HLOOKUP(B56,'STN-RPF-Tabela 1'!$A$4:$M$73,13,0)*1000 -> 378645.72 | AW56: =HLOOKUP(B56,'STN-RPF-Tabela 2'!$A$4:$M$73,13,0) -> 2.3946377 | AZ56: =HLOOKUP(B56,'STN-RPF-Tabela 1'!$A$4:$M$73,48,0)*1000 -> 2847175.4 | BA56: =HLOOKUP(B56,'STN-RPF-Tabela 2'!$A$4:$M$73,48,0) -> 18.006155 | BL56: =HLOOKUP(B56,'STN-RPF-Tabela 1'!$A$4:$M$73,66,0)*1000 -> 1032741.5 | BM56: =HLOOKUP(B56,'STN-RPF-Tabela 2'!$A$4:$M$73,66,0) -> 6.531281 | BN56: =HLOOKUP(B56,'STN-RPF-Tabela 1'!$A$4:$M$73,61,0)*1000 -> 158122.34 | BO56: =HLOOKUP(B56,'STN-RPF-Tabela 2'!$A$4:$M$73,61,0) -> 1 | BP56: =HLOOKUP(B56,'STN-RPF-Tabela 1'!$A$4:$M$73,64,0)*1000 -> 152601.47 | BQ56: =HLOOKUP(B56,'STN-RPF-Tabela 2'!$A$4:$M$73,64,0) -> 0.96508481 | BR56: ='BCB-DBGG-anual'!B24 -> 13467207 | BS56: ='BCB-DBGG-anual'!C24 -> 84.160738
B57: 2029 | AJ57: =HLOOKUP(B57,'STN-RPF-Tabela 1'!$A$4:$M$73,2,0)*1000 -> 3952236.9 | AK57: =HLOOKUP(B57,'STN-RPF-Tabela 2'!$A$4:$M$73,2,0) -> 23.297793 | AN57: =HLOOKUP(B57,'STN-RPF-Tabela 1'!$A$4:$M$73,3,0)*1000 -> 2418267.1 | AO57: =HLOOKUP(B57,'STN-RPF-Tabela 2'!$A$4:$M$73,3,0) -> 14.255291 | AR57: =HLOOKUP(B57,'STN-RPF-Tabela 1'!$A$4:$M$73,15,0)*1000 -> 275870.38 | AS57: =HLOOKUP(B57,'STN-RPF-Tabela 2'!$A$4:$M$73,15,0) -> 1.626211 | AT57: =HLOOKUP(B57,'STN-RPF-Tabela 1'!$A$4:$M$73,16,0)*1000 -> 162504.1 | AU57: =HLOOKUP(B57,'STN-RPF-Tabela 2'!$A$4:$M$73,16,0) -> 0.95793524 | AV57: =HLOOKUP(B57,'STN-RPF-Tabela 1'!$A$4:$M$73,13,0)*1000 -> 406236.25 | AW57: =HLOOKUP(B57,'STN-RPF-Tabela 2'!$A$4:$M$73,13,0) -> 2.3946966 | AZ57: =HLOOKUP(B57,'STN-RPF-Tabela 1'!$A$4:$M$73,48,0)*1000 -> 3027550 | BA57: =HLOOKUP(B57,'STN-RPF-Tabela 2'!$A$4:$M$73,48,0) -> 17.846915 | BL57: =HLOOKUP(B57,'STN-RPF-Tabela 1'!$A$4:$M$73,66,0)*1000 -> 1049531.9 | BM57: =HLOOKUP(B57,'STN-RPF-Tabela 2'!$A$4:$M$73,66,0) -> 6.1868198 | BN57: =HLOOKUP(B57,'STN-RPF-Tabela 1'!$A$4:$M$73,61,0)*1000 -> 212049.96 | BO57: =HLOOKUP(B57,'STN-RPF-Tabela 2'!$A$4:$M$73,61,0) -> 1.25 | BP57: =HLOOKUP(B57,'STN-RPF-Tabela 1'!$A$4:$M$73,64,0)*1000 -> 206871.64 | BQ57: =HLOOKUP(B57,'STN-RPF-Tabela 2'!$A$4:$M$73,64,0) -> 1.2194747 | BR57: ='BCB-DBGG-anual'!B25 -> 14403311 | BS57: ='BCB-DBGG-anual'!C25 -> 83.788093
B58: 2030 | AJ58: =HLOOKUP(B58,'STN-RPF-Tabela 1'!$A$4:$M$73,2,0)*1000 -> 4219707.3 | AK58: =HLOOKUP(B58,'STN-RPF-Tabela 2'!$A$4:$M$73,2,0) -> 23.226412 | AN58: =HLOOKUP(B58,'STN-RPF-Tabela 1'!$A$4:$M$73,3,0)*1000 -> 2590032 | AO58: =HLOOKUP(B58,'STN-RPF-Tabela 2'!$A$4:$M$73,3,0) -> 14.256238 | AR58: =HLOOKUP(B58,'STN-RPF-Tabela 1'!$A$4:$M$73,15,0)*1000 -> 294925.32 | AS58: =HLOOKUP(B58,'STN-RPF-Tabela 2'!$A$4:$M$73,15,0) -> 1.6233489 | AT58: =HLOOKUP(B58,'STN-RPF-Tabela 1'!$A$4:$M$73,16,0)*1000 -> 171772.62 | AU58: =HLOOKUP(B58,'STN-RPF-Tabela 2'!$A$4:$M$73,16,0) -> 0.94548306 | AV58: =HLOOKUP(B58,'STN-RPF-Tabela 1'!$A$4:$M$73,13,0)*1000 -> 443627.18 | AW58: =HLOOKUP(B58,'STN-RPF-Tabela 2'!$A$4:$M$73,13,0) -> 2.4418442 | AZ58: =HLOOKUP(B58,'STN-RPF-Tabela 1'!$A$4:$M$73,48,0)*1000 -> 3234632 | BA58: =HLOOKUP(B58,'STN-RPF-Tabela 2'!$A$4:$M$73,48,0) -> 17.804291 | BL58: =HLOOKUP(B58,'STN-RPF-Tabela 1'!$A$4:$M$73,66,0)*1000 -> 1098773.2 | BM58: =HLOOKUP(B58,'STN-RPF-Tabela 2'!$A$4:$M$73,66,0) -> 6.0479457 | BN58: =HLOOKUP(B58,'STN-RPF-Tabela 1'!$A$4:$M$73,61,0)*1000 -> 227096.38 | BO58: =HLOOKUP(B58,'STN-RPF-Tabela 2'!$A$4:$M$73,61,0) -> 1.25 | BP58: =HLOOKUP(B58,'STN-RPF-Tabela 1'!$A$4:$M$73,64,0)*1000 -> 222271.5 | BQ58: =HLOOKUP(B58,'STN-RPF-Tabela 2'!$A$4:$M$73,64,0) -> 1.2234426 | BR58: ='BCB-DBGG-anual'!B26 -> 15370313 | BS58: ='BCB-DBGG-anual'!C26 -> 83.404023
B59: 2031 | AJ59: =HLOOKUP(B59,'STN-RPF-Tabela 1'!$A$4:$M$73,2,0)*1000 -> 4510938 | AK59: =HLOOKUP(B59,'STN-RPF-Tabela 2'!$A$4:$M$73,2,0) -> 23.208585 | AN59: =HLOOKUP(B59,'STN-RPF-Tabela 1'!$A$4:$M$73,3,0)*1000 -> 2790520.5 | AO59: =HLOOKUP(B59,'STN-RPF-Tabela 2'!$A$4:$M$73,3,0) -> 14.35711 | AR59: =HLOOKUP(B59,'STN-RPF-Tabela 1'!$A$4:$M$73,15,0)*1000 -> 314984.93 | AS59: =HLOOKUP(B59,'STN-RPF-Tabela 2'!$A$4:$M$73,15,0) -> 1.6205841 | AT59: =HLOOKUP(B59,'STN-RPF-Tabela 1'!$A$4:$M$73,16,0)*1000 -> 183077.97 | AU59: =HLOOKUP(B59,'STN-RPF-Tabela 2'!$A$4:$M$73,16,0) -> 0.9419284 | AV59: =HLOOKUP(B59,'STN-RPF-Tabela 1'!$A$4:$M$73,13,0)*1000 -> 471380.04 | AW59: =HLOOKUP(B59,'STN-RPF-Tabela 2'!$A$4:$M$73,13,0) -> 2.4252303 | AZ59: =HLOOKUP(B59,'STN-RPF-Tabela 1'!$A$4:$M$73,48,0)*1000 -> 3451643.3 | BA59: =HLOOKUP(B59,'STN-RPF-Tabela 2'!$A$4:$M$73,48,0) -> 17.758558 | BL59: =HLOOKUP(B59,'STN-RPF-Tabela 1'!$A$4:$M$73,66,0)*1000 -> 1154702.5 | BM59: =HLOOKUP(B59,'STN-RPF-Tabela 2'!$A$4:$M$73,66,0) -> 5.9408952 | BN59: =HLOOKUP(B59,'STN-RPF-Tabela 1'!$A$4:$M$73,61,0)*1000 -> 242956.33 | BO59: =HLOOKUP(B59,'STN-RPF-Tabela 2'!$A$4:$M$73,61,0) -> 1.25 | BP59: =HLOOKUP(B59,'STN-RPF-Tabela 1'!$A$4:$M$73,64,0)*1000 -> 238074.96 | BQ59: =HLOOKUP(B59,'STN-RPF-Tabela 2'!$A$4:$M$73,64,0) -> 1.2248855 | BR59: ='BCB-DBGG-anual'!B27 -> 16396929 | BS59: ='BCB-DBGG-anual'!C27 -> 83.102751
B60: 2032 | AJ60: =HLOOKUP(B60,'STN-RPF-Tabela 1'!$A$4:$M$73,2,0)*1000 -> 4807327 | AK60: =HLOOKUP(B60,'STN-RPF-Tabela 2'!$A$4:$M$73,2,0) -> 23.130912 | AN60: =HLOOKUP(B60,'STN-RPF-Tabela 1'!$A$4:$M$73,3,0)*1000 -> 2963964.3 | AO60: =HLOOKUP(B60,'STN-RPF-Tabela 2'!$A$4:$M$73,3,0) -> 14.261397 | AR60: =HLOOKUP(B60,'STN-RPF-Tabela 1'!$A$4:$M$73,15,0)*1000 -> 336888.94 | AS60: =HLOOKUP(B60,'STN-RPF-Tabela 2'!$A$4:$M$73,15,0) -> 1.6209732 | AT60: =HLOOKUP(B60,'STN-RPF-Tabela 1'!$A$4:$M$73,16,0)*1000 -> 197259.17 | AU60: =HLOOKUP(B60,'STN-RPF-Tabela 2'!$A$4:$M$73,16,0) -> 0.94913127 | AV60: =HLOOKUP(B60,'STN-RPF-Tabela 1'!$A$4:$M$73,13,0)*1000 -> 500758.79 | AW60: =HLOOKUP(B60,'STN-RPF-Tabela 2'!$A$4:$M$73,13,0) -> 2.4094486 | AZ60: =HLOOKUP(B60,'STN-RPF-Tabela 1'!$A$4:$M$73,48,0)*1000 -> 3683744.9 | BA60: =HLOOKUP(B60,'STN-RPF-Tabela 2'!$A$4:$M$73,48,0) -> 17.72469 | BL60: =HLOOKUP(B60,'STN-RPF-Tabela 1'!$A$4:$M$73,66,0)*1000 -> 1228168.5 | BM60: =HLOOKUP(B60,'STN-RPF-Tabela 2'!$A$4:$M$73,66,0) -> 5.9094499 | BN60: =HLOOKUP(B60,'STN-RPF-Tabela 1'!$A$4:$M$73,61,0)*1000 -> 259789.1 | BO60: =HLOOKUP(B60,'STN-RPF-Tabela 2'!$A$4:$M$73,61,0) -> 1.25 | BP60: =HLOOKUP(B60,'STN-RPF-Tabela 1'!$A$4:$M$73,64,0)*1000 -> 254522.08 | BQ60: =HLOOKUP(B60,'STN-RPF-Tabela 2'!$A$4:$M$73,64,0) -> 1.2246572 | BR60: ='BCB-DBGG-anual'!B28 -> 17486731 | BS60: ='BCB-DBGG-anual'!C28 -> 82.835865
B61: 2033 | AJ61: =HLOOKUP(B61,'STN-RPF-Tabela 1'!$A$4:$M$73,2,0)*1000 -> 5010885.8 | AK61: =HLOOKUP(B61,'STN-RPF-Tabela 2'!$A$4:$M$73,2,0) -> 22.550381 | AN61: =HLOOKUP(B61,'STN-RPF-Tabela 1'!$A$4:$M$73,3,0)*1000 -> 3155936.3 | AO61: =HLOOKUP(B61,'STN-RPF-Tabela 2'!$A$4:$M$73,3,0) -> 14.202592 | AR61: =HLOOKUP(B61,'STN-RPF-Tabela 1'!$A$4:$M$73,15,0)*1000 -> 360612.99 | AS61: =HLOOKUP(B61,'STN-RPF-Tabela 2'!$A$4:$M$73,15,0) -> 1.6228589 | AT61: =HLOOKUP(B61,'STN-RPF-Tabela 1'!$A$4:$M$73,16,0)*1000 -> 212545.66 | AU61: =HLOOKUP(B61,'STN-RPF-Tabela 2'!$A$4:$M$73,16,0) -> 0.95651463 | AV61: =HLOOKUP(B61,'STN-RPF-Tabela 1'!$A$4:$M$73,13,0)*1000 -> 532133.91 | AW61: =HLOOKUP(B61,'STN-RPF-Tabela 2'!$A$4:$M$73,13,0) -> 2.3947507 | AZ61: =HLOOKUP(B61,'STN-RPF-Tabela 1'!$A$4:$M$73,48,0)*1000 -> 3817539.8 | BA61: =HLOOKUP(B61,'STN-RPF-Tabela 2'!$A$4:$M$73,48,0) -> 17.179992 | BL61: =HLOOKUP(B61,'STN-RPF-Tabela 1'!$A$4:$M$73,66,0)*1000 -> 1314025.6 | BM61: =HLOOKUP(B61,'STN-RPF-Tabela 2'!$A$4:$M$73,66,0) -> 5.9134811 | BN61: =HLOOKUP(B61,'STN-RPF-Tabela 1'!$A$4:$M$73,61,0)*1000 -> 277760.59 | BO61: =HLOOKUP(B61,'STN-RPF-Tabela 2'!$A$4:$M$73,61,0) -> 1.25 | BP61: =HLOOKUP(B61,'STN-RPF-Tabela 1'!$A$4:$M$73,64,0)*1000 -> 272071.53 | BQ61: =HLOOKUP(B61,'STN-RPF-Tabela 2'!$A$4:$M$73,64,0) -> 1.2243976 | BR61: ='BCB-DBGG-anual'!B29 -> 18636117 | BS61: ='BCB-DBGG-anual'!C29 -> 82.532982
B62: 2034 | AJ62: =HLOOKUP(B62,'STN-RPF-Tabela 1'!$A$4:$M$73,2,0)*1000 -> 5245520 | AK62: =HLOOKUP(B62,'STN-RPF-Tabela 2'!$A$4:$M$73,2,0) -> 22.073638 | AN62: =HLOOKUP(B62,'STN-RPF-Tabela 1'!$A$4:$M$73,3,0)*1000 -> 3357525.4 | AO62: =HLOOKUP(B62,'STN-RPF-Tabela 2'!$A$4:$M$73,3,0) -> 14.12878 | AR62: =HLOOKUP(B62,'STN-RPF-Tabela 1'!$A$4:$M$73,15,0)*1000 -> 386381.62 | AS62: =HLOOKUP(B62,'STN-RPF-Tabela 2'!$A$4:$M$73,15,0) -> 1.6259299 | AT62: =HLOOKUP(B62,'STN-RPF-Tabela 1'!$A$4:$M$73,16,0)*1000 -> 229029.11 | AU62: =HLOOKUP(B62,'STN-RPF-Tabela 2'!$A$4:$M$73,16,0) -> 0.96377588 | AV62: =HLOOKUP(B62,'STN-RPF-Tabela 1'!$A$4:$M$73,13,0)*1000 -> 558579.08 | AW62: =HLOOKUP(B62,'STN-RPF-Tabela 2'!$A$4:$M$73,13,0) -> 2.3505529 | AZ62: =HLOOKUP(B62,'STN-RPF-Tabela 1'!$A$4:$M$73,48,0)*1000 -> 3977641 | BA62: =HLOOKUP(B62,'STN-RPF-Tabela 2'!$A$4:$M$73,48,0) -> 16.738284 | BL62: =HLOOKUP(B62,'STN-RPF-Tabela 1'!$A$4:$M$73,66,0)*1000 -> 1391455.1 | BM62: =HLOOKUP(B62,'STN-RPF-Tabela 2'!$A$4:$M$73,66,0) -> 5.8553731 | BN62: =HLOOKUP(B62,'STN-RPF-Tabela 1'!$A$4:$M$73,61,0)*1000 -> 297046.65 | BO62: =HLOOKUP(B62,'STN-RPF-Tabela 2'!$A$4:$M$73,61,0) -> 1.25 | BP62: =HLOOKUP(B62,'STN-RPF-Tabela 1'!$A$4:$M$73,64,0)*1000 -> 290996.43 | BQ62: =HLOOKUP(B62,'STN-RPF-Tabela 2'!$A$4:$M$73,64,0) -> 1.2245401 | BR62: ='BCB-DBGG-anual'!B30 -> 19833695 | BS62: ='BCB-DBGG-anual'!C30 -> 82.107078
B63: 2035 | AJ63: =HLOOKUP(B63,'STN-RPF-Tabela 1'!$A$4:$M$73,2,0)*1000 -> 5481586.5 | AK63: =HLOOKUP(B63,'STN-RPF-Tabela 2'!$A$4:$M$73,2,0) -> 21.581216 | AN63: =HLOOKUP(B63,'STN-RPF-Tabela 1'!$A$4:$M$73,3,0)*1000 -> 3560214.6 | AO63: =HLOOKUP(B63,'STN-RPF-Tabela 2'!$A$4:$M$73,3,0) -> 14.016701 | AR63: =HLOOKUP(B63,'STN-RPF-Tabela 1'!$A$4:$M$73,15,0)*1000 -> 414157.98 | AS63: =HLOOKUP(B63,'STN-RPF-Tabela 2'!$A$4:$M$73,15,0) -> 1.6305558 | AT63: =HLOOKUP(B63,'STN-RPF-Tabela 1'!$A$4:$M$73,16,0)*1000 -> 246785.45 | AU63: =HLOOKUP(B63,'STN-RPF-Tabela 2'!$A$4:$M$73,16,0) -> 0.97160377 | AV63: =HLOOKUP(B63,'STN-RPF-Tabela 1'!$A$4:$M$73,13,0)*1000 -> 586520.13 | AW63: =HLOOKUP(B63,'STN-RPF-Tabela 2'!$A$4:$M$73,13,0) -> 2.3091522 | AZ63: =HLOOKUP(B63,'STN-RPF-Tabela 1'!$A$4:$M$73,48,0)*1000 -> 4135325.5 | BA63: =HLOOKUP(B63,'STN-RPF-Tabela 2'!$A$4:$M$73,48,0) -> 16.280935 | BL63: =HLOOKUP(B63,'STN-RPF-Tabela 1'!$A$4:$M$73,66,0)*1000 -> 1488622.9 | BM63: =HLOOKUP(B63,'STN-RPF-Tabela 2'!$A$4:$M$73,66,0) -> 5.8607654 | BN63: =HLOOKUP(B63,'STN-RPF-Tabela 1'!$A$4:$M$73,61,0)*1000 -> 317497.55 | BO63: =HLOOKUP(B63,'STN-RPF-Tabela 2'!$A$4:$M$73,61,0) -> 1.25 | BP63: =HLOOKUP(B63,'STN-RPF-Tabela 1'!$A$4:$M$73,64,0)*1000 -> 310944.13 | BQ63: =HLOOKUP(B63,'STN-RPF-Tabela 2'!$A$4:$M$73,64,0) -> 1.2241989 | BR63: ='BCB-DBGG-anual'!B31 -> 21093735 | BS63: ='BCB-DBGG-anual'!C31 -> 81.678704

Sheet STN-RPF-Tabela 2
A2: Tabela 2 - Projeções fiscais para 10 anos - % do PIB
A4: Discriminação | B4: 2024 | C4: 2025 | D4: 2026 | E4: 2027 | F4: 2028 | G4: 2029 | H4: 2030 | I4: 2031 | J4: 2032 | K4: 2033 | L4: 2034 | M4: 2035
A5: 1. RECEITA PRIMÁRIA TOTAL | B5: =100*'[1]Tabela 1'!B5/'[1]Tabela 3'!B$9 -> 22.814029 | C5: =100*'[1]Tabela 1'!C5/'[1]Tabela 3'!C$9 -> 23.022474 | D5: =100*'[1]Tabela 1'!D5/'[1]Tabela 3'!D$9 -> 23.317381 | E5: =100*'[1]Tabela 1'!E5/'[1]Tabela 3'!E$9 -> 23.196804 | F5: =100*'[1]Tabela 1'!F5/'[1]Tabela 3'!F$9 -> 23.27634 | G5: =100*'[1]Tabela 1'!G5/'[1]Tabela 3'!G$9 -> 23.297793 | H5: =100*'[1]Tabela 1'!H5/'[1]Tabela 3'!H$9 -> 23.226412 | I5: =100*'[1]Tabela 1'!I5/'[1]Tabela 3'!I$9 -> 23.208585 | ... M5: =100*'[1]Tabela 1'!M5/'[1]Tabela 3'!M$9 -> 21.581216
A6: 1.1 - Receita Administrada pela RFB | B6: =100*'[1]Tabela 1'!B6/'[1]Tabela 3'!B$9 -> 14.389631 | C6: =100*'[1]Tabela 1'!C6/'[1]Tabela 3'!C$9 -> 14.758496 | D6: =100*'[1]Tabela 1'!D6/'[1]Tabela 3'!D$9 -> 14.91133 | E6: =100*'[1]Tabela 1'!E6/'[1]Tabela 3'!E$9 -> 14.673507 | F6: =100*'[1]Tabela 1'!F6/'[1]Tabela 3'!F$9 -> 14.375222 | G6: =100*'[1]Tabela 1'!G6/'[1]Tabela 3'!G$9 -> 14.255291 | H6: =100*'[1]Tabela 1'!H6/'[1]Tabela 3'!H$9 -> 14.256238 | I6: =100*'[1]Tabela 1'!I6/'[1]Tabela 3'!I$9 -> 14.35711 | ... M6: =100*'[1]Tabela 1'!M6/'[1]Tabela 3'!M$9 -> 14.016701
A7: 1.1.1 Imposto de Importação | B7: =100*'[1]Tabela 1'!B7/'[1]Tabela 3'!B$9 -> 0.66199438 | C7: =100*'[1]Tabela 1'!C7/'[1]Tabela 3'!C$9 -> 0.72644526 | D7: =100*'[1]Tabela 1'!D7/'[1]Tabela 3'!D$9 -> 0.7231138 | E7: =100*'[1]Tabela 1'!E7/'[1]Tabela 3'!E$9 -> 0.7273521 | F7: =100*'[1]Tabela 1'!F7/'[1]Tabela 3'!F$9 -> 0.73730219 | G7: =100*'[1]Tabela 1'!G7/'[1]Tabela 3'!G$9 -> 0.74795885 | H7: =100*'[1]Tabela 1'!H7/'[1]Tabela 3'!H$9 -> 0.76573092 | I7: =100*'[1]Tabela 1'!I7/'[1]Tabela 3'!I$9 -> 0.79037136 | ... M7: =100*'[1]Tabela 1'!M7/'[1]Tabela 3'!M$9 -> 0.9256036
A8: 1.1.2 IPI | B8: =100*'[1]Tabela 1'!B8/'[1]Tabela 3'!B$9 -> 0.71839358 | C8: =100*'[1]Tabela 1'!C8/'[1]Tabela 3'!C$9 -> 0.70247835 | D8: =100*'[1]Tabela 1'!D8/'[1]Tabela 3'!D$9 -> 0.67689249 | E8: =100*'[1]Tabela 1'!E8/'[1]Tabela 3'!E$9 -> 0.68053798 | F8: =100*'[1]Tabela 1'!F8/'[1]Tabela 3'!F$9 -> 0.67708896 | G8: =100*'[1]Tabela 1'!G8/'[1]Tabela 3'!G$9 -> 0.6715822 | H8: =100*'[1]Tabela 1'!H8/'[1]Tabela 3'!H$9 -> 0.6663321 | I8: =100*'[1]Tabela 1'!I8/'[1]Tabela 3'!I$9 -> 0.66212298 | ... M8: =100*'[1]Tabela 1'!M8/'[1]Tabela 3'!M$9 -> 0.65362196
A9: 1.1.2.1 IPI - Fumo | B9: =100*'[1]Tabela 1'!B9/'[1]Tabela 3'!B$9 -> 0.069482603 | C9: =100*'[1]Tabela 1'!C9/'[1]Tabela 3'!C$9 -> 0.09184937 | D9: =100*'[1]Tabela 1'!D9/'[1]Tabela 3'!D$9 -> 0.075572996 | E9: =100*'[1]Tabela 1'!E9/'[1]Tabela 3'!E$9 -> 0.069747952 | F9: =100*'[1]Tabela 1'!F9/'[1]Tabela 3'!F$9 -> 0.064563016 | G9: =100*'[1]Tabela 1'!G9/'[1]Tabela 3'!G$9 -> 0.059845683 | H9: =100*'[1]Tabela 1'!H9/'[1]Tabela 3'!H$9 -> 0.058554175 | I9: =100*'[1]Tabela 1'!I9/'[1]Tabela 3'!I$9 -> 0.057350427 | ... M9: =100*'[1]Tabela 1'!M9/'[1]Tabela 3'!M$9 -> 0.052906491
A10: 1.1.2.2 IPI - Bebidas | B10: =100*'[1]Tabela 1'!B10/'[1]Tabela 3'!B$9 -> 0.028447567 | C10: =100*'[1]Tabela 1'!C10/'[1]Tabela 3'!C$9 -> 0.027576595 | D10: =100*'[1]Tabela 1'!D10/'[1]Tabela 3'!D$9 -> 0.025868771 | E10: =100*'[1]Tabela 1'!E10/'[1]Tabela 3'!E$9 -> 0.025091281 | F10: =100*'[1]Tabela 1'!F10/'[1]Tabela 3'!F$9 -> 0.024246366 | G10: =100*'[1]Tabela 1'!G10/'[1]Tabela 3'!G$9 -> 0.023483452 | H10: =100*'[1]Tabela 1'!H10/'[1]Tabela 3'!H$9 -> 0.022603509 | I10: =100*'[1]Tabela 1'!I10/'[1]Tabela 3'!I$9 -> 0.021791225 | ... M10: =100*'[1]Tabela 1'!M10/'[1]Tabela 3'!M$9 -> 0.018886345
A11: 1.1.2.3 IPI - Automóveis | B11: =100*'[1]Tabela 1'!B11/'[1]Tabela 3'!B$9 -> 0.073421627 | C11: =100*'[1]Tabela 1'!C11/'[1]Tabela 3'!C$9 -> 0.075122993 | D11: =100*'[1]Tabela 1'!D11/'[1]Tabela 3'!D$9 -> 0.074251219 | E11: =100*'[1]Tabela 1'!E11/'[1]Tabela 3'!E$9 -> 0.071001956 | F11: =100*'[1]Tabela 1'!F11/'[1]Tabela 3'!F$9 -> 0.069212288 | G11: =100*'[1]Tabela 1'!G11/'[1]Tabela 3'!G$9 -> 0.066609753 | H11: =100*'[1]Tabela 1'!H11/'[1]Tabela 3'!H$9 -> 0.06582397 | I11: =100*'[1]Tabela 1'!I11/'[1]Tabela 3'!I$9 -> 0.065058776 | ... M11: =100*'[1]Tabela 1'!M11/'[1]Tabela 3'!M$9 -> 0.062446417
A12: 1.1.2.4 IPI - Vinculado a importação | B12: =100*'[1]Tabela 1'!B12/'[1]Tabela 3'!B$9 -> 0.25220859 | C12: =100*'[1]Tabela 1'!C12/'[1]Tabela 3'!C$9 -> 0.25094594 | D12: =100*'[1]Tabela 1'!D12/'[1]Tabela 3'!D$9 -> 0.25393562 | E12: =100*'[1]Tabela 1'!E12/'[1]Tabela 3'!E$9 -> 0.25550094 | F12: =100*'[1]Tabela 1'!F12/'[1]Tabela 3'!F$9 -> 0.25848939 | G12: =100*'[1]Tabela 1'!G12/'[1]Tabela 3'!G$9 -> 0.26058822 | H12: =100*'[1]Tabela 1'!H12/'[1]Tabela 3'!H$9 -> 0.26189596 | I12: =100*'[1]Tabela 1'!I12/'[1]Tabela 3'!I$9 -> 0.26375697 | ... M12: =100*'[1]Tabela 1'!M12/'[1]Tabela 3'!M$9 -> 0.27735408
A13: 1.1.2.5 IPI - Outros | B13: =100*'[1]Tabela 1'!B13/'[1]Tabela 3'!B$9 -> 0.2948332 | C13: =100*'[1]Tabela 1'!C13/'[1]Tabela 3'!C$9 -> 0.25698346 | D13: =100*'[1]Tabela 1'!D13/'[1]Tabela 3'!D$9 -> 0.24726389 | E13: =100*'[1]Tabela 1'!E13/'[1]Tabela 3'!E$9 -> 0.25919586 | F13: =100*'[1]Tabela 1'!F13/'[1]Tabela 3'!F$9 -> 0.26057789 | G13: =100*'[1]Tabela 1'!G13/'[1]Tabela 3'!G$9 -> 0.26105508 | H13: =100*'[1]Tabela 1'!H13/'[1]Tabela 3'!H$9 -> 0.25745449 | I13: =100*'[1]Tabela 1'!I13/'[1]Tabela 3'!I$9 -> 0.25416558 | ... M13: =100*'[1]Tabela 1'!M13/'[1]Tabela 3'!M$9 -> 0.24202863
A14: 1.1.3 Imposto de Renda | B14: =100*'[1]Tabela 1'!B14/'[1]Tabela 3'!B$9 -> 6.6852416 | C14: =100*'[1]Tabela 1'!C14/'[1]Tabela 3'!C$9 -> 6.8376644 | D14: =100*'[1]Tabela 1'!D14/'[1]Tabela 3'!D$9 -> 6.9625827 | E14: =100*'[1]Tabela 1'!E14/'[1]Tabela 3'!E$9 -> 6.7916709 | F14: =100*'[1]Tabela 1'!F14/'[1]Tabela 3'!F$9 -> 6.6047692 | G14: =100*'[1]Tabela 1'!G14/'[1]Tabela 3'!G$9 -> 6.5237049 | H14: =100*'[1]Tabela 1'!H14/'[1]Tabela 3'!H$9 -> 6.5693941 | I14: =100*'[1]Tabela 1'!I14/'[1]Tabela 3'!I$9 -> 6.7032725 | ... M14: =100*'[1]Tabela 1'!M14/'[1]Tabela 3'!M$9 -> 6.6660399
A15: 1.1.3.1 IR - Pessoa Física | B15: =100*'[1]Tabela 1'!B15/'[1]Tabela 3'!B$9 -> 0.60472822 | C15: =100*'[1]Tabela 1'!C15/'[1]Tabela 3'!C$9 -> 0.59076514 | D15: =100*'[1]Tabela 1'!D15/'[1]Tabela 3'!D$9 -> 0.58072718 | E15: =100*'[1]Tabela 1'!E15/'[1]Tabela 3'!E$9 -> 0.58067704 | F15: =100*'[1]Tabela 1'!F15/'[1]Tabela 3'!F$9 -> 0.54650594 | G15: =100*'[1]Tabela 1'!G15/'[1]Tabela 3'!G$9 -> 0.52466464 | H15: =100*'[1]Tabela 1'!H15/'[1]Tabela 3'!H$9 -> 0.53102304 | I15: =100*'[1]Tabela 1'!I15/'[1]Tabela 3'!I$9 -> 0.67786082 | ... M15: =100*'[1]Tabela 1'!M15/'[1]Tabela 3'!M$9 -> 0.67089548
A16: 1.1.3.2 IR - Pessoa Jurídica | B16: =100*'[1]Tabela 1'!B16/'[1]Tabela 3'!B$9 -> 2.3877779 | C16: =100*'[1]Tabela 1'!C16/'[1]Tabela 3'!C$9 -> 2.4874836 | D16: =100*'[1]Tabela 1'!D16/'[1]Tabela 3'!D$9 -> 2.4465365 | E16: =100*'[1]Tabela 1'!E16/'[1]Tabela 3'!E$9 -> 2.4245779 | F16: =100*'[1]Tabela 1'!F16/'[1]Tabela 3'!F$9 -> 2.3946377 | G16: =100*'[1]Tabela 1'!G16/'[1]Tabela 3'!G$9 -> 2.3946966 | H16: =100*'[1]Tabela 1'!H16/'[1]Tabela 3'!H$9 -> 2.4418442 | I16: =100*'[1]Tabela 1'!I16/'[1]Tabela 3'!I$9 -> 2.4252303 | ... M16: =100*'[1]Tabela 1'!M16/'[1]Tabela 3'!M$9 -> 2.3091522
... A73: 14. DÍVIDA LÍQUIDA DO GOVERNO GERAL 4/ | B73: =100*'[1]Tabela 1'!B73/'[1]Tabela 3'!B$9 -> 63.391601 | C73: =100*'[1]Tabela 1'!C73/'[1]Tabela 3'!C$9 -> 67.488739 | D73: =100*'[1]Tabela 1'!D73/'[1]Tabela 3'!D$9 -> 70.197292 | E73: =100*'[1]Tabela 1'!E73/'[1]Tabela 3'!E$9 -> 71.449693 | F73: =100*'[1]Tabela 1'!F73/'[1]Tabela 3'!F$9 -> 71.717041 | G73: =100*'[1]Tabela 1'!G73/'[1]Tabela 3'!G$9 -> 71.458089 | H73: =100*'[1]Tabela 1'!H73/'[1]Tabela 3'!H$9 -> 71.286706 | I73: =100*'[1]Tabela 1'!I73/'[1]Tabela 3'!I$9 -> 71.108116 | ... M73: =100*'[1]Tabela 1'!M73/'[1]Tabela 3'!M$9 -> 70.188606
A74: Nota: Projeções consideram o Cenário de Referência do Relatório de Projeções Fiscais, que tem como premissa a adoção de medidas de receita para cumprimento das metas de resultado primário do PLDO 2026.
A75: 1/ Receitas líquidas adicionais necessárias para atingir as metas fiscais.
A76: 2/ Em 2024, as despesas são apresentadas pelo critério de pagamento efetivo.
A77: 3/ Inclui o resultado primário das empresas estatais regionais.
A78: 4/ Posição de dezembro de cada ano.
A80: Memorando | B80: 2024 | C80: 2025 | D80: 2026 | E80: 2027 | F80: 2028 | G80: 2029 | H80: 2030 | I80: 2031 | J80: 2032 | K80: 2033 | L80: 2034 | M80: 2035
A81: LIMITE DE GASTOS* | B81: =100*'[1]Tabela 1'!B81/'[1]Tabela 3'!B$9 -> 17.925034 | C81: =100*'[1]Tabela 1'!C81/'[1]Tabela 3'!C$9 -> 17.76903 | D81: =100*'[1]Tabela 1'!D81/'[1]Tabela 3'!D$9 -> 17.765567 | E81: =100*'[1]Tabela 1'!E81/'[1]Tabela 3'!E$9 -> 17.571718 | F81: =100*'[1]Tabela 1'!F81/'[1]Tabela 3'!F$9 -> 17.338972 | G81: =100*'[1]Tabela 1'!G81/'[1]Tabela 3'!G$9 -> 17.072708 | H81: =100*'[1]Tabela 1'!H81/'[1]Tabela 3'!H$9 -> 16.830286 | I81: =100*'[1]Tabela 1'!I81/'[1]Tabela 3'!I$9 -> 16.608659 | ... M81: =100*'[1]Tabela 1'!M81/'[1]Tabela 3'!M$9 -> 15.430759
A82: Despesas sujeitas ao Limite** | B82: =100*'[1]Tabela 1'!B82/'[1]Tabela 3'!B$9 -> 17.683451 | C82: =100*'[1]Tabela 1'!C82/'[1]Tabela 3'!C$9 -> 17.562393 | D82: =100*'[1]Tabela 1'!D82/'[1]Tabela 3'!D$9 -> 17.695264 | E82: =100*'[1]Tabela 1'!E82/'[1]Tabela 3'!E$9 -> 17.502377 | F82: =100*'[1]Tabela 1'!F82/'[1]Tabela 3'!F$9 -> 17.270665 | G82: =100*'[1]Tabela 1'!G82/'[1]Tabela 3'!G$9 -> 17.0054 | H82: =100*'[1]Tabela 1'!H82/'[1]Tabela 3'!H$9 -> 16.763731 | I82: =100*'[1]Tabela 1'!I82/'[1]Tabela 3'!I$9 -> 16.542783 | ... M82: =100*'[1]Tabela 1'!M82/'[1]Tabela 3'!M$9 -> 15.366945
A83: DESPESAS NÃO SUJEITAS AO LIMITE* | B83: =100*'[1]Tabela 1'!B83/'[1]Tabela 3'!B$9 -> 1.0935545 | C83: =100*'[1]Tabela 1'!C83/'[1]Tabela 3'!C$9 -> 1.2540854 | D83: =100*'[1]Tabela 1'!D83/'[1]Tabela 3'!D$9 -> 1.2707979 | E83: =100*'[1]Tabela 1'!E83/'[1]Tabela 3'!E$9 -> 0.78741731 | F83: =100*'[1]Tabela 1'!F83/'[1]Tabela 3'!F$9 -> 0.73549003 | G83: =100*'[1]Tabela 1'!G83/'[1]Tabela 3'!G$9 -> 0.84151502 | H83: =100*'[1]Tabela 1'!H83/'[1]Tabela 3'!H$9 -> 1.0405602 | I83: =100*'[1]Tabela 1'!I83/'[1]Tabela 3'!I$9 -> 1.2157756 | ... M83: =100*'[1]Tabela 1'!M83/'[1]Tabela 3'!M$9 -> 0.91399016
A84: TAXAS IMPLÍCITAS DA DÍVIDA PÚBLICA
A85: Dívida líquida do setor público (% a.a.) | B85: ='[1]Tabela 1'!B85 -> 14.715022 | C85: ='[1]Tabela 1'!C85 -> 13.940922 | D85: ='[1]Tabela 1'!D85 -> 12.358109 | E85: ='[1]Tabela 1'!E85 -> 10.76367 | F85: ='[1]Tabela 1'!F85 -> 9.1710214 | G85: ='[1]Tabela 1'!G85 -> 8.6683012 | H85: ='[1]Tabela 1'!H85 -> 8.4528733 | I85: ='[1]Tabela 1'!I85 -> 8.315075 | ... M85: ='[1]Tabela 1'!M85 -> 8.264667
A86: Dívida bruta do governo geral (% a.a.) | B86: ='[1]Tabela 1'!B86 -> 10.710417 | C86: ='[1]Tabela 1'!C86 -> 11.713776 | D86: ='[1]Tabela 1'!D86 -> 10.711364 | E86: ='[1]Tabela 1'!E86 -> 9.3039305 | F86: ='[1]Tabela 1'!F86 -> 8.0369048 | G86: ='[1]Tabela 1'!G86 -> 7.6051537 | H86: ='[1]Tabela 1'!H86 -> 7.4409441 | I86: ='[1]Tabela 1'!I86 -> 7.3181064 | ... M86: ='[1]Tabela 1'!M86 -> 7.2895715
A87: *Considera o limite de despesas da LC 200/2023.
A88: **A diferença entre o limite de despesa e as despesas sujeitas ao limite justifica-se pelo float, dado que o novo limite de despesas é orçamentário e as projeções do Relatório de Projeções Fiscais são financeiras.

Sheet RTN-2.2-A
A1: Voltar
A2: Tabela 2.2-A Resultado Primário do Governo Central - Brasil - Anual
A3: % do PIB
A5: Discriminação | B5: 1997 | C5: 1998 | D5: 1999 | E5: 2000 | F5: 2001 | G5: 2002 | H5: 2003 | I5: 2004 | J5: 2005 | K5: 2006 | L5: 2007 | M5: 2008 | N5: 2009 | O5: 2010 | P5: 2011 | Q5: 2012 | R5: 2013 | S5: 2014 | T5: 2015 | U5: 2016 | V5: 2017 | W5: 2018 | X5: 2019 | Y5: 2020 | Z5: 2021 | AA5: 2022 | AB5: 2023 | AC5: 2024
A6: 1. RECEITA TOTAL 1/ | B6: 0.16701416 | C6: 0.18308577 | D6: 0.19249932 | E6: 0.19602492 | F6: 0.20554061 | G6: 0.21497797 | H6: 0.20730024 | I6: 0.21401764 | J6: 0.22474227 | K6: 0.22528379 | L6: 0.22731336 | M6: 0.23011614 | N6: 0.22145701 | O6: 0.23637868 | P6: 0.22581897 | Q6: 0.2227088 | R6: 0.22113044 | S6: 0.21136599 | T6: 0.20833023 | U6: 0.20990851 | V6: 0.21010668 | W6: 0.21258841 | X6: 0.22135321 | Y6: 0.19292692 | Z6: 0.21444954 | AA6: 0.22950195 | AB6: 0.21505603 | AC6: 0.22814029
A7: 1.1 - Receita Administrada pela RFB | B7: 0.10682927 | C7: 0.1114903 | D7: 0.12348437 | E7: 0.13025499 | F7: 0.13620933 | G7: 0.14770465 | H7: 0.14137158 | I7: 0.14649853 | J7: 0.15344698 | K7: 0.14907518 | L7: 0.15348128 | M7: 0.1499571 | N7: 0.13685387 | O7: 0.13670276 | P7: 0.14370202 | Q7: 0.13448958 | R7: 0.13507968 | S7: 0.12790864 | T7: 0.12761247 | U7: 0.13075594 | V7: 0.12687969 | W7: 0.12921676 | X7: 0.12803709 | Y7: 0.11820895 | Z7: 0.13267793 | AA7: 0.13790129 | AB7: 0.1315231 | AC7: 0.14389631
A8: 1.1.01 Imposto sobre a Importação | B8: 0.0053936714 | C8: 0.0065156346 | D8: 0.0072271517 | E8: 0.0070870089 | F8: 0.0069002402 | G8: 0.0053443274 | H8: 0.0047351482 | I8: 0.0046968291 | J8: 0.004155538 | K8: 0.0041413256 | L8: 0.0044908617 | M8: 0.0055216597 | N8: 0.004790794 | O8: 0.0054282494 | P8: 0.0060965102 | Q8: 0.0064525654 | R8: 0.0069657481 | S8: 0.0063269725 | T8: 0.0064949405 | U8: 0.0050069924 | V8: 0.0049239379 | W8: 0.0058077576 | X8: 0.005824135 | Y8: 0.0060113166 | Z8: 0.0068763092 | AA8: 0.0058611704 | AB8: 0.004954792 | AC8: 0.0066199438
A9: 1.1.02 IPI | B9: 0.017385702 | C9: 0.015786916 | D9: 0.014787655 | E9: 0.014761578 | F9: 0.014394355 | G9: 0.012508749 | H9: 0.010404717 | I9: 0.010876936 | J9: 0.011264971 | K9: 0.011365713 | L9: 0.011717865 | M9: 0.012013984 | N9: 0.0084266538 | O9: 0.0096642548 | P9: 0.0094761852 | Q9: 0.0092383018 | R9: 0.008267165 | S9: 0.0086773863 | T9: 0.0081034104 | U9: 0.0067461757 | V9: 0.0072936992 | W9: 0.0079135076 | X9: 0.0071301954 | Y9: 0.0074504016 | Z9: 0.0079100071 | AA9: 0.0059420099 | AB9: 0.0054212582 | AC9: 0.0071839358
A10: 1.1.02.1 IPI - Fumo | B10: 0.0029821391 | C10: 0.0025292749 | D10: 0.0020965307 | E10: 0.0016661135 | F10: 0.0015252092 | G10: 0.0012919061 | H10: 0.001160414 | I10: 0.0011770114 | J10: 0.0010608995 | K10: 0.0009945645 | L10: 0.0010305503 | M10: 0.0010326615 | N10: 0.00099430886 | O10: 0.00095356995 | P10: 0.00085589339 | Q10: 0.00084724408 | R10: 0.00095627689 | S10: 0.00097840222 | T10: 0.00094761084 | U10: 0.00091213186 | V10: 0.00079110391 | W10: 0.00074354028 | X10: 0.00075231302 | Y10: 0.0007851879 | Z10: 0.00061879551 | AA10: 0.00066788266 | AB10: 0.00034947828 | AC10: 0.00069482603
A11: 1.1.02.2 IPI - Bebidas | B11: 0 | C11: 0 | D11: 0 | E11: 0.0016195445 | F11: 0.0015212096 | G11: 0.0012059347 | H11: 0.001105696 | I11: 0.0010209781 | J11: 0.0010861528 | K11: 0.0010900796 | L11: 0.00095168419 | M11: 0.00080047217 | N11: 0.00069125952 | O11: 0.00062536451 | P11: 0.00068337421 | Q11: 0.00066807819 | R11: 0.00064484173 | S11: 0.0005849001 | T11: 0.00043269863 | U11: 0.00042809974 | V11: 0.00044702115 | W11: 0.00039514159 | X11: 0.00049274366 | Y11: 0.00039228883 | Z11: 0.0002981999 | AA11: 0.00024933418 | AB11: 0.00026993987 | AC11: 0.00028447567
A12: 1.1.02.3 IPI - Automóveis | B12: 0 | C12: 0 | D12: 0 | E12: 0.0019805036 | F12: 0.0019719775 | G12: 0.0017893305 | H12: 0.0013467064 | I12: 0.0015140155 | J12: 0.0017236392 | K12: 0.0017862984 | L12: 0.001922073 | M12: 0.0019395273 | N12: 0.0006292368 | O12: 0.0014890817 | P12: 0.0016330353 | Q12: 0.0009096832 | R12: 0.00070837684 | S12: 0.00084976067 | T12: 0.00072693109 | U12: 0.00052615829 | V12: 0.00067829621 | W12: 0.00081570788 | X12: 0.00076320123 | Y12: 0.00045287121 | Z12: 0.00038245012 | AA12: 0.00040161891 | AB12: 0.00063219791 | AC12: 0.00073421627
A13: 1.1.02.4 IPI - Vinculado à importação | B13: 0 | C13: 0 | D13: 0 | E13: 0.0040361602 | F13: 0.0036119458 | G13: 0.0032799865 | H13: 0.0026557477 | I13: 0.0026430625 | J13: 0.0024316145 | K13: 0.002552567 | L13: 0.0028278016 | M13: 0.003328528 | N13: 0.0025155213 | O13: 0.0028974087 | P13: 0.0031342323 | Q13: 0.0033085098 | R13: 0.0027428962 | S13: 0.0026093123 | T13: 0.0028023667 | U13: 0.0021456261 | V13: 0.0021253711 | W13: 0.0025700093 | X13: 0.0025862656 | Y13: 0.0028834585 | Z13: 0.0035167314 | AA13: 0.0024327409 | AB13: 0.0020659527 | AC13: 0.0025220859
A14: 1.1.02.5 IPI - Outros | B14: 0.014403563 | C14: 0.013257641 | D14: 0.012691125 | E14: 0.0054592565 | F14: 0.0057640125 | G14: 0.0049415908 | H14: 0.004136153 | I14: 0.0045218688 | J14: 0.0049626654 | K14: 0.0049422036 | L14: 0.0049857559 | M14: 0.004912795 | N14: 0.0035963273 | O14: 0.0036988299 | P14: 0.00316965 | Q14: 0.0035047865 | R14: 0.0032147734 | S14: 0.003655011 | T14: 0.0031938031 | U14: 0.0027341598 | V14: 0.0032519068 | W14: 0.0033891085 | X14: 0.0025356719 | Y14: 0.0029365951 | Z14: 0.0030938301 | AA14: 0.0021904332 | AB14: 0.0021036894 | AC14: 0.002948332
A15: 1.1.03 Imposto sobre a Renda | B15: 0.03573195 | C15: 0.042810809 | D15: 0.043661022 | E15: 0.042734518 | F15: 0.045636626 | G15: 0.053045297 | H15: 0.04867691 | I15: 0.047050237 | J15: 0.05311269 | K15: 0.052225623 | L15: 0.05441156 | M15: 0.057640121 | N15: 0.053643467 | O15: 0.050097805 | P15: 0.05388008 | Q15: 0.051228581 | R15: 0.051127491 | S15: 0.04943531 | T15: 0.050108928 | U15: 0.054410177 | V15: 0.051604585 | W15: 0.051791828 | X15: 0.053912491 | Y15: 0.05047901 | Z15: 0.05753628 | AA15: 0.066194836 | AB15: 0.063578597 | AC15: 0.066852416
A16: 1.1.03.1 I.R. - Pessoa Física | B16: 0.0028012664 | C16: 0.0028375474 | D16: 0.0027941097 | E16: 0.0030148661 | F16: 0.0030550915 | G16: 0.0029757947 | H16: 0.0029564139 | I16: 0.0031189439 | J16: 0.0033650688 | K16: 0.0035520921 | L16: 0.0050399953 | M16: 0.0048387917 | N16: 0.0044428676 | O16: 0.0044544853 | P16: 0.0049938718 | Q16: 0.005014867 | R16: 0.0049325895 | S16: 0.0047948029 | T16: 0.0047025744 | U16: 0.0048642932 | V16: 0.0049896314 | W16: 0.0049954643 | X16: 0.0053922037 | Y16: 0.0054740929 | Z16: 0.0062429575 | AA16: 0.0057728553 | AB16: 0.0053881539 | AC16: 0.0060472822
... A164: 10. RESULTADO NOMINAL DO GOVERNO CENTRAL (8 + 9) 14/ | B164: -0.022379237 | C164: -0.044994216 | D164: -0.024212325 | E164: -0.02086281 | F164: -0.019208158 | G164: -0.0067364562 | H164: -0.03617831 | I164: -0.01380836 | J164: -0.033762337 | K164: -0.030909564 | L164: -0.021912214 | M164: -0.0080039658 | N164: -0.032211797 | O164: -0.011782627 | P164: -0.019997699 | Q164: -0.012707105 | R164: -0.020735718 | S164: -0.046988082 | T164: -0.085709516 | U164: -0.076217977 | V164: -0.069751874 | W164: -0.060888908 | X164: -0.054000121 | Y164: -0.13297985 | Z164: -0.049173039 | AA164: -0.044474416 | AB164: -0.080330181 | AC164: -0.076678835
A166: Memorando
A167: Arrecadação Líquida para o RGPS | B167: 0.046488036 | C167: 0.046175244 | D167: 0.045108771 | E167: 0.046464433 | F167: 0.047495064 | G167: 0.047708414 | H167: 0.046992131 | I167: 0.047894432 | J167: 0.049956174 | K167: 0.051264892 | L167: 0.051616991 | M167: 0.052529137 | N167: 0.054607349 | O167: 0.054548823 | P167: 0.056186124 | Q167: 0.057274857 | R167: 0.057608577 | S167: 0.058402125 | T167: 0.058419688 | U167: 0.057125312 | V167: 0.056910792 | W167: 0.055850075 | X167: 0.055937741 | Y167: 0.053192372 | Z167: 0.05129126 | AA167: 0.053147528 | AB167: 0.054157713 | AC167: 0.054591001
A168: Arrecadação Ordinária | B168: 0.046488036 | C168: 0.046175244 | D168: 0.045108771 | E168: 0.046464433 | F168: 0.047495064 | G168: 0.047708414 | H168: 0.046992131 | I168: 0.047894432 | J168: 0.049956174 | K168: 0.051264892 | L168: 0.051616991 | M168: 0.052529137 | N168: 0.054607349 | O168: 0.054548823 | P168: 0.056186124 | Q168: 0.056903083 | R168: 0.055916836 | S168: 0.055278375 | T168: 0.054182217 | U168: 0.054319061 | V168: 0.054799883 | W168: 0.053917712 | X168: 0.054558021 | Y168: 0.051956142 | Z168: 0.050484426 | AA168: 0.052840367 | AB168: 0.054157713 | AC168: 0.054591001
A169: Compensação ao RGPS pelas Desonerações da Folha | B169: 0 | C169: 0 | D169: 0 | E169: 0 | F169: 0 | G169: 0 | H169: 0 | I169: 0 | J169: 0 | K169: 0 | L169: 0 | M169: 0 | N169: 0 | O169: 0 | P169: 0 | Q169: 0.00037177346 | R169: 0.0016917413 | S169: 0.0031237493 | T169: 0.004237471 | U169: 0.0028062513 | V169: 0.0021109095 | W169: 0.0019323626 | X169: 0.0013797198 | Y169: 0.0012362297 | Z169: 0.00080683371 | AA169: 0.00030716164 | AB169: 0 | AC169: 0
A171: Custeio Administrativo | B171: 0 | C171: 0 | D171: 0 | E171: 0 | F171: 0 | G171: 0 | H171: 0 | I171: 0 | J171: 0 | K171: 0 | L171: 0 | M171: 0 | N171: 0 | O171: 0 | P171: 0.0074595476 | Q171: 0.0074058374 | R171: 0.0069879419 | S171: 0.0071714757 | T171: 0.007073225 | U171: 0.0078704106 | V171: 0.0068291155 | W171: 0.0066443298 | X171: 0.0062870947 | Y171: 0.0059310118 | Z171: 0.0050755186 | AA171: 0.0051521289 | AB171: 0.0052087105 | AC171: 0.0052258877
A172: Investimento | B172: 0 | C172: 0 | D172: 0 | E172: 0 | F172: 0 | G172: 0 | H172: 0 | I172: 0 | J172: 0 | K172: 0 | L172: 0 | M172: 0.0090378146 | N172: 0.010203382 | O172: 0.011513891 | P172: 0.012026069 | Q172: 0.012347205 | R172: 0.011858354 | S172: 0.013416911 | T172: 0.0092618291 | U172: 0.010338089 | V172: 0.0069386 | W172: 0.0075858877 | X172: 0.0076590002 | Y172: 0.013785815 | Z172: 0.0063057413 | AA172: 0.0044698503 | AB172: 0.0074351428 | AC172: 0.0073311393
A174: PAC 15/ | B174: 0 | C174: 0 | D174: 0 | E174: 0 | F174: 0 | G174: 0 | H174: 0 | I174: 0 | J174: 0 | K174: 0 | L174: 0.0026982854 | M174: 0.0036530787 | N174: 0.0053809069 | O174: 0.0056826743 | P174: 0.0064030478 | Q174: 0.008163837 | R174: 0.0083867226 | S174: 0.0099841684 | T174: 0.0078820774 | U174: 0.0067060997 | V174: 0.0044944391 | W174: 0.0039399041 | X174: 0.003664975 | Y174: 0 | Z174: 0 | AA174: 0 | AB174: 0 | AC174: 0
A175: Minha Casa Minha Vida | B175: 0 | C175: 0 | D175: 0 | E175: 0 | F175: 0 | G175: 0 | H175: 0 | I175: 0 | J175: 0 | K175: 0 | L175: 0 | M175: 0 | N175: 0.0004715991 | O175: 0.00040454501 | P175: 0.0017621262 | Q175: 0.0023369701 | R175: 0.0026609527 | S175: 0.0030162422 | T175: 0.0034539563 | U175: 0.0012705165 | V175: 0.00054938175 | W175: 0.000652398 | X175: 0.00062827326 | Y175: 0.00033482541 | Z175: 0.00015534706 | AA175: 7.4331058e-05 | AB175: 0.00085241193 | AC175: 0.0010975961
A177: Fundo Soberano do Brasil | B177: 0 | C177: 0 | D177: 0 | E177: 0 | F177: 0 | G177: 0 | H177: 0 | I177: 0 | J177: 0 | K177: 0 | L177: 0 | M177: -0.0045803543 | N177: 0 | O177: 0 | P177: 0 | Q177: 0.0025754139 | R177: 0 | S177: 0 | T177: 0.00014260013 | U177: 0 | V177: 0 | W177: 0.00057408539 | X177: 0 | Y177: 0 | Z177: 0 | AA177: 0 | AB177: 0 | AC177: 0
A179: Memorando: | B179: 1997 | C179: 1998 | D179: 1999 | E179: 2000 | F179: 2001 | G179: 2002 | H179: 2003 | I179: 2004 | J179: 2005 | K179: 2006 | L179: 2007 | M179: 2008 | N179: 2009 | O179: 2010 | P179: 2011 | Q179: 2012 | R179: 2013 | S179: 2014 | T179: 2015 | U179: 2016 | V179: 2017 | W179: 2018 | X179: 2019 | Y179: 2020 | Z179: 2021 | AA179: 2022 | AB179: 2023 | AC179: 2024
A180: PIB Nominal (R$ Milhões) | B180: 952089.2 | C180: 1002351 | D180: 1087710.5 | E180: 1199092.1 | F180: 1315755.5 | G180: 1488787.3 | H180: 1717950.4 | I180: 1957751.2 | J180: 2170584.5 | K180: 2409449.9 | L180: 2720262.9 | M180: 3109803.1 | N180: 3333039.4 | O180: 3885847 | P180: 4376382 | Q180: 4814760 | R180: 5331619 | S180: 5778953 | T180: 5995787 | U180: 6269328 | V180: 6585479 | W180: 7004141 | X180: 7389131 | Y180: 7609597 | Z180: 9012142 | AA180: 10079677 | AB180: 10943345 | AC180: 11744710
A182: Obs.: Dados sujeitos à alteração.
A183: 1/ Apurado pelo conceito de caixa, que corresponde ao ingresso efetivo na Conta Única.
A184: 2/ Apurado pelo conceito de "pagamento efetivo", que corresponde ao valor do saque efetuado na Conta Única. A partir de 01/03/2012, inclui recursos de complementação do FGTS e despesas realizadas com recursos dessa contribuição (conforme previsto na Portaria STN nº 278, de 19/04/2012).
A185: 3/ Fonte: Ministério da Previdência Social. A apuração do resultado do RGPS por clientela urbana e rural é realizada pelo Ministério da Previdência Social segundo metodologia própria.
A186: 4/ Inclui retornos derivados de decisões judiciais relativas aos programas "Unificados Rurais" e "Unificados Industriais".
A187: 5/ Concessão de empréstimos menos retornos.
A188: 6/ Inclui "despesas" decorrentes da baixa de ativos associada a inscrição em Dívida Ativa da União.
A189: 7/ Operações de crédito direcionadas exclusivamente para a aquisição de bens e serviços de tecnologia assistiva destinados a pessoas com deficiência, nos termos da Lei nº 12.613/2012. Concessão de empréstimos menos retornos.
A190: 8/ Receitas referentes à devolução de diferencial de encargo, à atualização de devolução de equalização e de recuperação de despesas de exercícios anteriores.
A191: 9/ Recursos transitórios referentes à amortização de contratos de Itaipu com o Tesouro Nacional.
A192: 10/ Sistemática de registros nas estatísticas fiscais dos subsídios e subvenções estabelecida em conformidade com os Acórdãos nº 825/2015 e nº 3.297/2015 do TCU. Nesta nova sistemática, o BCB passou a incorporar mensalmente os efeitos fiscais desses eventos segundo o critério de competência na apuração abaixo da linha, enquanto que a STN registra semestralmente impactos quando dos pagamentos dos saldos apurados pelas instituições financeiras operadoras dos programas.
A193: 11/ Ajuste Metodológico referente ao ingresso de recursos do PIS/Pasep não reclamados por prazo superior a 20 (vinte) anos, nos termos do art. 121 do ADCT, com redação dada pela Emenda Constitucional nº 126/2022. Enquanto na metodologia acima da linha do Tesouro Nacional estes recursos se refletiram nas Demais Receitas Não Administradas pela RFB, afetando a estatística de resultado primário do Governo Central, na metodologia abaixo da linha tal operação foi definida como ajuste patrimonial, com efeito nulo sobre o resultado primário do Governo Central.
... A198: 16/ Os valores desta linha até o ano de 2019 não incluem os créditos extraordinários referentes ao Programa de Aceleração do Crescimento (PAC).

Sheet RTN-2.2
A1: Voltar
A2: Tabela 2.2 Resultado Primário do Governo Central - Brasil - Anual
A3: R$ Milhões - Valores Correntes
A5: Discriminação | B5: 1997 | C5: 1998 | D5: 1999 | E5: 2000 | F5: 2001 | G5: 2002 | H5: 2003 | I5: 2004 | J5: 2005 | K5: 2006 | L5: 2007 | M5: 2008 | N5: 2009 | O5: 2010 | P5: 2011 | Q5: 2012 | R5: 2013 | S5: 2014 | T5: 2015 | U5: 2016 | V5: 2017 | W5: 2018 | X5: 2019 | Y5: 2020 | Z5: 2021 | AA5: 2022 | AB5: 2023 | AC5: 2024
A6: 1. RECEITA TOTAL 1/ | B6: 159012.38 | C6: 183516.2 | D6: 209383.53 | E6: 235051.93 | F6: 270441.18 | G6: 320056.45 | H6: 356131.53 | I6: 418993.29 | J6: 487822.08 | K6: 542810.01 | L6: 618352.11 | M6: 715615.9 | N6: 738124.95 | O6: 918531.37 | P6: 988270.08 | Q6: 1072289.4 | R6: 1178983.2 | S6: 1221474.1 | T6: 1249103.7 | U6: 1315985.3 | V6: 1383653.1 | W6: 1488999.2 | X6: 1635607.9 | Y6: 1468096.1 | Z6: 1932649.7 | AA6: 2313305.4 | AB6: 2353432.2 | AC6: 2679441.6
A7: 1.1 - Receita Administrada pela RFB | B7: 101710.99 | C7: 111752.41 | D7: 134315.24 | E7: 156187.72 | F7: 179218.17 | G7: 219900.79 | H7: 242869.36 | I7: 286807.67 | J7: 333069.63 | K7: 359189.17 | L7: 417509.44 | M7: 466337.04 | N7: 456139.33 | O7: 531205.99 | P7: 628894.93 | Q7: 647535.06 | R7: 720193.37 | S7: 739178 | T7: 765137.18 | U7: 819751.85 | V7: 835563.54 | W7: 905052.42 | X7: 946082.86 | Y7: 899522.51 | Z7: 1195712.3 | AA7: 1390000.4 | AB7: 1439302.6 | AC7: 1690020.4
A8: 1.1.01 Imposto sobre a Importação | B8: 5135.2563 | C8: 6530.9529 | D8: 7861.0488 | E8: 8497.9762 | F8: 9079.0288 | G8: 7956.5665 | H8: 8134.7497 | I8: 9195.223 | J8: 9019.9464 | K8: 9978.3167 | L8: 12216.325 | M8: 17171.274 | N8: 15967.905 | O8: 21093.347 | P8: 26680.657 | Q8: 31067.554 | R8: 37138.715 | S8: 36563.277 | T8: 38942.28 | U8: 31390.478 | V8: 32426.49 | W8: 40678.353 | X8: 43035.297 | Y8: 45743.696 | Z8: 61970.275 | AA8: 59078.702 | AB8: 54221.997 | AC8: 77749.321
A9: 1.1.02 IPI | B9: 16552.739 | C9: 15824.031 | D9: 16084.688 | E9: 17700.492 | F9: 18939.451 | G9: 18622.865 | H9: 17874.788 | I9: 21294.335 | J9: 24451.572 | K9: 27385.117 | L9: 31875.674 | M9: 37361.124 | N9: 28086.369 | O9: 37553.815 | P9: 41471.406 | Q9: 44480.206 | R9: 44077.374 | S9: 50146.207 | T9: 48586.322 | U9: 42293.988 | V9: 48032.503 | W9: 55427.323 | X9: 52685.947 | Y9: 56694.554 | Z9: 71286.107 | AA9: 59893.538 | AB9: 59326.697 | AC9: 84373.243
A10: 1.1.02.1 IPI - Fumo | B10: 2839.2624 | C10: 2535.2212 | D10: 2280.4184 | E10: 1997.8234 | F10: 2006.8024 | G10: 1923.3734 | H10: 1993.5337 | I10: 2304.2955 | J10: 2302.7719 | K10: 2396.3534 | L10: 2803.3678 | M10: 3211.374 | N10: 3314.0706 | O10: 3705.4269 | P10: 3745.7164 | Q10: 4079.2769 | R10: 5098.504 | S10: 5654.1405 | T10: 5681.6727 | U10: 5718.4538 | V10: 5209.7982 | W10: 5207.8609 | X10: 5558.9395 | Y10: 5974.9635 | Z10: 5576.673 | AA10: 6732.0413 | AB10: 3824.4612 | AC10: 8160.5303
A11: 1.1.02.2 IPI - Bebidas | B11: 0 | C11: 0 | D11: 0 | E11: 1941.983 | F11: 2001.5399 | G11: 1795.3802 | H11: 1899.5308 | I11: 1998.8211 | J11: 2357.5864 | K11: 2626.4923 | L11: 2588.8312 | M11: 2489.3108 | N11: 2303.9952 | O11: 2430.0708 | P11: 2990.7066 | Q11: 3216.6361 | R11: 3438.0504 | S11: 3380.1102 | T11: 2594.3688 | U11: 2683.8977 | V11: 2943.8484 | W11: 2767.6274 | X11: 3640.9474 | Y11: 2985.1599 | Z11: 2687.4199 | AA11: 2513.2079 | AB11: 2954.045 | AC11: 3341.0842
A12: 1.1.02.3 IPI - Automóveis | B12: 0 | C12: 0 | D12: 0 | E12: 2374.8062 | F12: 2594.6402 | G12: 2663.9324 | H12: 2313.5748 | I12: 2964.0656 | J12: 3741.3046 | K12: 4303.9965 | L12: 5228.544 | M12: 6031.5478 | N12: 2097.271 | O12: 5786.3435 | P12: 7146.7862 | Q12: 4379.9063 | R12: 3776.7954 | S12: 4910.727 | T12: 4358.524 | U12: 3298.6589 | V12: 4466.9054 | W12: 5713.333 | X12: 5639.3939 | Y12: 3446.1674 | Z12: 3446.6948 | AA12: 4048.1888 | AB12: 6918.3597 | AC12: 8623.1572
A13: 1.1.02.4 IPI - Vinculado à importação | B13: 0 | C13: 0 | D13: 0 | E13: 4839.7277 | F13: 4752.4374 | G13: 4883.2022 | H13: 4562.4428 | I13: 5174.4588 | J13: 5278.0248 | K13: 6150.2824 | L13: 7692.364 | M13: 10351.067 | N13: 8384.3313 | O13: 11258.887 | P13: 13716.598 | Q13: 15929.681 | R13: 14624.077 | S13: 15079.093 | T13: 16802.394 | U13: 13451.634 | V13: 13996.587 | W13: 18000.707 | X13: 19110.255 | Y13: 21941.957 | Z13: 31693.283 | AA13: 24521.242 | AB13: 22608.433 | AC13: 29621.167
A14: 1.1.02.5 IPI - Outros | B14: 13713.477 | C14: 13288.809 | D14: 13804.27 | E14: 6546.1512 | F14: 7584.031 | G14: 7356.9773 | H14: 7105.7057 | I14: 8852.6941 | J14: 10771.885 | K14: 11907.992 | L14: 13562.567 | M14: 15277.825 | N14: 11986.701 | O14: 14373.087 | P14: 13871.599 | Q14: 16874.706 | R14: 17139.947 | S14: 21122.137 | T14: 19149.363 | U14: 17141.344 | V14: 21415.364 | W14: 23737.794 | X14: 18736.412 | Y14: 22346.305 | Z14: 27882.037 | AA14: 22078.859 | AB14: 23021.398 | AC14: 34627.304
A15: 1.1.03 Imposto sobre a Renda | B15: 34020.004 | C15: 42911.457 | D15: 47490.552 | E15: 51242.622 | F15: 60046.641 | G15: 78973.162 | H15: 83624.516 | I15: 92112.659 | J15: 115285.58 | K15: 125835.02 | L15: 148013.75 | M15: 179249.43 | N15: 178795.79 | O15: 194672.41 | P15: 235799.81 | Q15: 246653.32 | R15: 272592.3 | S15: 285684.34 | T15: 300442.46 | U15: 341115.25 | V15: 339840.91 | W15: 362757.27 | X15: 398366.46 | Y15: 384124.93 | Z15: 518525.12 | AA15: 667222.54 | AB15: 695762.5 | AC15: 785162.25
A16: 1.1.03.1 I.R. - Pessoa Física | B16: 2667.0555 | C16: 2844.2185 | D16: 3039.1824 | E16: 3615.102 | F16: 4019.7533 | G16: 4430.3253 | H16: 5078.9724 | I16: 6106.1163 | J16: 7304.1662 | K16: 8558.5881 | L16: 13710.112 | M16: 15047.689 | N16: 14808.253 | O16: 17309.448 | P16: 21855.091 | Q16: 24145.381 | R16: 26298.688 | S16: 27708.941 | T16: 28195.634 | U16: 30495.85 | V16: 32859.113 | W16: 34988.936 | X16: 39843.7 | Y16: 41655.641 | Z16: 56262.42 | AA16: 58188.515 | AB16: 58964.426 | AC16: 71023.576
... A164: 10. RESULTADO NOMINAL DO GOVERNO CENTRAL (8 + 9) 14/ | B164: -21307.03 | C164: -45099.997 | D164: -26336 | E164: -25016.43 | F164: -25273.239 | G164: -10029.15 | H164: -62152.541 | I164: -27033.334 | J164: -73284.006 | K164: -74475.046 | L164: -59606.985 | M164: -24890.758 | N164: -107363.19 | O164: -45785.487 | P164: -87517.572 | Q164: -61181.66 | R164: -110554.95 | S164: -271541.92 | T164: -513896 | U164: -477835.5 | V164: -459349.5 | W164: -426474.5 | X164: -399013.97 | Y164: -1011923.1 | Z164: -443154.41 | AA164: -448287.73 | AB164: -879080.85 | AC164: -900570.68
A166: Memorando
A167: Arrecadação Líquida para o RGPS | B167: 44260.757 | C167: 46283.802 | D167: 49065.284 | E167: 55715.134 | F167: 62491.89 | G167: 71027.679 | H167: 80730.15 | I167: 93765.382 | J167: 108434.1 | K167: 123520.19 | L167: 140411.79 | M167: 163355.27 | N167: 182008.44 | O167: 211968.38 | P167: 245891.94 | Q167: 275764.69 | R167: 307146.99 | S167: 337503.13 | T167: 350272 | U167: 358137.32 | V167: 374784.83 | W167: 391181.8 | X167: 413331.29 | Y167: 404772.51 | Z167: 462244.11 | AA167: 535709.9 | AB167: 592666.52 | AC167: 641155.48
A168: Arrecadação Ordinária | B168: 44260.757 | C168: 46283.802 | D168: 49065.284 | E168: 55715.134 | F168: 62491.89 | G168: 71027.679 | H168: 80730.15 | I168: 93765.382 | J168: 108434.1 | K168: 123520.19 | L168: 140411.79 | M168: 163355.27 | N168: 182008.44 | O168: 211968.38 | P168: 245891.94 | Q168: 273974.69 | R168: 298127.27 | S168: 319451.13 | T168: 324865.03 | U168: 340544.01 | V168: 360883.48 | W168: 377647.26 | X168: 403136.36 | Y168: 395365.3 | Z168: 454972.81 | AA168: 532613.81 | AB168: 592666.52 | AC168: 641155.48
A169: Compensação ao RGPS pelas Desonerações da Folha | B169: 0 | C169: 0 | D169: 0 | E169: 0 | F169: 0 | G169: 0 | H169: 0 | I169: 0 | J169: 0 | K169: 0 | L169: 0 | M169: 0 | N169: 0 | O169: 0 | P169: 0 | Q169: 1790 | R169: 9019.72 | S169: 18052 | T169: 25406.974 | U169: 17593.31 | V169: 13901.35 | W169: 13534.54 | X169: 10194.93 | Y169: 9407.21 | Z169: 7271.3 | AA169: 3096.09 | AB169: 0 | AC169: 0
A171: Custeio Administrativo | B171: 0 | C171: 0 | D171: 0 | E171: 0 | F171: 0 | G171: 0 | H171: 0 | I171: 0 | J171: 0 | K171: 0 | L171: 0 | M171: 0 | N171: 0 | O171: 0 | P171: 32645.83 | Q171: 35657.329 | R171: 37257.044 | S171: 41443.621 | T171: 42409.551 | U171: 49342.186 | V171: 44972.997 | W171: 46537.823 | X171: 46456.167 | Y171: 45132.609 | Z171: 45741.294 | AA171: 51931.794 | AB171: 57000.714 | AC171: 61376.535
A172: Investimento | B172: 0 | C172: 0 | D172: 0 | E172: 0 | F172: 0 | G172: 0 | H172: 0 | I172: 0 | J172: 0 | K172: 0 | L172: 0 | M172: 28105.824 | N172: 34008.274 | O172: 44741.218 | P172: 52630.672 | Q172: 59448.829 | R172: 63224.225 | S172: 77535.697 | T172: 55531.954 | U172: 64812.871 | V172: 45694.005 | W172: 53132.627 | X172: 56593.356 | Y172: 104904.5 | Z172: 56828.236 | AA172: 45054.646 | AB172: 81365.33 | AC172: 86102.105
A174: PAC 15/ | B174: 0 | C174: 0 | D174: 0 | E174: 0 | F174: 0 | G174: 0 | H174: 0 | I174: 0 | J174: 0 | K174: 0 | L174: 7340.0458 | M174: 11360.355 | N174: 17934.775 | O174: 22082.003 | P174: 28022.183 | Q174: 39306.916 | R174: 44714.81 | S174: 57698.04 | T174: 47259.258 | U174: 42042.739 | V174: 29598.034 | W174: 27595.644 | X174: 27080.981 | Y174: 0 | Z174: 0 | AA174: 0 | AB174: 0 | AC174: 0
A175: Minha Casa Minha Vida | B175: 0 | C175: 0 | D175: 0 | E175: 0 | F175: 0 | G175: 0 | H175: 0 | I175: 0 | J175: 0 | K175: 0 | L175: 0 | M175: 0 | N175: 1571.8584 | O175: 1572 | P175: 7711.7373 | Q175: 11251.95 | R175: 14187.186 | S175: 17430.722 | T175: 20709.186 | U175: 7965.2845 | V175: 3617.942 | W175: 4569.4876 | X175: 4642.3934 | Y175: 2547.8864 | Z175: 1400.0098 | AA175: 749.23303 | AB175: 9328.2376 | AC175: 12890.948
A177: Fundo Soberano do Brasil | B177: 0 | C177: 0 | D177: 0 | E177: 0 | F177: 0 | G177: 0 | H177: 0 | I177: 0 | J177: 0 | K177: 0 | L177: 0 | M177: -14244 | N177: 0 | O177: 0 | P177: 0 | Q177: 12400 | R177: 0 | S177: 0 | T177: 855 | U177: 0 | V177: 0 | W177: 4020.975 | X177: 0 | Y177: 0 | Z177: 0 | AA177: 0 | AB177: 0 | AC177: 0
A179: Obs.: Dados sujeitos à alteração.
A180: 1/ Apurado pelo conceito de caixa, que corresponde ao ingresso efetivo na Conta Única.
A181: 2/ Apurado pelo conceito de "pagamento efetivo", que corresponde ao valor do saque efetuado na Conta Única. A partir de 01/03/2012, inclui recursos de complementação do FGTS e despesas realizadas com recursos dessa contribuição (conforme previsto na Portaria STN nº 278, de 19/04/2012).
A182: 3/ Fonte: Ministério da Previdência Social. A apuração do resultado do RGPS por clientela urbana e rural é realizada pelo Ministério da Previdência Social segundo metodologia própria.
A183: 4/ Inclui retornos derivados de decisões judiciais relativas aos programas "Unificados Rurais" e "Unificados Industriais".
A184: 5/ Concessão de empréstimos menos retornos.
A185: 6/ Inclui "despesas" decorrentes da baixa de ativos associada a inscrição em Dívida Ativa da União.
A186: 7/ Operações de crédito direcionadas exclusivamente para a aquisição de bens e serviços de tecnologia assistiva destinados a pessoas com deficiência, nos termos da Lei nº 12.613/2012. Concessão de empréstimos menos retornos.
A187: 8/ Receitas referentes à devolução de diferencial de encargo, à atualização de devolução de equalização e de recuperação de despesas de exercícios anteriores.
A188: 9/ Recursos transitórios referentes à amortização de contratos de Itaipu com o Tesouro Nacional.
A189: 10/ Sistemática de registros nas estatísticas fiscais dos subsídios e subvenções estabelecida em conformidade com os Acórdãos nº 825/2015 e nº 3.297/2015 do TCU. Nesta nova sistemática, o BCB passou a incorporar mensalmente os efeitos fiscais desses eventos segundo o critério de competência na apuração abaixo da linha, enquanto que a STN registra semestralmente impactos quando dos pagamentos dos saldos apurados pelas instituições financeiras operadoras dos programas.
A190: 11/ Ajuste Metodológico referente ao ingresso de recursos do PIS/Pasep não reclamados por prazo superior a 20 (vinte) anos, nos termos do art. 121 do ADCT, com redação dada pela Emenda Constitucional nº 126/2022. Enquanto na metodologia acima da linha do Tesouro Nacional estes recursos se refletiram nas Demais Receitas Não Administradas pela RFB, afetando a estatística de resultado primário do Governo Central, na metodologia abaixo da linha tal operação foi definida como ajuste patrimonial, com efeito nulo sobre o resultado primário do Governo Central.
... A195: 16/ Os valores desta linha até o ano de 2019 não incluem os créditos extraordinários referentes ao Programa de Aceleração do Crescimento (PAC).

Sheet STN-RPF-Tabela 1
A2: Tabela 1 - Projeções fiscais para 10 anos - R$ bilhões correntes
A4: Discriminação | B4: 2024 | C4: 2025 | D4: 2026 | E4: 2027 | F4: 2028 | G4: 2029 | H4: 2030 | I4: 2031 | J4: 2032 | K4: 2033 | L4: 2034 | M4: 2035
A5: 1. RECEITA PRIMÁRIA TOTAL | B5: 2679.4416 | C5: 2929.9545 | D5: 3198.2822 | E5: 3419.5939 | F5: 3680.5094 | G5: 3952.2369 | H5: 4219.7073 | I5: 4510.938 | J5: 4807.327 | K5: 5010.8858 | L5: 5245.52 | M5: 5481.5865
A6: 1.1 - Receita Administrada pela RFB | B6: 1690.0204 | C6: 1878.2395 | D6: 2045.283 | E6: 2163.1185 | F6: 2273.0438 | G6: 2418.2671 | H6: 2590.032 | I6: 2790.5205 | J6: 2963.9643 | K6: 3155.9363 | L6: 3357.5254 | M6: 3560.2146
A7: 1.1.1 Imposto de Importação | B7: 77.749321 | C7: 92.451033 | D7: 99.184466 | E7: 107.22377 | F7: 116.58395 | G7: 126.88371 | H7: 139.11577 | I7: 153.62058 | J7: 170.36379 | K7: 189.33948 | L7: 210.93129 | M7: 235.1015
A8: 1.1.2 IPI | B8: 84.373243 | C8: 89.400886 | D8: 92.844612 | E8: 100.32259 | F8: 107.06289 | G8: 113.92718 | H8: 121.05728 | I8: 128.69358 | J8: 136.9579 | K8: 145.90015 | L8: 155.60218 | M8: 166.0187
A9: 1.1.2.1 IPI - Fumo | B9: 8.1605303 | C9: 11.689207 | D9: 10.36582 | E9: 10.282006 | F9: 10.208855 | G9: 10.15222 | H9: 10.637953 | I9: 11.146919 | J9: 11.680229 | K9: 12.239051 | L9: 12.824601 | M9: 13.438145
A10: 1.1.2.2 IPI - Bebidas | B10: 3.3410842 | C10: 3.5095345 | D10: 3.5482386 | E10: 3.6988712 | F10: 3.8338921 | G10: 3.9837321 | H10: 4.1065399 | I10: 4.2354528 | J10: 4.3683779 | K10: 4.5062752 | L10: 4.6492287 | M10: 4.7970946
A11: 1.1.2.3 IPI - Automóveis | B11: 8.6231572 | C11: 9.5605254 | D11: 10.184521 | E11: 10.466867 | F11: 10.944009 | G11: 11.299676 | H11: 11.958708 | I11: 12.645153 | J11: 13.377223 | K11: 14.156163 | L11: 14.984486 | M11: 15.861268
A12: 1.1.2.4 IPI - Vinculado a importação | B12: 29.621167 | C12: 31.936627 | D12: 34.830574 | E12: 37.665078 | F12: 40.872948 | G12: 44.206178 | H12: 47.580499 | I12: 51.265141 | J12: 55.356533 | K12: 59.891763 | L12: 64.939296 | M12: 70.447392
A13: 1.1.2.5 IPI - Outros | B13: 34.627304 | C13: 32.704992 | D13: 33.915459 | E13: 38.209772 | F13: 41.203187 | G13: 44.285376 | H13: 46.773585 | I13: 49.40091 | J13: 52.175537 | K13: 55.106894 | L13: 58.204565 | M13: 61.474797
A14: 1.1.3 Imposto de Renda | B14: 785.16225 | C14: 870.19515 | D14: 955.00881 | E14: 1001.205 | F14: 1044.3616 | G14: 1106.6811 | H14: 1193.5085 | I14: 1302.882 | J14: 1392.7148 | K14: 1490.6646 | L14: 1588.8739 | M14: 1693.1611
A15: 1.1.3.1 IR - Pessoa Física | B15: 71.023576 | C15: 75.183708 | D15: 79.654289 | E15: 85.601433 | F15: 86.4148 | G15: 89.004092 | H15: 96.474727 | I15: 131.75246 | J15: 139.9137 | K15: 149.91343 | L15: 160.31471 | M15: 170.40614
... A73: 14. DÍVIDA LÍQUIDA DO GOVERNO GERAL 4/ | B73: 7445.1597 | C73: 8588.9524 | D73: 9628.472 | E73: 10532.871 | F73: 11340.067 | G73: 12122.148 | H73: 12951.162 | I73: 13820.933 | J73: 14733.653 | K73: 15704.544 | L73: 16727.289 | M73: 17827.768
A74: Nota: Projeções consideram o Cenário de Referência do Relatório de Projeções Fiscais, que tem como premissa a adoção de medidas de receita para cumprimento das metas de resultado primário do PLDO 2026.
A75: 1/ Receitas líquidas adicionais necessárias para atingir as metas fiscais.
A76: 2/ Em 2024, as despesas são apresentadas pelo critério de pagamento efetivo.
A77: 3/ Inclui o resultado primário das empresas estatais regionais.
A78: 4/ Posição de dezembro de cada ano.
A80: Memorando | B80: 2024 | C80: 2025 | D80: 2026 | E80: 2027 | F80: 2028 | G80: 2029 | H80: 2030 | I80: 2031 | J80: 2032 | K80: 2033 | L80: 2034 | M80: 2035
A81: LIMITE DE GASTOS* | B81: 2105.2433 | C81: 2261.375 | D81: 2436.7787 | E81: 2590.3628 | F81: 2741.6788 | G81: 2896.2136 | H81: 3057.6775 | I81: 3228.143 | J81: 3408.112 | K81: 3598.1142 | L81: 3771.2842 | M81: 3919.3826
A82: Despesas sujeitas ao Limite** | B82: 2076.87 | C82: 2235.0774 | D82: 2427.1357 | E82: 2580.1409 | F82: 2730.878 | G82: 2884.7954 | H82: 3045.5861 | I82: 3215.339 | J82: 3394.5381 | K82: 3583.7184 | L82: 3756.0078 | M82: 3903.1738
A83: DESPESAS NÃO SUJEITAS AO LIMITE* | B83: 128.43481 | C83: 159.60114 | D83: 174.30647 | E83: 116.07838 | F83: 116.29741 | G83: 142.75458 | H83: 189.04596 | I83: 236.30431 | J83: 289.20687 | K83: 233.82144 | L83: 221.6332 | M83: 232.15171
A84: TAXAS IMPLÍCITAS DA DÍVIDA PÚBLICA
A85: Dívida líquida do setor público (% a.a.) | B85: 14.715022 | C85: 13.940922 | D85: 12.358109 | E85: 10.76367 | F85: 9.1710214 | G85: 8.6683012 | H85: 8.4528733 | I85: 8.315075 | J85: 8.2664904 | K85: 8.2754087 | L85: 8.1968345 | M85: 8.264667
A86: Dívida bruta do governo geral (% a.a.) | B86: 10.710417 | C86: 11.713776 | D86: 10.711364 | E86: 9.3039305 | F86: 8.0369048 | G86: 7.6051537 | H86: 7.4409441 | I86: 7.3181064 | J86: 7.2906406 | K86: 7.30977 | L86: 7.2592934 | M86: 7.2895715
A87: *Considera o limite de despesas da LC 200/2023.
A88: **A diferença entre o limite de despesa e as despesas sujeitas ao limite justifica-se pelo float, dado que o novo limite de despesas é orçamentário e as projeções do Relatório de Projeções Fiscais são financeiras.

Sheet BCB-DBGG-trimestral
A1: Fonte: Histórico BCB
B2: R$ Milhões | C2: % do PIB | D2: https://www.bcb.gov.br/content/estatisticas/Documents/Tabelas_especiais/Divggnp.xlsx
A3: 2008.I | B3: 1599048.5 | C3: 57.090623
A4: 2008.II | B4: 1612136.7 | C4: 55.595415
A5: 2008.III | B5: 1656166.5 | C5: 54.830469
A6: 2008.IV | B6: 1740887.8 | C6: 55.980645
A7: 2009.I | B7: 1812527.1 | C7: 57.469847
A8: 2009.II | B8: 1859801.5 | C8: 58.338895
A9: 2009.III | B9: 1962852.3 | C9: 60.80391
A10: 2009.IV | B10: 1973423.7 | C10: 59.207932
A11: 2010.I | B11: 1947898.9 | C11: 56.243857
A12: 2010.II | B12: 2010317.7 | C12: 55.78208
A13: 2010.III | B13: 2057909.4 | C13: 54.89268
A14: 2010.IV | B14: 2011521.7 | C14: 51.765334
... A72: 2025.II | B72: 9388792.9 | C72: 76.539459

Sheet BCB-DBGG-anual
A1: Fonte: Histórico BCB | C1: https://www.bcb.gov.br/content/estatisticas/Documents/Tabelas_especiais/Divggnp.xlsx
A2: Fonte: Projeções STN para o ARF-PLDO a parir de 2025
B3: R$ Milhões | C3: % do PIB
A4: 2008 | B4: 1740887.8 | C4: 55.980645
A5: 2009 | B5: 1973423.7 | C5: 59.207932
A6: 2010 | B6: 2011521.7 | C6: 51.765334
A7: 2011 | B7: 2243603.7 | C7: 51.266176
A8: 2012 | B8: 2583946.4 | C8: 53.667189
A9: 2013 | B9: 2747996.7 | C9: 51.541506
A10: 2014 | B10: 3252448.5 | C10: 56.280931
A11: 2015 | B11: 3927523.1 | C11: 65.504713
A12: 2016 | B12: 4378486.4 | C12: 69.839804
A13: 2017 | B13: 4854678.6 | C13: 73.717927
A14: 2018 | B14: 5271982.3 | C14: 75.269505
A15: 2019 | B15: 5500104.2 | C15: 74.435061
... A31: 2035 | B31: 21093735 | C31: 81.678704
